Workbook

Sheet Dashboard
B2: ANALIZADOR DE PUNTAJE CREDITICIO
B3: No Somos Ignorantes | v1.0 | Conoce, entiende y mejora tu puntaje
B5: TU PUNTAJE ESTIMADO
B6: =IFERROR(MAX(300,MIN(850,ROUND((C13*0.35+C14*0.30+C15*0.15+C16*0.10+C17*0.10)*5.5+300,0))),300) | D6: =IF(B6>=750,"EXCELENTE",IF(B6>=700,"MUY BUENO",IF(B6>=650,"BUENO",IF(B6>=550,"REGULAR",IF(B6>=450,"BAJO","MUY BAJO")))))
B7: 300 | C7: 450 | D7: 550 | E7: 650 | F7: 750 | G7: 850
B8: =IF(B6>=750,"Felicidades! Tienes un puntaje EXCELENTE. Mantelo!",IF(B6>=700,"Proximo nivel: EXCELENTE (750). Necesitas +"&TEXT(750-B6,"#,##0")&" puntos",IF(B6>=650,"Proximo nivel: MUY BUENO (700). Necesitas +"&TEXT(700-B6,"#,##0")&" puntos",IF(B6>=550,"Proximo nivel: BUENO (650). Necesitas +"&TEXT(650-B6,"#,##0")&" puntos","Proximo nivel: REGULAR (550). Necesitas +"&TEXT(550-B6,"#,##0")&" puntos"))))
B10: FACTORES QUE AFECTAN TU PUNTAJE (ingresa tu puntuacion 0-100)
B11: FACTOR | C11: TU PUNTAJE (0-100) | D11: PESO (%) | E11: CONTRIBUCION | F11: ESTADO
B13: Historial de Pagos (35%) | C13: 85 | D13: 0.35 | E13: =ROUND(C13*D13,1) | F13: =IF(C13>=80,"Excelente",IF(C13>=60,"Bueno",IF(C13>=40,"Mejorar","Critico")))
B14: Uso de Credito (30%) | C14: 60 | D14: 0.3 | E14: =ROUND(C14*D14,1) | F14: =IF(C14>=80,"Excelente",IF(C14>=60,"Bueno",IF(C14>=40,"Mejorar","Critico")))
B15: Antiguedad de Cuentas (15%) | C15: 75 | D15: 0.15 | E15: =ROUND(C15*D15,1) | F15: =IF(C15>=80,"Excelente",IF(C15>=60,"Bueno",IF(C15>=40,"Mejorar","Critico")))
B16: Tipos de Credito (10%) | C16: 70 | D16: 0.1 | E16: =ROUND(C16*D16,1) | F16: =IF(C16>=80,"Excelente",IF(C16>=60,"Bueno",IF(C16>=40,"Mejorar","Critico")))
B17: Consultas Recientes (10%) | C17: 45 | D17: 0.1 | E17: =ROUND(C17*D17,1) | F17: =IF(C17>=80,"Excelente",IF(C17>=60,"Bueno",IF(C17>=40,"Mejorar","Critico")))
B18: TOTAL PONDERADO | C18: =ROUND(SUMPRODUCT(C13:C17,D13:D17)/SUM(D13:D17),0) | D18: 1 | E18: =SUM(E13:E17)
B20: INTERPRETACION DEL PUNTAJE
B21: 750 - 850 | C21: EXCELENTE | D21: Acceso a las mejores tasas y condiciones de credito
B22: 700 - 749 | C22: MUY BUENO | D22: Buenas opciones de credito con tasas competitivas
B23: 650 - 699 | C23: BUENO | D23: Acceso a credito estandar, tasas promedio del mercado
B24: 550 - 649 | C24: REGULAR | D24: Opciones limitadas, tasas mas altas, posibles garantias
B25: 450 - 549 | C25: BAJO | D25: Dificultad para obtener credito, necesita mejorar
B26: 300 - 449 | C26: MUY BAJO | D26: Requiere reconstruir historial. Busca asesoramiento
B60: Factor | C60: Tu Puntaje | D60: Ideal
B61: Historial de Pagos | C61: =C13 | D61: 100
B62: Uso de Credito | C62: =C14 | D62: 100
B63: Antiguedad de Cuentas | C63: =C15 | D63: 100
B64: Tipos de Credito | C64: =C16 | D64: 100
B65: Consultas Recientes | C65: =C17 | D65: 100
B68: Factor | C68: Contribucion
B69: Historial de Pagos | C69: =E13
B70: Uso de Credito | C70: =E14
B71: Antiguedad de Cuentas | C71: =E15
B72: Tipos de Credito | C72: =E16
B73: Consultas Recientes | C73: =E17
B76: Factor | C76: Peso
B77: Historial de Pagos | C77: 0.35
B78: Uso de Credito | C78: 0.3
B79: Antiguedad de Cuentas | C79: 0.15
B80: Tipos de Credito | C80: 0.1
B81: Consultas Recientes | C81: 0.1

Sheet Historial
B2: HISTORIAL DE PAGOS
B3: Registra tus pagos de los ultimos 24 meses para calcular tu puntuacion
B5: RESUMEN DE PAGOS (ultimos 24 meses)
B6: METRICA | C6: CANTIDAD | D6: IMPACTO | E6: PUNTOS PERDIDOS
B7: Total de pagos realizados | C7: 24 | D7: Base del historial | E7: 0
B8: Pagos puntuales (a tiempo) | C8: 20 | D8: Factor positivo principal | E8: 0
B9: Pagos atrasados 1-30 dias | C9: 3 | D9: -10 puntos cada uno | E9: =C9*10
B10: Pagos atrasados 31-60 dias | C10: 1 | D10: -20 puntos cada uno | E10: =C10*20
B11: Pagos atrasados 61-90 dias | C11: 0 | D11: -40 puntos cada uno | E11: =C11*40
B12: Pagos atrasados 90+ dias | C12: 0 | D12: -50 puntos cada uno | E12: =C12*50
B13: Cuentas en cobranza | C13: 0 | D13: -30 puntos cada una | E13: =C13*30
B15: PUNTAJE HISTORIAL DE PAGOS | D15: =MAX(0,MIN(100,100-SUM(E9:E13)))
B16: Usa este puntaje en el Dashboard (factor: Historial de Pagos)
B18: CALCULADORA DE USO DE CREDITO
B19: TARJETA/LINEA | C19: LIMITE (Bs.) | D19: SALDO USADO (Bs.) | E19: USO (%) | F19: ESTADO
B20: Visa Clasica | C20: 15000 | D20: 4500 | E20: =IFERROR(IF(C20>0,D20/C20,0),0) | F20: =IF(C20=0,"",IF(E20<0.1,"Optimo",IF(E20<0.3,"Bueno",IF(E20<0.5,"Cuidado",IF(E20<0.75,"Alto","Critico")))))
B21: Mastercard Gold | C21: 30000 | D21: 12000 | E21: =IFERROR(IF(C21>0,D21/C21,0),0) | F21: =IF(C21=0,"",IF(E21<0.1,"Optimo",IF(E21<0.3,"Bueno",IF(E21<0.5,"Cuidado",IF(E21<0.75,"Alto","Critico")))))
B22: Linea de credito BNB | C22: 50000 | D22: 5000 | E22: =IFERROR(IF(C22>0,D22/C22,0),0) | F22: =IF(C22=0,"",IF(E22<0.1,"Optimo",IF(E22<0.3,"Bueno",IF(E22<0.5,"Cuidado",IF(E22<0.75,"Alto","Critico")))))
E23: =IFERROR(IF(C23>0,D23/C23,0),0) | F23: =IF(C23=0,"",IF(E23<0.1,"Optimo",IF(E23<0.3,"Bueno",IF(E23<0.5,"Cuidado",IF(E23<0.75,"Alto","Critico")))))
E24: =IFERROR(IF(C24>0,D24/C24,0),0) | F24: =IF(C24=0,"",IF(E24<0.1,"Optimo",IF(E24<0.3,"Bueno",IF(E24<0.5,"Cuidado",IF(E24<0.75,"Alto","Critico")))))
E25: =IFERROR(IF(C25>0,D25/C25,0),0) | F25: =IF(C25=0,"",IF(E25<0.1,"Optimo",IF(E25<0.3,"Bueno",IF(E25<0.5,"Cuidado",IF(E25<0.75,"Alto","Critico")))))
E26: =IFERROR(IF(C26>0,D26/C26,0),0) | F26: =IF(C26=0,"",IF(E26<0.1,"Optimo",IF(E26<0.3,"Bueno",IF(E26<0.5,"Cuidado",IF(E26<0.75,"Alto","Critico")))))
E27: =IFERROR(IF(C27>0,D27/C27,0),0) | F27: =IF(C27=0,"",IF(E27<0.1,"Optimo",IF(E27<0.3,"Bueno",IF(E27<0.5,"Cuidado",IF(E27<0.75,"Alto","Critico")))))
B28: TOTAL | C28: =SUM(C20:C27) | D28: =SUM(D20:D27) | E28: =IFERROR(D28/C28,0)
B30: PUNTAJE USO DE CREDITO | D30: =IF(E28<0.1,100,IF(E28<0.3,90,IF(E28<0.5,70,IF(E28<0.75,50,30))))
B31: Usa este puntaje en el Dashboard (factor: Uso de Credito)

Sheet Simulador
B2: SIMULADOR: QUE PASA SI...?
B3: Simula diferentes escenarios y ve como afectan tu puntaje
B5: ESCENARIOS DE MEJORA
B6: ESCENARIO | C6: PUNTAJE ACTUAL | D6: PUNTAJE NUEVO | E6: CAMBIO | F6: IMPACTO
B7: Pago todas las deudas atrasadas | C7: =Dashboard!B6 | D7: =IFERROR(MAX(300,MIN(850,ROUND((100*0.35+Dashboard!C14*0.30+Dashboard!C15*0.15+Dashboard!C16*0.10+Dashboard!C17*0.10)*5.5+300,0))),300) | E7: =D7-C7 | F7: =IF(E7>50,"ALTO IMPACTO",IF(E7>20,"IMPACTO MEDIO",IF(E7>0,"IMPACTO BAJO",IF(E7=0,"SIN CAMBIO","NEGATIVO"))))
B8: Reduzco uso de credito al 10% | C8: =Dashboard!B6 | D8: =IFERROR(MAX(300,MIN(850,ROUND((Dashboard!C13*0.35+100*0.30+Dashboard!C15*0.15+Dashboard!C16*0.10+Dashboard!C17*0.10)*5.5+300,0))),300) | E8: =D8-C8 | F8: =IF(E8>50,"ALTO IMPACTO",IF(E8>20,"IMPACTO MEDIO",IF(E8>0,"IMPACTO BAJO",IF(E8=0,"SIN CAMBIO","NEGATIVO"))))
B9: Mantengo cuentas por 5+ anios | C9: =Dashboard!B6 | D9: =IFERROR(MAX(300,MIN(850,ROUND((Dashboard!C13*0.35+Dashboard!C14*0.30+90*0.15+Dashboard!C16*0.10+Dashboard!C17*0.10)*5.5+300,0))),300) | E9: =D9-C9 | F9: =IF(E9>50,"ALTO IMPACTO",IF(E9>20,"IMPACTO MEDIO",IF(E9>0,"IMPACTO BAJO",IF(E9=0,"SIN CAMBIO","NEGATIVO"))))
B10: Agrego un tipo de credito nuevo | C10: =Dashboard!B6 | D10: =IFERROR(MAX(300,MIN(850,ROUND((Dashboard!C13*0.35+Dashboard!C14*0.30+Dashboard!C15*0.15+85*0.10+Dashboard!C17*0.10)*5.5+300,0))),300) | E10: =D10-C10 | F10: =IF(E10>50,"ALTO IMPACTO",IF(E10>20,"IMPACTO MEDIO",IF(E10>0,"IMPACTO BAJO",IF(E10=0,"SIN CAMBIO","NEGATIVO"))))
B11: No hago mas consultas por 6 meses | C11: =Dashboard!B6 | D11: =IFERROR(MAX(300,MIN(850,ROUND((Dashboard!C13*0.35+Dashboard!C14*0.30+Dashboard!C15*0.15+Dashboard!C16*0.10+80*0.10)*5.5+300,0))),300) | E11: =D11-C11 | F11: =IF(E11>50,"ALTO IMPACTO",IF(E11>20,"IMPACTO MEDIO",IF(E11>0,"IMPACTO BAJO",IF(E11=0,"SIN CAMBIO","NEGATIVO"))))
B12: ESCENARIO IDEAL (todo perfecto) | C12: =Dashboard!B6 | D12: =IFERROR(MAX(300,MIN(850,ROUND((100*0.35+100*0.30+100*0.15+100*0.10+100*0.10)*5.5+300,0))),300) | E12: =D12-C12 | F12: =IF(E12>50,"ALTO IMPACTO",IF(E12>20,"IMPACTO MEDIO",IF(E12>0,"IMPACTO BAJO",IF(E12=0,"SIN CAMBIO","NEGATIVO"))))
B13: PEOR CASO (todo critico) | C13: =Dashboard!B6 | D13: =IFERROR(MAX(300,MIN(850,ROUND((10*0.35+10*0.30+10*0.15+10*0.10+10*0.10)*5.5+300,0))),300) | E13: =D13-C13 | F13: =IF(E13>50,"ALTO IMPACTO",IF(E13>20,"IMPACTO MEDIO",IF(E13>0,"IMPACTO BAJO",IF(E13=0,"SIN CAMBIO","NEGATIVO"))))
B15: SIMULADOR PERSONALIZADO
B16: Ingresa los puntajes hipoteticos para cada factor y ve el resultado
B17: FACTOR | C17: ACTUAL | D17: SIMULADO | E17: DIFERENCIA
B18: Historial de Pagos | C18: =Dashboard!C13 | D18: 95 | E18: =D18-C18
B19: Uso de Credito | C19: =Dashboard!C14 | D19: 70 | E19: =D19-C19
B20: Antiguedad de Cuentas | C20: =Dashboard!C15 | D20: 85 | E20: =D20-C20
B21: Tipos de Credito | C21: =Dashboard!C16 | D21: 80 | E21: =D21-C21
B22: Consultas Recientes | C22: =Dashboard!C17 | D22: 55 | E22: =D22-C22
B24: PUNTAJE SIMULADO | D24: =IFERROR(MAX(300,MIN(850,ROUND((D18*0.35+D19*0.30+D20*0.15+D21*0.10+D22*0.10)*5.5+300,0))),300)
B25: VS ACTUAL: | D25: =D24-Dashboard!B6

Sheet Recomendaciones
B2: RECOMENDACIONES PERSONALIZADAS
B3: Acciones concretas basadas en tu perfil actual
B5: Historial de Pagos - Tu puntaje: | D5: =Dashboard!C13
B6: Accion 1 | C6: =IF(Dashboard!C13>=70,"Configura pagos automaticos para TODAS tus cuentas","Si tienes atrasos, paga al menos el minimo HOY")
B7: Accion 2 | C7: =IF(Dashboard!C13>=70,"Negocia eliminacion de atrasos menores con el banco","Establece alertas de pago 5 dias antes del vencimiento")
B8: Accion 3 | C8: =IF(Dashboard!C13>=70,"Un solo pago atrasado puede bajar 50+ puntos","Si no puedes pagar todo, paga el minimo para evitar reporte")
B10: Uso de Credito - Tu puntaje: | D10: =Dashboard!C14
B11: Accion 1 | C11: =IF(Dashboard!C14>=70,"Mantene tu uso por debajo del 30% del limite","Si usas mas del 50%, paga antes de la fecha de corte")
B12: Accion 2 | C12: =IF(Dashboard!C14>=70,"Pide aumento de limite (sin usarlo) para bajar el %","Distribuye gastos en varias tarjetas en vez de una")
B13: Accion 3 | C13: =IF(Dashboard!C14>=70,"El punto optimo es usar menos del 10% del limite","Paga 2 veces al mes para mantener el saldo bajo")
B15: Antiguedad - Tu puntaje: | D15: =Dashboard!C15
B16: Accion 1 | C16: =IF(Dashboard!C15>=70,"NO cierres tu tarjeta mas antigua, mantela activa","Usa tu tarjeta vieja al menos 1 vez al mes")
B17: Accion 2 | C17: =IF(Dashboard!C15>=70,"La antiguedad promedio ideal es 5+ anios","Abre cuentas nuevas solo cuando sea necesario")
B18: Accion 3 | C18: =IF(Dashboard!C15>=70,"Cada cuenta nueva baja tu promedio de antiguedad","Si necesitas una nueva tarjeta, conserva las viejas")
B20: Tipos de Credito - Tu puntaje: | D20: =Dashboard!C16
B21: Accion 1 | C21: =IF(Dashboard!C16>=70,"Ideal: 1 tarjeta + 1 prestamo + 1 linea de credito","No abras creditos solo por diversificar (ten un proposito)")
B22: Accion 2 | C22: =IF(Dashboard!C16>=70,"Los creditos hipotecarios suman mucho al mix","Un prestamo personal pequeno puede ayudar al mix")
B23: Accion 3 | C23: =IF(Dashboard!C16>=70,"Las tiendas con credito propio tambien cuentan","La variedad demuestra que manejas diferentes obligaciones")
B25: Consultas Recientes - Tu puntaje: | D25: =Dashboard!C17
B26: Accion 1 | C26: =IF(Dashboard!C17>=70,"Evita solicitar multiples creditos en poco tiempo","Cada consulta baja tu puntaje 5-10 puntos temporalmente")
B27: Accion 2 | C27: =IF(Dashboard!C17>=70,"Agrupa solicitudes del mismo tipo en 2 semanas","Las consultas se borran del reporte despues de 2 anios")
B28: Accion 3 | C28: =IF(Dashboard!C17>=70,"Consultar tu PROPIO reporte no afecta tu puntaje","Evita pre-aprobaciones que generan consultas duras")

Sheet Config
A1: CONFIGURACION
A3: Producto | B3: Analizador de Puntaje Crediticio
A4: Version | B4: v1.0.0
A5: Marca | B5: No Somos Ignorantes
A6: Precio | B6: Bs. 39
A7: Modelo | B7: Aproximacion buros bolivianos (educativo)
A8: Rango puntaje | B8: 300 - 850
A9: Factores | B9: 5 (Historial, Uso, Antiguedad, Mix, Consultas)
A10: Proteccion | B10: nsi2024
A11: Contacto | B11: nosomosignorantes@gmail.com
A14: INSTRUCCIONES DE USO
A15: 1. Ve al Dashboard e ingresa tu puntuacion estimada (0-100) para cada factor.
A16: 2. Usa la hoja 'Historial' para calcular tu puntaje exacto de pagos y uso de credito.
A17: 3. Copia los puntajes calculados al Dashboard para mayor precision.
A18: 4. Ve al 'Simulador' para explorar que pasaria si mejoras ciertos factores.
A19: 5. Revisa 'Recomendaciones' para acciones concretas basadas en tu perfil.
A21: COMO ESTIMAR CADA FACTOR (0-100):
A22: - Historial: 100 = nunca atrasado, -10 por cada atraso <30d, -20 por >30d
A23: - Uso credito: 100 = <10% usado, 90 = <30%, 70 = <50%, 50 = <75%, 30 = >75%
A24: - Antiguedad: 100 = >10 anios promedio, 80 = 5-10, 60 = 3-5, 40 = 1-3, 20 = <1
A25: - Mix: 100 = 4+ tipos (hipoteca, auto, tarjeta, personal), 50 = solo tarjetas
A26: - Consultas: 100 = 0 en 6 meses, 80 = 1-2, 60 = 3-4, 40 = 5+
... A30: NO es tu puntaje oficial. Para tu puntaje real, consulta tu buro de credito.
