Workbook

Sheet Dashboard
B2: COSTOS INDIRECTOS - PANEL EJECUTIVO
B3: No Somos Ignorantes | v1.0 | Asignacion de costos por producto
B5: TOTAL COSTOS INDIRECTOS (Bs.) | F5: TOTAL COSTOS DIRECTOS (Bs.)
B6: =IFERROR(SUM(CostosIndirectos!D4:D23),0) | F6: =IFERROR(SUM(Productos!D4:D18),0)
B8: % Costos Indirectos: | C8: =IFERROR(B6/(B6+F6),0) | F8: % Costos Directos: | G8: =IFERROR(F6/(B6+F6),0)
B10: TASA DE ASIGNACION | F10: COSTO TOTAL PROMEDIO (Bs.)
B11: =IFERROR(B6/SUM(BaseAsignacion!D4:D18),0) | F11: =IFERROR(AVERAGE(Productos!H4:H18),0)
B12: Bs. por unidad de base | F12: Costo directo + indirecto por producto
B14: COSTO TOTAL POR PRODUCTO | F14: DISTRIBUCION DE COSTOS INDIRECTOS
B15: Producto | C15: Costo Directo | D15: Costo Indirecto | F15: Concepto | G15: Monto (Bs.)
B16: =IFERROR(Productos!B4,"") | C16: =IFERROR(Productos!D4,0) | D16: =IFERROR(Productos!G4,0) | F16: =IFERROR(CostosIndirectos!B4,"") | G16: =IFERROR(CostosIndirectos!D4,0)
B17: =IFERROR(Productos!B5,"") | C17: =IFERROR(Productos!D5,0) | D17: =IFERROR(Productos!G5,0) | F17: =IFERROR(CostosIndirectos!B5,"") | G17: =IFERROR(CostosIndirectos!D5,0)
B18: =IFERROR(Productos!B6,"") | C18: =IFERROR(Productos!D6,0) | D18: =IFERROR(Productos!G6,0) | F18: =IFERROR(CostosIndirectos!B6,"") | G18: =IFERROR(CostosIndirectos!D6,0)
B19: =IFERROR(Productos!B7,"") | C19: =IFERROR(Productos!D7,0) | D19: =IFERROR(Productos!G7,0) | F19: =IFERROR(CostosIndirectos!B7,"") | G19: =IFERROR(CostosIndirectos!D7,0)
B20: =IFERROR(Productos!B8,"") | C20: =IFERROR(Productos!D8,0) | D20: =IFERROR(Productos!G8,0) | F20: =IFERROR(CostosIndirectos!B8,"") | G20: =IFERROR(CostosIndirectos!D8,0)
B21: =IFERROR(Productos!B9,"") | C21: =IFERROR(Productos!D9,0) | D21: =IFERROR(Productos!G9,0) | F21: =IFERROR(CostosIndirectos!B9,"") | G21: =IFERROR(CostosIndirectos!D9,0)
B22: =IFERROR(Productos!B10,"") | C22: =IFERROR(Productos!D10,0) | D22: =IFERROR(Productos!G10,0) | F22: =IFERROR(CostosIndirectos!B10,"") | G22: =IFERROR(CostosIndirectos!D10,0)
B23: =IFERROR(Productos!B11,"") | C23: =IFERROR(Productos!D11,0) | D23: =IFERROR(Productos!G11,0) | F23: =IFERROR(CostosIndirectos!B11,"") | G23: =IFERROR(CostosIndirectos!D11,0)
B24: =IFERROR(Productos!B12,"") | C24: =IFERROR(Productos!D12,0) | D24: =IFERROR(Productos!G12,0)
B25: =IFERROR(Productos!B13,"") | C25: =IFERROR(Productos!D13,0) | D25: =IFERROR(Productos!G13,0)
B26: =IFERROR(Productos!B14,"") | C26: =IFERROR(Productos!D14,0) | D26: =IFERROR(Productos!G14,0)
B27: =IFERROR(Productos!B15,"") | C27: =IFERROR(Productos!D15,0) | D27: =IFERROR(Productos!G15,0)
B28: =IFERROR(Productos!B16,"") | C28: =IFERROR(Productos!D16,0) | D28: =IFERROR(Productos!G16,0)
B29: =IFERROR(Productos!B17,"") | C29: =IFERROR(Productos!D17,0) | D29: =IFERROR(Productos!G17,0)
B30: =IFERROR(Productos!B18,"") | C30: =IFERROR(Productos!D18,0) | D30: =IFERROR(Productos!G18,0)

Sheet CostosIndirectos
A1: COSTOS INDIRECTOS DE FABRICACION
A2: Ingresa todos los costos indirectos del periodo. Se asignaran a productos segun la base elegida.
A3: # | B3: CONCEPTO | C3: TIPO | D3: MONTO (Bs.) | E3: % DEL TOTAL
A4: =IF(B4="","",ROW()-3) | B4: Alquiler de planta | C4: Alquiler | D4: 5000 | E4: =IFERROR(D4/SUM(D$4:D$23),0)
A5: =IF(B5="","",ROW()-3) | B5: Depreciacion maquinaria | C5: Depreciacion | D5: 3000 | E5: =IFERROR(D5/SUM(D$4:D$23),0)
A6: =IF(B6="","",ROW()-3) | B6: Electricidad fabrica | C6: Servicios | D6: 1200 | E6: =IFERROR(D6/SUM(D$4:D$23),0)
A7: =IF(B7="","",ROW()-3) | B7: Agua industrial | C7: Servicios | D7: 400 | E7: =IFERROR(D7/SUM(D$4:D$23),0)
A8: =IF(B8="","",ROW()-3) | B8: Seguro de planta | C8: Seguros | D8: 800 | E8: =IFERROR(D8/SUM(D$4:D$23),0)
A9: =IF(B9="","",ROW()-3) | B9: Mantenimiento equipos | C9: Mantenimiento | D9: 1500 | E9: =IFERROR(D9/SUM(D$4:D$23),0)
A10: =IF(B10="","",ROW()-3) | B10: Supervisor de produccion | C10: Supervision | D10: 4000 | E10: =IFERROR(D10/SUM(D$4:D$23),0)
A11: =IF(B11="","",ROW()-3) | B11: Material de limpieza | C11: Otros | D11: 300 | E11: =IFERROR(D11/SUM(D$4:D$23),0)
A12: =IF(B12="","",ROW()-3) | E12: =IFERROR(D12/SUM(D$4:D$23),0)
A13: =IF(B13="","",ROW()-3) | E13: =IFERROR(D13/SUM(D$4:D$23),0)
A14: =IF(B14="","",ROW()-3) | E14: =IFERROR(D14/SUM(D$4:D$23),0)
A15: =IF(B15="","",ROW()-3) | E15: =IFERROR(D15/SUM(D$4:D$23),0)
A16: =IF(B16="","",ROW()-3) | E16: =IFERROR(D16/SUM(D$4:D$23),0)
A17: =IF(B17="","",ROW()-3) | E17: =IFERROR(D17/SUM(D$4:D$23),0)
A18: =IF(B18="","",ROW()-3) | E18: =IFERROR(D18/SUM(D$4:D$23),0)
A19: =IF(B19="","",ROW()-3) | E19: =IFERROR(D19/SUM(D$4:D$23),0)
A20: =IF(B20="","",ROW()-3) | E20: =IFERROR(D20/SUM(D$4:D$23),0)
A21: =IF(B21="","",ROW()-3) | E21: =IFERROR(D21/SUM(D$4:D$23),0)
A22: =IF(B22="","",ROW()-3) | E22: =IFERROR(D22/SUM(D$4:D$23),0)
A23: =IF(B23="","",ROW()-3) | E23: =IFERROR(D23/SUM(D$4:D$23),0)
B24: TOTAL COSTOS INDIRECTOS | D24: =SUM(D4:D23)

Sheet BaseAsignacion
A1: BASE DE ASIGNACION
A2: Define la base para distribuir costos indirectos (horas maquina, horas MOD, unidades, etc.).
A3: Base: | B3: Horas Maquina
C4: =IFERROR(SUM(CostosIndirectos!D4:D23)/SUM(D6:D20),0)
A5: # | B5: PRODUCTO | C5: BASE ASIGNADA | D5: UNIDADES BASE | E5: % DEL TOTAL
A6: =IF(B6="","",ROW()-5) | B6: =IFERROR(Productos!B4,"") | C6: =$B$3 | D6: 100 | E6: =IFERROR(D6/SUM(D$6:D$20),0)
A7: =IF(B7="","",ROW()-5) | B7: =IFERROR(Productos!B5,"") | C7: =$B$3 | D7: 150 | E7: =IFERROR(D7/SUM(D$6:D$20),0)
A8: =IF(B8="","",ROW()-5) | B8: =IFERROR(Productos!B6,"") | C8: =$B$3 | D8: 80 | E8: =IFERROR(D8/SUM(D$6:D$20),0)
A9: =IF(B9="","",ROW()-5) | B9: =IFERROR(Productos!B7,"") | C9: =$B$3 | D9: 200 | E9: =IFERROR(D9/SUM(D$6:D$20),0)
A10: =IF(B10="","",ROW()-5) | B10: =IFERROR(Productos!B8,"") | C10: =$B$3 | D10: 120 | E10: =IFERROR(D10/SUM(D$6:D$20),0)
A11: =IF(B11="","",ROW()-5) | B11: =IFERROR(Productos!B9,"") | C11: =$B$3 | E11: =IFERROR(D11/SUM(D$6:D$20),0)
A12: =IF(B12="","",ROW()-5) | B12: =IFERROR(Productos!B10,"") | C12: =$B$3 | E12: =IFERROR(D12/SUM(D$6:D$20),0)
A13: =IF(B13="","",ROW()-5) | B13: =IFERROR(Productos!B11,"") | C13: =$B$3 | E13: =IFERROR(D13/SUM(D$6:D$20),0)
A14: =IF(B14="","",ROW()-5) | B14: =IFERROR(Productos!B12,"") | C14: =$B$3 | E14: =IFERROR(D14/SUM(D$6:D$20),0)
A15: =IF(B15="","",ROW()-5) | B15: =IFERROR(Productos!B13,"") | C15: =$B$3 | E15: =IFERROR(D15/SUM(D$6:D$20),0)
A16: =IF(B16="","",ROW()-5) | B16: =IFERROR(Productos!B14,"") | C16: =$B$3 | E16: =IFERROR(D16/SUM(D$6:D$20),0)
A17: =IF(B17="","",ROW()-5) | B17: =IFERROR(Productos!B15,"") | C17: =$B$3 | E17: =IFERROR(D17/SUM(D$6:D$20),0)
A18: =IF(B18="","",ROW()-5) | B18: =IFERROR(Productos!B16,"") | C18: =$B$3 | E18: =IFERROR(D18/SUM(D$6:D$20),0)
A19: =IF(B19="","",ROW()-5) | B19: =IFERROR(Productos!B17,"") | C19: =$B$3 | E19: =IFERROR(D19/SUM(D$6:D$20),0)
A20: =IF(B20="","",ROW()-5) | B20: =IFERROR(Productos!B18,"") | C20: =$B$3 | E20: =IFERROR(D20/SUM(D$6:D$20),0)
B21: TOTAL | D21: =SUM(D6:D20)

Sheet Productos
A1: COSTO TOTAL POR PRODUCTO
A2: El costo total = costo directo + costo indirecto asignado. Ingresa materiales y MOD por producto.
A3: # | B3: PRODUCTO | C3: UNIDADES | D3: COSTO DIRECTO (Bs.) | E3: COSTO DIRECTO UNIT. | F3: BASE ASIGN. | G3: COSTO INDIRECTO ASIGN. | H3: COSTO TOTAL (Bs.) | I3: COSTO UNIT. TOTAL
A4: =IF(B4="","",ROW()-3) | B4: Producto A - Basico | C4: 500 | D4: 15000 | E4: =IFERROR(D4/C4,0) | F4: =IFERROR(BaseAsignacion!D6,0) | G4: =IFERROR(F4*SUM(CostosIndirectos!D4:D23)/SUM(BaseAsignacion!D6:D20),0) | H4: =D4+G4 | I4: =IFERROR(H4/C4,0)
A5: =IF(B5="","",ROW()-3) | B5: Producto B - Intermedio | C5: 300 | D5: 12000 | E5: =IFERROR(D5/C5,0) | F5: =IFERROR(BaseAsignacion!D7,0) | G5: =IFERROR(F5*SUM(CostosIndirectos!D4:D23)/SUM(BaseAsignacion!D6:D20),0) | H5: =D5+G5 | I5: =IFERROR(H5/C5,0)
A6: =IF(B6="","",ROW()-3) | B6: Producto C - Premium | C6: 200 | D6: 20000 | E6: =IFERROR(D6/C6,0) | F6: =IFERROR(BaseAsignacion!D8,0) | G6: =IFERROR(F6*SUM(CostosIndirectos!D4:D23)/SUM(BaseAsignacion!D6:D20),0) | H6: =D6+G6 | I6: =IFERROR(H6/C6,0)
A7: =IF(B7="","",ROW()-3) | B7: Producto D - Especial | C7: 400 | D7: 18000 | E7: =IFERROR(D7/C7,0) | F7: =IFERROR(BaseAsignacion!D9,0) | G7: =IFERROR(F7*SUM(CostosIndirectos!D4:D23)/SUM(BaseAsignacion!D6:D20),0) | H7: =D7+G7 | I7: =IFERROR(H7/C7,0)
A8: =IF(B8="","",ROW()-3) | B8: Producto E - Economico | C8: 600 | D8: 10000 | E8: =IFERROR(D8/C8,0) | F8: =IFERROR(BaseAsignacion!D10,0) | G8: =IFERROR(F8*SUM(CostosIndirectos!D4:D23)/SUM(BaseAsignacion!D6:D20),0) | H8: =D8+G8 | I8: =IFERROR(H8/C8,0)
A9: =IF(B9="","",ROW()-3) | E9: =IFERROR(D9/C9,0) | F9: =IFERROR(BaseAsignacion!D11,0) | G9: =IFERROR(F9*SUM(CostosIndirectos!D4:D23)/SUM(BaseAsignacion!D6:D20),0) | H9: =D9+G9 | I9: =IFERROR(H9/C9,0)
A10: =IF(B10="","",ROW()-3) | E10: =IFERROR(D10/C10,0) | F10: =IFERROR(BaseAsignacion!D12,0) | G10: =IFERROR(F10*SUM(CostosIndirectos!D4:D23)/SUM(BaseAsignacion!D6:D20),0) | H10: =D10+G10 | I10: =IFERROR(H10/C10,0)
A11: =IF(B11="","",ROW()-3) | E11: =IFERROR(D11/C11,0) | F11: =IFERROR(BaseAsignacion!D13,0) | G11: =IFERROR(F11*SUM(CostosIndirectos!D4:D23)/SUM(BaseAsignacion!D6:D20),0) | H11: =D11+G11 | I11: =IFERROR(H11/C11,0)
A12: =IF(B12="","",ROW()-3) | E12: =IFERROR(D12/C12,0) | F12: =IFERROR(BaseAsignacion!D14,0) | G12: =IFERROR(F12*SUM(CostosIndirectos!D4:D23)/SUM(BaseAsignacion!D6:D20),0) | H12: =D12+G12 | I12: =IFERROR(H12/C12,0)
A13: =IF(B13="","",ROW()-3) | E13: =IFERROR(D13/C13,0) | F13: =IFERROR(BaseAsignacion!D15,0) | G13: =IFERROR(F13*SUM(CostosIndirectos!D4:D23)/SUM(BaseAsignacion!D6:D20),0) | H13: =D13+G13 | I13: =IFERROR(H13/C13,0)
A14: =IF(B14="","",ROW()-3) | E14: =IFERROR(D14/C14,0) | F14: =IFERROR(BaseAsignacion!D16,0) | G14: =IFERROR(F14*SUM(CostosIndirectos!D4:D23)/SUM(BaseAsignacion!D6:D20),0) | H14: =D14+G14 | I14: =IFERROR(H14/C14,0)
A15: =IF(B15="","",ROW()-3) | E15: =IFERROR(D15/C15,0) | F15: =IFERROR(BaseAsignacion!D17,0) | G15: =IFERROR(F15*SUM(CostosIndirectos!D4:D23)/SUM(BaseAsignacion!D6:D20),0) | H15: =D15+G15 | I15: =IFERROR(H15/C15,0)
A16: =IF(B16="","",ROW()-3) | E16: =IFERROR(D16/C16,0) | F16: =IFERROR(BaseAsignacion!D18,0) | G16: =IFERROR(F16*SUM(CostosIndirectos!D4:D23)/SUM(BaseAsignacion!D6:D20),0) | H16: =D16+G16 | I16: =IFERROR(H16/C16,0)
A17: =IF(B17="","",ROW()-3) | E17: =IFERROR(D17/C17,0) | F17: =IFERROR(BaseAsignacion!D19,0) | G17: =IFERROR(F17*SUM(CostosIndirectos!D4:D23)/SUM(BaseAsignacion!D6:D20),0) | H17: =D17+G17 | I17: =IFERROR(H17/C17,0)
A18: =IF(B18="","",ROW()-3) | E18: =IFERROR(D18/C18,0) | F18: =IFERROR(BaseAsignacion!D20,0) | G18: =IFERROR(F18*SUM(CostosIndirectos!D4:D23)/SUM(BaseAsignacion!D6:D20),0) | H18: =D18+G18 | I18: =IFERROR(H18/C18,0)
B19: TOTAL | C19: =SUM(C4:C18) | D19: =SUM(D4:D18) | G19: =SUM(G4:G18) | H19: =SUM(H4:H18)

Sheet Config
A1: v1.0.0
A3: CONFIGURACION
A5: Producto | B5: Calculadora de Costos Indirectos
A6: Version | B6: v1.0.0
A7: Marca | B7: No Somos Ignorantes
A8: Precio | B8: Bs. 69
A9: Proteccion | B9: nsi2024
A11: INSTRUCCIONES
A12: 1. | B12: En 'CostosIndirectos', registra todos los costos indirectos del periodo.
A13: 2. | B13: En 'BaseAsignacion', define las unidades base por producto (horas maquina, MOD, etc.).
A14: 3. | B14: En 'Productos', ingresa cada producto con su costo directo y unidades.
A15: 4. | B15: El sistema calcula automaticamente la tasa de asignacion y el costo total.
A16: 5. | B16: El Dashboard muestra KPIs y graficos de desglose de costos.
A17: 6. | B17: Para desbloquear: Revisar -> Desproteger hoja -> nsi2024
