Workbook

Sheet Dashboard
B2: FLUJO DE CAJA DUAL (Bs / USD)
B3: No Somos Ignorantes | v1.0 | Control de efectivo en dos monedas
B4: Tipo de Cambio (Bs/USD): | D4: 6.96
B6: SALDO EN BOLIVIANOS (Bs.) | F6: SALDO EN DOLARES (USD)
B7: =IFERROR(SUMPRODUCT((Flujo_BOB!D4:D203="Ingreso")*Flujo_BOB!E4:E203)-SUMPRODUCT((Flujo_BOB!D4:D203="Egreso")*Flujo_BOB!E4:E203),0) | F7: =IFERROR(SUMPRODUCT((Flujo_USD!D4:D203="Ingreso")*Flujo_USD!E4:E203)-SUMPRODUCT((Flujo_USD!D4:D203="Egreso")*Flujo_USD!E4:E203),0)
B9: SALDO TOTAL COMBINADO (Bs.) | F9: FLUJO NETO DEL MES (Bs.)
B10: =B7+(F7*D4) | F10: =IFERROR(SUMPRODUCT((MONTH(Flujo_BOB!A4:A203)=MONTH(TODAY()))*(YEAR(Flujo_BOB!A4:A203)=YEAR(TODAY()))*(Flujo_BOB!D4:D203="Ingreso")*Flujo_BOB!E4:E203)-SUMPRODUCT((MONTH(Flujo_BOB!A4:A203)=MONTH(TODAY()))*(YEAR(Flujo_BOB!A4:A203)=YEAR(TODAY()))*(Flujo_BOB!D4:D203="Egreso")*Flujo_BOB!E4:E203)+(SUMPRODUCT((MONTH(Flujo_USD!A4:A203)=MONTH(TODAY()))*(YEAR(Flujo_USD!A4:A203)=YEAR(TODAY()))*(Flujo_USD!D4:D203="Ingreso")*Flujo_USD!E4:E203)-SUMPRODUCT((MONTH(Flujo_USD!A4:A203)=MONTH(TODAY()))*(YEAR(Flujo_USD!A4:A203)=YEAR(TODAY()))*(Flujo_USD!D4:D203="Egreso")*Flujo_USD!E4:E203))*D4,0)
B12: FLUJO MENSUAL COMBINADO (Bs.) | F12: SALDO ACUMULADO
B13: Mes | C13: Ingresos Bs. | D13: Egresos Bs. | F13: Mes | G13: Saldo Bs. | H13: Saldo USD
B14: Ene | C14: =IFERROR(SUMPRODUCT((MONTH(Flujo_BOB!A4:A203)=1)*(YEAR(Flujo_BOB!A4:A203)=YEAR(TODAY()))*(Flujo_BOB!D4:D203="Ingreso")*Flujo_BOB!E4:E203)+SUMPRODUCT((MONTH(Flujo_USD!A4:A203)=1)*(YEAR(Flujo_USD!A4:A203)=YEAR(TODAY()))*(Flujo_USD!D4:D203="Ingreso")*Flujo_USD!E4:E203)*D4,0) | D14: =IFERROR(SUMPRODUCT((MONTH(Flujo_BOB!A4:A203)=1)*(YEAR(Flujo_BOB!A4:A203)=YEAR(TODAY()))*(Flujo_BOB!D4:D203="Egreso")*Flujo_BOB!E4:E203)+SUMPRODUCT((MONTH(Flujo_USD!A4:A203)=1)*(YEAR(Flujo_USD!A4:A203)=YEAR(TODAY()))*(Flujo_USD!D4:D203="Egreso")*Flujo_USD!E4:E203)*D4,0) | F14: Ene | G14: =IFERROR(SUMPRODUCT((MONTH(Flujo_BOB!A4:A203)=1)*(YEAR(Flujo_BOB!A4:A203)=YEAR(TODAY()))*IF(Flujo_BOB!D4:D203="Ingreso",1,-1)*Flujo_BOB!E4:E203),0) | H14: =IFERROR(SUMPRODUCT((MONTH(Flujo_USD!A4:A203)=1)*(YEAR(Flujo_USD!A4:A203)=YEAR(TODAY()))*IF(Flujo_USD!D4:D203="Ingreso",1,-1)*Flujo_USD!E4:E203),0)
B15: Feb | C15: =IFERROR(SUMPRODUCT((MONTH(Flujo_BOB!A4:A203)=2)*(YEAR(Flujo_BOB!A4:A203)=YEAR(TODAY()))*(Flujo_BOB!D4:D203="Ingreso")*Flujo_BOB!E4:E203)+SUMPRODUCT((MONTH(Flujo_USD!A4:A203)=2)*(YEAR(Flujo_USD!A4:A203)=YEAR(TODAY()))*(Flujo_USD!D4:D203="Ingreso")*Flujo_USD!E4:E203)*D4,0) | D15: =IFERROR(SUMPRODUCT((MONTH(Flujo_BOB!A4:A203)=2)*(YEAR(Flujo_BOB!A4:A203)=YEAR(TODAY()))*(Flujo_BOB!D4:D203="Egreso")*Flujo_BOB!E4:E203)+SUMPRODUCT((MONTH(Flujo_USD!A4:A203)=2)*(YEAR(Flujo_USD!A4:A203)=YEAR(TODAY()))*(Flujo_USD!D4:D203="Egreso")*Flujo_USD!E4:E203)*D4,0) | F15: Feb | G15: =IFERROR(SUMPRODUCT((MONTH(Flujo_BOB!A4:A203)=1)*(YEAR(Flujo_BOB!A4:A203)=YEAR(TODAY()))*IF(Flujo_BOB!D4:D203="Ingreso",1,-1)*Flujo_BOB!E4:E203)+SUMPRODUCT((MONTH(Flujo_BOB!A4:A203)=2)*(YEAR(Flujo_BOB!A4:A203)=YEAR(TODAY()))*IF(Flujo_BOB!D4:D203="Ingreso",1,-1)*Flujo_BOB!E4:E203),0) | H15: =IFERROR(SUMPRODUCT((MONTH(Flujo_USD!A4:A203)=1)*(YEAR(Flujo_USD!A4:A203)=YEAR(TODAY()))*IF(Flujo_USD!D4:D203="Ingreso",1,-1)*Flujo_USD!E4:E203)+SUMPRODUCT((MONTH(Flujo_USD!A4:A203)=2)*(YEAR(Flujo_USD!A4:A203)=YEAR(TODAY()))*IF(Flujo_USD!D4:D203="Ingreso",1,-1)*Flujo_USD!E4:E203),0)
B16: Mar | C16: =IFERROR(SUMPRODUCT((MONTH(Flujo_BOB!A4:A203)=3)*(YEAR(Flujo_BOB!A4:A203)=YEAR(TODAY()))*(Flujo_BOB!D4:D203="Ingreso")*Flujo_BOB!E4:E203)+SUMPRODUCT((MONTH(Flujo_USD!A4:A203)=3)*(YEAR(Flujo_USD!A4:A203)=YEAR(TODAY()))*(Flujo_USD!D4:D203="Ingreso")*Flujo_USD!E4:E203)*D4,0) | D16: =IFERROR(SUMPRODUCT((MONTH(Flujo_BOB!A4:A203)=3)*(YEAR(Flujo_BOB!A4:A203)=YEAR(TODAY()))*(Flujo_BOB!D4:D203="Egreso")*Flujo_BOB!E4:E203)+SUMPRODUCT((MONTH(Flujo_USD!A4:A203)=3)*(YEAR(Flujo_USD!A4:A203)=YEAR(TODAY()))*(Flujo_USD!D4:D203="Egreso")*Flujo_USD!E4:E203)*D4,0) | F16: Mar | G16: =IFERROR(SUMPRODUCT((MONTH(Flujo_BOB!A4:A203)=1)*(YEAR(Flujo_BOB!A4:A203)=YEAR(TODAY()))*IF(Flujo_BOB!D4:D203="Ingreso",1,-1)*Flujo_BOB!E4:E203)+SUMPRODUCT((MONTH(Flujo_BOB!A4:A203)=2)*(YEAR(Flujo_BOB!A4:A203)=YEAR(TODAY()))*IF(Flujo_BOB!D4:D203="Ingreso",1,-1)*Flujo_BOB!E4:E203)+SUMPRODUCT((MONTH(Flujo_BOB!A4:A203)=3)*(YEAR(Flujo_BOB!A4:A203)=YEAR(TODAY()))*IF(Flujo_BOB!D4:D203="Ingreso",1,-1)*Flujo_BOB!E4:E203),0) | H16: =IFERROR(SUMPRODUCT((MONTH(Flujo_USD!A4:A203)=1)*(YEAR(Flujo_USD!A4:A203)=YEAR(TODAY()))*IF(Flujo_USD!D4:D203="Ingreso",1,-1)*Flujo_USD!E4:E203)+SUMPRODUCT((MONTH(Flujo_USD!A4:A203)=2)*(YEAR(Flujo_USD!A4:A203)=YEAR(TODAY()))*IF(Flujo_USD!D4:D203="Ingreso",1,-1)*Flujo_USD!E4:E203)+SUMPRODUCT((MONTH(Flujo_USD!A4:A203)=3)*(YEAR(Flujo_USD!A4:A203)=YEAR(TODAY()))*IF(Flujo_USD!D4:D203="Ingreso",1,-1)*Flujo_USD!E4:E203),0)
B17: Abr | C17: =IFERROR(SUMPRODUCT((MONTH(Flujo_BOB!A4:A203)=4)*(YEAR(Flujo_BOB!A4:A203)=YEAR(TODAY()))*(Flujo_BOB!D4:D203="Ingreso")*Flujo_BOB!E4:E203)+SUMPRODUCT((MONTH(Flujo_USD!A4:A203)=4)*(YEAR(Flujo_USD!A4:A203)=YEAR(TODAY()))*(Flujo_USD!D4:D203="Ingreso")*Flujo_USD!E4:E203)*D4,0) | D17: =IFERROR(SUMPRODUCT((MONTH(Flujo_BOB!A4:A203)=4)*(YEAR(Flujo_BOB!A4:A203)=YEAR(TODAY()))*(Flujo_BOB!D4:D203="Egreso")*Flujo_BOB!E4:E203)+SUMPRODUCT((MONTH(Flujo_USD!A4:A203)=4)*(YEAR(Flujo_USD!A4:A203)=YEAR(TODAY()))*(Flujo_USD!D4:D203="Egreso")*Flujo_USD!E4:E203)*D4,0) | F17: Abr | G17: =IFERROR(SUMPRODUCT((MONTH(Flujo_BOB!A4:A203)=1)*(YEAR(Flujo_BOB!A4:A203)=YEAR(TODAY()))*IF(Flujo_BOB!D4:D203="Ingreso",1,-1)*Flujo_BOB!E4:E203)+SUMPRODUCT((MONTH(Flujo_BOB!A4:A203)=2)*(YEAR(Flujo_BOB!A4:A203)=YEAR(TODAY()))*IF(Flujo_BOB!D4:D203="Ingreso",1,-1)*Flujo_BOB!E4:E203)+SUMPRODUCT((MONTH(Flujo_BOB!A4:A203)=3)*(YEAR(Flujo_BOB!A4:A203)=YEAR(TODAY()))*IF(Flujo_BOB!D4:D203="Ingreso",1,-1)*Flujo_BOB!E4:E203)+SUMPRODUCT((MONTH(Flujo_BOB!A4:A203)=4)*(YEAR(Flujo_BOB!A4:A203)=YEAR(TODAY()))*IF(Flujo_BOB!D4:D203="Ingreso",1,-1)*Flujo_BOB!E4:E203),0) | H17: =IFERROR(SUMPRODUCT((MONTH(Flujo_USD!A4:A203)=1)*(YEAR(Flujo_USD!A4:A203)=YEAR(TODAY()))*IF(Flujo_USD!D4:D203="Ingreso",1,-1)*Flujo_USD!E4:E203)+SUMPRODUCT((MONTH(Flujo_USD!A4:A203)=2)*(YEAR(Flujo_USD!A4:A203)=YEAR(TODAY()))*IF(Flujo_USD!D4:D203="Ingreso",1,-1)*Flujo_USD!E4:E203)+SUMPRODUCT((MONTH(Flujo_USD!A4:A203)=3)*(YEAR(Flujo_USD!A4:A203)=YEAR(TODAY()))*IF(Flujo_USD!D4:D203="Ingreso",1,-1)*Flujo_USD!E4:E203)+SUMPRODUCT((MONTH(Flujo_USD!A4:A203)=4)*(YEAR(Flujo_USD!A4:A203)=YEAR(TODAY()))*IF(Flujo_USD!D4:D203="Ingreso",1,-1)*Flujo_USD!E4:E203),0)
B18: May | C18: =IFERROR(SUMPRODUCT((MONTH(Flujo_BOB!A4:A203)=5)*(YEAR(Flujo_BOB!A4:A203)=YEAR(TODAY()))*(Flujo_BOB!D4:D203="Ingreso")*Flujo_BOB!E4:E203)+SUMPRODUCT((MONTH(Flujo_USD!A4:A203)=5)*(YEAR(Flujo_USD!A4:A203)=YEAR(TODAY()))*(Flujo_USD!D4:D203="Ingreso")*Flujo_USD!E4:E203)*D4,0) | D18: =IFERROR(SUMPRODUCT((MONTH(Flujo_BOB!A4:A203)=5)*(YEAR(Flujo_BOB!A4:A203)=YEAR(TODAY()))*(Flujo_BOB!D4:D203="Egreso")*Flujo_BOB!E4:E203)+SUMPRODUCT((MONTH(Flujo_USD!A4:A203)=5)*(YEAR(Flujo_USD!A4:A203)=YEAR(TODAY()))*(Flujo_USD!D4:D203="Egreso")*Flujo_USD!E4:E203)*D4,0) | F18: May | G18: =IFERROR(SUMPRODUCT((MONTH(Flujo_BOB!A4:A203)=1)*(YEAR(Flujo_BOB!A4:A203)=YEAR(TODAY()))*IF(Flujo_BOB!D4:D203="Ingreso",1,-1)*Flujo_BOB!E4:E203)+SUMPRODUCT((MONTH(Flujo_BOB!A4:A203)=2)*(YEAR(Flujo_BOB!A4:A203)=YEAR(TODAY()))*IF(Flujo_BOB!D4:D203="Ingreso",1,-1)*Flujo_BOB!E4:E203)+SUMPRODUCT((MONTH(Flujo_BOB!A4:A203)=3)*(YEAR(Flujo_BOB!A4:A203)=YEAR(TODAY()))*IF(Flujo_BOB!D4:D203="Ingreso",1,-1)*Flujo_BOB!E4:E203)+SUMPRODUCT((MONTH(Flujo_BOB!A4:A203)=4)*(YEAR(Flujo_BOB!A4:A203)=YEAR(TODAY()))*IF(Flujo_BOB!D4:D203="Ingreso",1,-1)*Flujo_BOB!E4:E203)+SUMPRODUCT((MONTH(Flujo_BOB!A4:A203)=5)*(YEAR(Flujo_BOB!A4:A203)=YEAR(TODAY()))*IF(Flujo_BOB!D4:D203="Ingreso",1,-1)*Flujo_BOB!E4:E203),0) | H18: =IFERROR(SUMPRODUCT((MONTH(Flujo_USD!A4:A203)=1)*(YEAR(Flujo_USD!A4:A203)=YEAR(TODAY()))*IF(Flujo_USD!D4:D203="Ingreso",1,-1)*Flujo_USD!E4:E203)+SUMPRODUCT((MONTH(Flujo_USD!A4:A203)=2)*(YEAR(Flujo_USD!A4:A203)=YEAR(TODAY()))*IF(Flujo_USD!D4:D203="Ingreso",1,-1)*Flujo_USD!E4:E203)+SUMPRODUCT((MONTH(Flujo_USD!A4:A203)=3)*(YEAR(Flujo_USD!A4:A203)=YEAR(TODAY()))*IF(Flujo_USD!D4:D203="Ingreso",1,-1)*Flujo_USD!E4:E203)+SUMPRODUCT((MONTH(Flujo_USD!A4:A203)=4)*(YEAR(Flujo_USD!A4:A203)=YEAR(TODAY()))*IF(Flujo_USD!D4:D203="Ingreso",1,-1)*Flujo_USD!E4:E203)+SUMPRODUCT((MONTH(Flujo_USD!A4:A203)=5)*(YEAR(Flujo_USD!A4:A203)=YEAR(TODAY()))*IF(Flujo_USD!D4:D203="Ingreso",1,-1)*Flujo_USD!E4:E203),0)
B19: Jun | C19: =IFERROR(SUMPRODUCT((MONTH(Flujo_BOB!A4:A203)=6)*(YEAR(Flujo_BOB!A4:A203)=YEAR(TODAY()))*(Flujo_BOB!D4:D203="Ingreso")*Flujo_BOB!E4:E203)+SUMPRODUCT((MONTH(Flujo_USD!A4:A203)=6)*(YEAR(Flujo_USD!A4:A203)=YEAR(TODAY()))*(Flujo_USD!D4:D203="Ingreso")*Flujo_USD!E4:E203)*D4,0) | D19: =IFERROR(SUMPRODUCT((MONTH(Flujo_BOB!A4:A203)=6)*(YEAR(Flujo_BOB!A4:A203)=YEAR(TODAY()))*(Flujo_BOB!D4:D203="Egreso")*Flujo_BOB!E4:E203)+SUMPRODUCT((MONTH(Flujo_USD!A4:A203)=6)*(YEAR(Flujo_USD!A4:A203)=YEAR(TODAY()))*(Flujo_USD!D4:D203="Egreso")*Flujo_USD!E4:E203)*D4,0) | F19: Jun | G19: =IFERROR(SUMPRODUCT((MONTH(Flujo_BOB!A4:A203)=1)*(YEAR(Flujo_BOB!A4:A203)=YEAR(TODAY()))*IF(Flujo_BOB!D4:D203="Ingreso",1,-1)*Flujo_BOB!E4:E203)+SUMPRODUCT((MONTH(Flujo_BOB!A4:A203)=2)*(YEAR(Flujo_BOB!A4:A203)=YEAR(TODAY()))*IF(Flujo_BOB!D4:D203="Ingreso",1,-1)*Flujo_BOB!E4:E203)+SUMPRODUCT((MONTH(Flujo_BOB!A4:A203)=3)*(YEAR(Flujo_BOB!A4:A203)=YEAR(TODAY()))*IF(Flujo_BOB!D4:D203="Ingreso",1,-1)*Flujo_BOB!E4:E203)+SUMPRODUCT((MONTH(Flujo_BOB!A4:A203)=4)*(YEAR(Flujo_BOB!A4:A203)=YEAR(TODAY()))*IF(Flujo_BOB!D4:D203="Ingreso",1,-1)*Flujo_BOB!E4:E203)+SUMPRODUCT((MONTH(Flujo_BOB!A4:A203)=5)*(YEAR(Flujo_BOB!A4:A203)=YEAR(TODAY()))*IF(Flujo_BOB!D4:D203="Ingreso",1,-1)*Flujo_BOB!E4:E203)+SUMPRODUCT((MONTH(Flujo_BOB!A4:A203)=6)*(YEAR(Flujo_BOB!A4:A203)=YEAR(TODAY()))*IF(Flujo_BOB!D4:D203="Ingreso",1,-1)*Flujo_BOB!E4:E203),0) | H19: =IFERROR(SUMPRODUCT((MONTH(Flujo_USD!A4:A203)=1)*(YEAR(Flujo_USD!A4:A203)=YEAR(TODAY()))*IF(Flujo_USD!D4:D203="Ingreso",1,-1)*Flujo_USD!E4:E203)+SUMPRODUCT((MONTH(Flujo_USD!A4:A203)=2)*(YEAR(Flujo_USD!A4:A203)=YEAR(TODAY()))*IF(Flujo_USD!D4:D203="Ingreso",1,-1)*Flujo_USD!E4:E203)+SUMPRODUCT((MONTH(Flujo_USD!A4:A203)=3)*(YEAR(Flujo_USD!A4:A203)=YEAR(TODAY()))*IF(Flujo_USD!D4:D203="Ingreso",1,-1)*Flujo_USD!E4:E203)+SUMPRODUCT((MONTH(Flujo_USD!A4:A203)=4)*(YEAR(Flujo_USD!A4:A203)=YEAR(TODAY()))*IF(Flujo_USD!D4:D203="Ingreso",1,-1)*Flujo_USD!E4:E203)+SUMPRODUCT((MONTH(Flujo_USD!A4:A203)=5)*(YEAR(Flujo_USD!A4:A203)=YEAR(TODAY()))*IF(Flujo_USD!D4:D203="Ingreso",1,-1)*Flujo_USD!E4:E203)+SUMPRODUCT((MONTH(Flujo_USD!A4:A203)=6)*(YEAR(Flujo_USD!A4:A203)=YEAR(TODAY()))*IF(Flujo_USD!D4:D203="Ingreso",1,-1)*Flujo_USD!E4:E203),0)
B20: Jul | C20: =IFERROR(SUMPRODUCT((MONTH(Flujo_BOB!A4:A203)=7)*(YEAR(Flujo_BOB!A4:A203)=YEAR(TODAY()))*(Flujo_BOB!D4:D203="Ingreso")*Flujo_BOB!E4:E203)+SUMPRODUCT((MONTH(Flujo_USD!A4:A203)=7)*(YEAR(Flujo_USD!A4:A203)=YEAR(TODAY()))*(Flujo_USD!D4:D203="Ingreso")*Flujo_USD!E4:E203)*D4,0) | D20: =IFERROR(SUMPRODUCT((MONTH(Flujo_BOB!A4:A203)=7)*(YEAR(Flujo_BOB!A4:A203)=YEAR(TODAY()))*(Flujo_BOB!D4:D203="Egreso")*Flujo_BOB!E4:E203)+SUMPRODUCT((MONTH(Flujo_USD!A4:A203)=7)*(YEAR(Flujo_USD!A4:A203)=YEAR(TODAY()))*(Flujo_USD!D4:D203="Egreso")*Flujo_USD!E4:E203)*D4,0) | F20: Jul | G20: =IFERROR(SUMPRODUCT((MONTH(Flujo_BOB!A4:A203)=1)*(YEAR(Flujo_BOB!A4:A203)=YEAR(TODAY()))*IF(Flujo_BOB!D4:D203="Ingreso",1,-1)*Flujo_BOB!E4:E203)+SUMPRODUCT((MONTH(Flujo_BOB!A4:A203)=2)*(YEAR(Flujo_BOB!A4:A203)=YEAR(TODAY()))*IF(Flujo_BOB!D4:D203="Ingreso",1,-1)*Flujo_BOB!E4:E203)+SUMPRODUCT((MONTH(Flujo_BOB!A4:A203)=3)*(YEAR(Flujo_BOB!A4:A203)=YEAR(TODAY()))*IF(Flujo_BOB!D4:D203="Ingreso",1,-1)*Flujo_BOB!E4:E203)+SUMPRODUCT((MONTH(Flujo_BOB!A4:A203)=4)*(YEAR(Flujo_BOB!A4:A203)=YEAR(TODAY()))*IF(Flujo_BOB!D4:D203="Ingreso",1,-1)*Flujo_BOB!E4:E203)+SUMPRODUCT((MONTH(Flujo_BOB!A4:A203)=5)*(YEAR(Flujo_BOB!A4:A203)=YEAR(TODAY()))*IF(Flujo_BOB!D4:D203="Ingreso",1,-1)*Flujo_BOB!E4:E203)+SUMPRODUCT((MONTH(Flujo_BOB!A4:A203)=6)*(YEAR(Flujo_BOB!A4:A203)=YEAR(TODAY()))*IF(Flujo_BOB!D4:D203="Ingreso",1,-1)*Flujo_BOB!E4:E203)+SUMPRODUCT((MONTH(Flujo_BOB!A4:A203)=7)*(YEAR(Flujo_BOB!A4:A203)=YEAR(TODAY()))*IF(Flujo_BOB!D4:D203="Ingreso",1,-1)*Flujo_BOB!E4:E203),0) | H20: =IFERROR(SUMPRODUCT((MONTH(Flujo_USD!A4:A203)=1)*(YEAR(Flujo_USD!A4:A203)=YEAR(TODAY()))*IF(Flujo_USD!D4:D203="Ingreso",1,-1)*Flujo_USD!E4:E203)+SUMPRODUCT((MONTH(Flujo_USD!A4:A203)=2)*(YEAR(Flujo_USD!A4:A203)=YEAR(TODAY()))*IF(Flujo_USD!D4:D203="Ingreso",1,-1)*Flujo_USD!E4:E203)+SUMPRODUCT((MONTH(Flujo_USD!A4:A203)=3)*(YEAR(Flujo_USD!A4:A203)=YEAR(TODAY()))*IF(Flujo_USD!D4:D203="Ingreso",1,-1)*Flujo_USD!E4:E203)+SUMPRODUCT((MONTH(Flujo_USD!A4:A203)=4)*(YEAR(Flujo_USD!A4:A203)=YEAR(TODAY()))*IF(Flujo_USD!D4:D203="Ingreso",1,-1)*Flujo_USD!E4:E203)+SUMPRODUCT((MONTH(Flujo_USD!A4:A203)=5)*(YEAR(Flujo_USD!A4:A203)=YEAR(TODAY()))*IF(Flujo_USD!D4:D203="Ingreso",1,-1)*Flujo_USD!E4:E203)+SUMPRODUCT((MONTH(Flujo_USD!A4:A203)=6)*(YEAR(Flujo_USD!A4:A203)=YEAR(TODAY()))*IF(Flujo_USD!D4:D203="Ingreso",1,-1)*Flujo_USD!E4:E203)+SUMPRODUCT((MONTH(Flujo_USD!A4:A203)=7)*(YEAR(Flujo_USD!A4:A203)=YEAR(TODAY()))*IF(Flujo_USD!D4:D203="Ingreso",1,-1)*Flujo_USD!E4:E203),0)
B21: Ago | C21: =IFERROR(SUMPRODUCT((MONTH(Flujo_BOB!A4:A203)=8)*(YEAR(Flujo_BOB!A4:A203)=YEAR(TODAY()))*(Flujo_BOB!D4:D203="Ingreso")*Flujo_BOB!E4:E203)+SUMPRODUCT((MONTH(Flujo_USD!A4:A203)=8)*(YEAR(Flujo_USD!A4:A203)=YEAR(TODAY()))*(Flujo_USD!D4:D203="Ingreso")*Flujo_USD!E4:E203)*D4,0) | D21: =IFERROR(SUMPRODUCT((MONTH(Flujo_BOB!A4:A203)=8)*(YEAR(Flujo_BOB!A4:A203)=YEAR(TODAY()))*(Flujo_BOB!D4:D203="Egreso")*Flujo_BOB!E4:E203)+SUMPRODUCT((MONTH(Flujo_USD!A4:A203)=8)*(YEAR(Flujo_USD!A4:A203)=YEAR(TODAY()))*(Flujo_USD!D4:D203="Egreso")*Flujo_USD!E4:E203)*D4,0) | F21: Ago | G21: =IFERROR(SUMPRODUCT((MONTH(Flujo_BOB!A4:A203)=1)*(YEAR(Flujo_BOB!A4:A203)=YEAR(TODAY()))*IF(Flujo_BOB!D4:D203="Ingreso",1,-1)*Flujo_BOB!E4:E203)+SUMPRODUCT((MONTH(Flujo_BOB!A4:A203)=2)*(YEAR(Flujo_BOB!A4:A203)=YEAR(TODAY()))*IF(Flujo_BOB!D4:D203="Ingreso",1,-1)*Flujo_BOB!E4:E203)+SUMPRODUCT((MONTH(Flujo_BOB!A4:A203)=3)*(YEAR(Flujo_BOB!A4:A203)=YEAR(TODAY()))*IF(Flujo_BOB!D4:D203="Ingreso",1,-1)*Flujo_BOB!E4:E203)+SUMPRODUCT((MONTH(Flujo_BOB!A4:A203)=4)*(YEAR(Flujo_BOB!A4:A203)=YEAR(TODAY()))*IF(Flujo_BOB!D4:D203="Ingreso",1,-1)*Flujo_BOB!E4:E203)+SUMPRODUCT((MONTH(Flujo_BOB!A4:A203)=5)*(YEAR(Flujo_BOB!A4:A203)=YEAR(TODAY()))*IF(Flujo_BOB!D4:D203="Ingreso",1,-1)*Flujo_BOB!E4:E203)+SUMPRODUCT((MONTH(Flujo_BOB!A4:A203)=6)*(YEAR(Flujo_BOB!A4:A203)=YEAR(TODAY()))*IF(Flujo_BOB!D4:D203="Ingreso",1,-1)*Flujo_BOB!E4:E203)+SUMPRODUCT((MONTH(Flujo_BOB!A4:A203)=7)*(YEAR(Flujo_BOB!A4:A203)=YEAR(TODAY()))*IF(Flujo_BOB!D4:D203="Ingreso",1,-1)*Flujo_BOB!E4:E203)+SUMPRODUCT((MONTH(Flujo_BOB!A4:A203)=8)*(YEAR(Flujo_BOB!A4:A203)=YEAR(TODAY()))*IF(Flujo_BOB!D4:D203="Ingreso",1,-1)*Flujo_BOB!E4:E203),0) | H21: =IFERROR(SUMPRODUCT((MONTH(Flujo_USD!A4:A203)=1)*(YEAR(Flujo_USD!A4:A203)=YEAR(TODAY()))*IF(Flujo_USD!D4:D203="Ingreso",1,-1)*Flujo_USD!E4:E203)+SUMPRODUCT((MONTH(Flujo_USD!A4:A203)=2)*(YEAR(Flujo_USD!A4:A203)=YEAR(TODAY()))*IF(Flujo_USD!D4:D203="Ingreso",1,-1)*Flujo_USD!E4:E203)+SUMPRODUCT((MONTH(Flujo_USD!A4:A203)=3)*(YEAR(Flujo_USD!A4:A203)=YEAR(TODAY()))*IF(Flujo_USD!D4:D203="Ingreso",1,-1)*Flujo_USD!E4:E203)+SUMPRODUCT((MONTH(Flujo_USD!A4:A203)=4)*(YEAR(Flujo_USD!A4:A203)=YEAR(TODAY()))*IF(Flujo_USD!D4:D203="Ingreso",1,-1)*Flujo_USD!E4:E203)+SUMPRODUCT((MONTH(Flujo_USD!A4:A203)=5)*(YEAR(Flujo_USD!A4:A203)=YEAR(TODAY()))*IF(Flujo_USD!D4:D203="Ingreso",1,-1)*Flujo_USD!E4:E203)+SUMPRODUCT((MONTH(Flujo_USD!A4:A203)=6)*(YEAR(Flujo_USD!A4:A203)=YEAR(TODAY()))*IF(Flujo_USD!D4:D203="Ingreso",1,-1)*Flujo_USD!E4:E203)+SUMPRODUCT((MONTH(Flujo_USD!A4:A203)=7)*(YEAR(Flujo_USD!A4:A203)=YEAR(TODAY()))*IF(Flujo_USD!D4:D203="Ingreso",1,-1)*Flujo_USD!E4:E203)+SUMPRODUCT((MONTH(Flujo_USD!A4:A203)=8)*(YEAR(Flujo_USD!A4:A203)=YEAR(TODAY()))*IF(Flujo_USD!D4:D203="Ingreso",1,-1)*Flujo_USD!E4:E203),0)
B22: Sep | C22: =IFERROR(SUMPRODUCT((MONTH(Flujo_BOB!A4:A203)=9)*(YEAR(Flujo_BOB!A4:A203)=YEAR(TODAY()))*(Flujo_BOB!D4:D203="Ingreso")*Flujo_BOB!E4:E203)+SUMPRODUCT((MONTH(Flujo_USD!A4:A203)=9)*(YEAR(Flujo_USD!A4:A203)=YEAR(TODAY()))*(Flujo_USD!D4:D203="Ingreso")*Flujo_USD!E4:E203)*D4,0) | D22: =IFERROR(SUMPRODUCT((MONTH(Flujo_BOB!A4:A203)=9)*(YEAR(Flujo_BOB!A4:A203)=YEAR(TODAY()))*(Flujo_BOB!D4:D203="Egreso")*Flujo_BOB!E4:E203)+SUMPRODUCT((MONTH(Flujo_USD!A4:A203)=9)*(YEAR(Flujo_USD!A4:A203)=YEAR(TODAY()))*(Flujo_USD!D4:D203="Egreso")*Flujo_USD!E4:E203)*D4,0) | F22: Sep | G22: =IFERROR(SUMPRODUCT((MONTH(Flujo_BOB!A4:A203)=1)*(YEAR(Flujo_BOB!A4:A203)=YEAR(TODAY()))*IF(Flujo_BOB!D4:D203="Ingreso",1,-1)*Flujo_BOB!E4:E203)+SUMPRODUCT((MONTH(Flujo_BOB!A4:A203)=2)*(YEAR(Flujo_BOB!A4:A203)=YEAR(TODAY()))*IF(Flujo_BOB!D4:D203="Ingreso",1,-1)*Flujo_BOB!E4:E203)+SUMPRODUCT((MONTH(Flujo_BOB!A4:A203)=3)*(YEAR(Flujo_BOB!A4:A203)=YEAR(TODAY()))*IF(Flujo_BOB!D4:D203="Ingreso",1,-1)*Flujo_BOB!E4:E203)+SUMPRODUCT((MONTH(Flujo_BOB!A4:A203)=4)*(YEAR(Flujo_BOB!A4:A203)=YEAR(TODAY()))*IF(Flujo_BOB!D4:D203="Ingreso",1,-1)*Flujo_BOB!E4:E203)+SUMPRODUCT((MONTH(Flujo_BOB!A4:A203)=5)*(YEAR(Flujo_BOB!A4:A203)=YEAR(TODAY()))*IF(Flujo_BOB!D4:D203="Ingreso",1,-1)*Flujo_BOB!E4:E203)+SUMPRODUCT((MONTH(Flujo_BOB!A4:A203)=6)*(YEAR(Flujo_BOB!A4:A203)=YEAR(TODAY()))*IF(Flujo_BOB!D4:D203="Ingreso",1,-1)*Flujo_BOB!E4:E203)+SUMPRODUCT((MONTH(Flujo_BOB!A4:A203)=7)*(YEAR(Flujo_BOB!A4:A203)=YEAR(TODAY()))*IF(Flujo_BOB!D4:D203="Ingreso",1,-1)*Flujo_BOB!E4:E203)+SUMPRODUCT((MONTH(Flujo_BOB!A4:A203)=8)*(YEAR(Flujo_BOB!A4:A203)=YEAR(TODAY()))*IF(Flujo_BOB!D4:D203="Ingreso",1,-1)*Flujo_BOB!E4:E203)+SUMPRODUCT((MONTH(Flujo_BOB!A4:A203)=9)*(YEAR(Flujo_BOB!A4:A203)=YEAR(TODAY()))*IF(Flujo_BOB!D4:D203="Ingreso",1,-1)*Flujo_BOB!E4:E203),0) | H22: =IFERROR(SUMPRODUCT((MONTH(Flujo_USD!A4:A203)=1)*(YEAR(Flujo_USD!A4:A203)=YEAR(TODAY()))*IF(Flujo_USD!D4:D203="Ingreso",1,-1)*Flujo_USD!E4:E203)+SUMPRODUCT((MONTH(Flujo_USD!A4:A203)=2)*(YEAR(Flujo_USD!A4:A203)=YEAR(TODAY()))*IF(Flujo_USD!D4:D203="Ingreso",1,-1)*Flujo_USD!E4:E203)+SUMPRODUCT((MONTH(Flujo_USD!A4:A203)=3)*(YEAR(Flujo_USD!A4:A203)=YEAR(TODAY()))*IF(Flujo_USD!D4:D203="Ingreso",1,-1)*Flujo_USD!E4:E203)+SUMPRODUCT((MONTH(Flujo_USD!A4:A203)=4)*(YEAR(Flujo_USD!A4:A203)=YEAR(TODAY()))*IF(Flujo_USD!D4:D203="Ingreso",1,-1)*Flujo_USD!E4:E203)+SUMPRODUCT((MONTH(Flujo_USD!A4:A203)=5)*(YEAR(Flujo_USD!A4:A203)=YEAR(TODAY()))*IF(Flujo_USD!D4:D203="Ingreso",1,-1)*Flujo_USD!E4:E203)+SUMPRODUCT((MONTH(Flujo_USD!A4:A203)=6)*(YEAR(Flujo_USD!A4:A203)=YEAR(TODAY()))*IF(Flujo_USD!D4:D203="Ingreso",1,-1)*Flujo_USD!E4:E203)+SUMPRODUCT((MONTH(Flujo_USD!A4:A203)=7)*(YEAR(Flujo_USD!A4:A203)=YEAR(TODAY()))*IF(Flujo_USD!D4:D203="Ingreso",1,-1)*Flujo_USD!E4:E203)+SUMPRODUCT((MONTH(Flujo_USD!A4:A203)=8)*(YEAR(Flujo_USD!A4:A203)=YEAR(TODAY()))*IF(Flujo_USD!D4:D203="Ingreso",1,-1)*Flujo_USD!E4:E203)+SUMPRODUCT((MONTH(Flujo_USD!A4:A203)=9)*(YEAR(Flujo_USD!A4:A203)=YEAR(TODAY()))*IF(Flujo_USD!D4:D203="Ingreso",1,-1)*Flujo_USD!E4:E203),0)
B23: Oct | C23: =IFERROR(SUMPRODUCT((MONTH(Flujo_BOB!A4:A203)=10)*(YEAR(Flujo_BOB!A4:A203)=YEAR(TODAY()))*(Flujo_BOB!D4:D203="Ingreso")*Flujo_BOB!E4:E203)+SUMPRODUCT((MONTH(Flujo_USD!A4:A203)=10)*(YEAR(Flujo_USD!A4:A203)=YEAR(TODAY()))*(Flujo_USD!D4:D203="Ingreso")*Flujo_USD!E4:E203)*D4,0) | D23: =IFERROR(SUMPRODUCT((MONTH(Flujo_BOB!A4:A203)=10)*(YEAR(Flujo_BOB!A4:A203)=YEAR(TODAY()))*(Flujo_BOB!D4:D203="Egreso")*Flujo_BOB!E4:E203)+SUMPRODUCT((MONTH(Flujo_USD!A4:A203)=10)*(YEAR(Flujo_USD!A4:A203)=YEAR(TODAY()))*(Flujo_USD!D4:D203="Egreso")*Flujo_USD!E4:E203)*D4,0) | F23: Oct | G23: =IFERROR(SUMPRODUCT((MONTH(Flujo_BOB!A4:A203)=1)*(YEAR(Flujo_BOB!A4:A203)=YEAR(TODAY()))*IF(Flujo_BOB!D4:D203="Ingreso",1,-1)*Flujo_BOB!E4:E203)+SUMPRODUCT((MONTH(Flujo_BOB!A4:A203)=2)*(YEAR(Flujo_BOB!A4:A203)=YEAR(TODAY()))*IF(Flujo_BOB!D4:D203="Ingreso",1,-1)*Flujo_BOB!E4:E203)+SUMPRODUCT((MONTH(Flujo_BOB!A4:A203)=3)*(YEAR(Flujo_BOB!A4:A203)=YEAR(TODAY()))*IF(Flujo_BOB!D4:D203="Ingreso",1,-1)*Flujo_BOB!E4:E203)+SUMPRODUCT((MONTH(Flujo_BOB!A4:A203)=4)*(YEAR(Flujo_BOB!A4:A203)=YEAR(TODAY()))*IF(Flujo_BOB!D4:D203="Ingreso",1,-1)*Flujo_BOB!E4:E203)+SUMPRODUCT((MONTH(Flujo_BOB!A4:A203)=5)*(YEAR(Flujo_BOB!A4:A203)=YEAR(TODAY()))*IF(Flujo_BOB!D4:D203="Ingreso",1,-1)*Flujo_BOB!E4:E203)+SUMPRODUCT((MONTH(Flujo_BOB!A4:A203)=6)*(YEAR(Flujo_BOB!A4:A203)=YEAR(TODAY()))*IF(Flujo_BOB!D4:D203="Ingreso",1,-1)*Flujo_BOB!E4:E203)+SUMPRODUCT((MONTH(Flujo_BOB!A4:A203)=7)*(YEAR(Flujo_BOB!A4:A203)=YEAR(TODAY()))*IF(Flujo_BOB!D4:D203="Ingreso",1,-1)*Flujo_BOB!E4:E203)+SUMPRODUCT((MONTH(Flujo_BOB!A4:A203)=8)*(YEAR(Flujo_BOB!A4:A203)=YEAR(TODAY()))*IF(Flujo_BOB!D4:D203="Ingreso",1,-1)*Flujo_BOB!E4:E203)+SUMPRODUCT((MONTH(Flujo_BOB!A4:A203)=9)*(YEAR(Flujo_BOB!A4:A203)=YEAR(TODAY()))*IF(Flujo_BOB!D4:D203="Ingreso",1,-1)*Flujo_BOB!E4:E203)+SUMPRODUCT((MONTH(Flujo_BOB!A4:A203)=10)*(YEAR(Flujo_BOB!A4:A203)=YEAR(TODAY()))*IF(Flujo_BOB!D4:D203="Ingreso",1,-1)*Flujo_BOB!E4:E203),0) | H23: =IFERROR(SUMPRODUCT((MONTH(Flujo_USD!A4:A203)=1)*(YEAR(Flujo_USD!A4:A203)=YEAR(TODAY()))*IF(Flujo_USD!D4:D203="Ingreso",1,-1)*Flujo_USD!E4:E203)+SUMPRODUCT((MONTH(Flujo_USD!A4:A203)=2)*(YEAR(Flujo_USD!A4:A203)=YEAR(TODAY()))*IF(Flujo_USD!D4:D203="Ingreso",1,-1)*Flujo_USD!E4:E203)+SUMPRODUCT((MONTH(Flujo_USD!A4:A203)=3)*(YEAR(Flujo_USD!A4:A203)=YEAR(TODAY()))*IF(Flujo_USD!D4:D203="Ingreso",1,-1)*Flujo_USD!E4:E203)+SUMPRODUCT((MONTH(Flujo_USD!A4:A203)=4)*(YEAR(Flujo_USD!A4:A203)=YEAR(TODAY()))*IF(Flujo_USD!D4:D203="Ingreso",1,-1)*Flujo_USD!E4:E203)+SUMPRODUCT((MONTH(Flujo_USD!A4:A203)=5)*(YEAR(Flujo_USD!A4:A203)=YEAR(TODAY()))*IF(Flujo_USD!D4:D203="Ingreso",1,-1)*Flujo_USD!E4:E203)+SUMPRODUCT((MONTH(Flujo_USD!A4:A203)=6)*(YEAR(Flujo_USD!A4:A203)=YEAR(TODAY()))*IF(Flujo_USD!D4:D203="Ingreso",1,-1)*Flujo_USD!E4:E203)+SUMPRODUCT((MONTH(Flujo_USD!A4:A203)=7)*(YEAR(Flujo_USD!A4:A203)=YEAR(TODAY()))*IF(Flujo_USD!D4:D203="Ingreso",1,-1)*Flujo_USD!E4:E203)+SUMPRODUCT((MONTH(Flujo_USD!A4:A203)=8)*(YEAR(Flujo_USD!A4:A203)=YEAR(TODAY()))*IF(Flujo_USD!D4:D203="Ingreso",1,-1)*Flujo_USD!E4:E203)+SUMPRODUCT((MONTH(Flujo_USD!A4:A203)=9)*(YEAR(Flujo_USD!A4:A203)=YEAR(TODAY()))*IF(Flujo_USD!D4:D203="Ingreso",1,-1)*Flujo_USD!E4:E203)+SUMPRODUCT((MONTH(Flujo_USD!A4:A203)=10)*(YEAR(Flujo_USD!A4:A203)=YEAR(TODAY()))*IF(Flujo_USD!D4:D203="Ingreso",1,-1)*Flujo_USD!E4:E203),0)
B24: Nov | C24: =IFERROR(SUMPRODUCT((MONTH(Flujo_BOB!A4:A203)=11)*(YEAR(Flujo_BOB!A4:A203)=YEAR(TODAY()))*(Flujo_BOB!D4:D203="Ingreso")*Flujo_BOB!E4:E203)+SUMPRODUCT((MONTH(Flujo_USD!A4:A203)=11)*(YEAR(Flujo_USD!A4:A203)=YEAR(TODAY()))*(Flujo_USD!D4:D203="Ingreso")*Flujo_USD!E4:E203)*D4,0) | D24: =IFERROR(SUMPRODUCT((MONTH(Flujo_BOB!A4:A203)=11)*(YEAR(Flujo_BOB!A4:A203)=YEAR(TODAY()))*(Flujo_BOB!D4:D203="Egreso")*Flujo_BOB!E4:E203)+SUMPRODUCT((MONTH(Flujo_USD!A4:A203)=11)*(YEAR(Flujo_USD!A4:A203)=YEAR(TODAY()))*(Flujo_USD!D4:D203="Egreso")*Flujo_USD!E4:E203)*D4,0) | F24: Nov | G24: =IFERROR(SUMPRODUCT((MONTH(Flujo_BOB!A4:A203)=1)*(YEAR(Flujo_BOB!A4:A203)=YEAR(TODAY()))*IF(Flujo_BOB!D4:D203="Ingreso",1,-1)*Flujo_BOB!E4:E203)+SUMPRODUCT((MONTH(Flujo_BOB!A4:A203)=2)*(YEAR(Flujo_BOB!A4:A203)=YEAR(TODAY()))*IF(Flujo_BOB!D4:D203="Ingreso",1,-1)*Flujo_BOB!E4:E203)+SUMPRODUCT((MONTH(Flujo_BOB!A4:A203)=3)*(YEAR(Flujo_BOB!A4:A203)=YEAR(TODAY()))*IF(Flujo_BOB!D4:D203="Ingreso",1,-1)*Flujo_BOB!E4:E203)+SUMPRODUCT((MONTH(Flujo_BOB!A4:A203)=4)*(YEAR(Flujo_BOB!A4:A203)=YEAR(TODAY()))*IF(Flujo_BOB!D4:D203="Ingreso",1,-1)*Flujo_BOB!E4:E203)+SUMPRODUCT((MONTH(Flujo_BOB!A4:A203)=5)*(YEAR(Flujo_BOB!A4:A203)=YEAR(TODAY()))*IF(Flujo_BOB!D4:D203="Ingreso",1,-1)*Flujo_BOB!E4:E203)+SUMPRODUCT((MONTH(Flujo_BOB!A4:A203)=6)*(YEAR(Flujo_BOB!A4:A203)=YEAR(TODAY()))*IF(Flujo_BOB!D4:D203="Ingreso",1,-1)*Flujo_BOB!E4:E203)+SUMPRODUCT((MONTH(Flujo_BOB!A4:A203)=7)*(YEAR(Flujo_BOB!A4:A203)=YEAR(TODAY()))*IF(Flujo_BOB!D4:D203="Ingreso",1,-1)*Flujo_BOB!E4:E203)+SUMPRODUCT((MONTH(Flujo_BOB!A4:A203)=8)*(YEAR(Flujo_BOB!A4:A203)=YEAR(TODAY()))*IF(Flujo_BOB!D4:D203="Ingreso",1,-1)*Flujo_BOB!E4:E203)+SUMPRODUCT((MONTH(Flujo_BOB!A4:A203)=9)*(YEAR(Flujo_BOB!A4:A203)=YEAR(TODAY()))*IF(Flujo_BOB!D4:D203="Ingreso",1,-1)*Flujo_BOB!E4:E203)+SUMPRODUCT((MONTH(Flujo_BOB!A4:A203)=10)*(YEAR(Flujo_BOB!A4:A203)=YEAR(TODAY()))*IF(Flujo_BOB!D4:D203="Ingreso",1,-1)*Flujo_BOB!E4:E203)+SUMPRODUCT((MONTH(Flujo_BOB!A4:A203)=11)*(YEAR(Flujo_BOB!A4:A203)=YEAR(TODAY()))*IF(Flujo_BOB!D4:D203="Ingreso",1,-1)*Flujo_BOB!E4:E203),0) | H24: =IFERROR(SUMPRODUCT((MONTH(Flujo_USD!A4:A203)=1)*(YEAR(Flujo_USD!A4:A203)=YEAR(TODAY()))*IF(Flujo_USD!D4:D203="Ingreso",1,-1)*Flujo_USD!E4:E203)+SUMPRODUCT((MONTH(Flujo_USD!A4:A203)=2)*(YEAR(Flujo_USD!A4:A203)=YEAR(TODAY()))*IF(Flujo_USD!D4:D203="Ingreso",1,-1)*Flujo_USD!E4:E203)+SUMPRODUCT((MONTH(Flujo_USD!A4:A203)=3)*(YEAR(Flujo_USD!A4:A203)=YEAR(TODAY()))*IF(Flujo_USD!D4:D203="Ingreso",1,-1)*Flujo_USD!E4:E203)+SUMPRODUCT((MONTH(Flujo_USD!A4:A203)=4)*(YEAR(Flujo_USD!A4:A203)=YEAR(TODAY()))*IF(Flujo_USD!D4:D203="Ingreso",1,-1)*Flujo_USD!E4:E203)+SUMPRODUCT((MONTH(Flujo_USD!A4:A203)=5)*(YEAR(Flujo_USD!A4:A203)=YEAR(TODAY()))*IF(Flujo_USD!D4:D203="Ingreso",1,-1)*Flujo_USD!E4:E203)+SUMPRODUCT((MONTH(Flujo_USD!A4:A203)=6)*(YEAR(Flujo_USD!A4:A203)=YEAR(TODAY()))*IF(Flujo_USD!D4:D203="Ingreso",1,-1)*Flujo_USD!E4:E203)+SUMPRODUCT((MONTH(Flujo_USD!A4:A203)=7)*(YEAR(Flujo_USD!A4:A203)=YEAR(TODAY()))*IF(Flujo_USD!D4:D203="Ingreso",1,-1)*Flujo_USD!E4:E203)+SUMPRODUCT((MONTH(Flujo_USD!A4:A203)=8)*(YEAR(Flujo_USD!A4:A203)=YEAR(TODAY()))*IF(Flujo_USD!D4:D203="Ingreso",1,-1)*Flujo_USD!E4:E203)+SUMPRODUCT((MONTH(Flujo_USD!A4:A203)=9)*(YEAR(Flujo_USD!A4:A203)=YEAR(TODAY()))*IF(Flujo_USD!D4:D203="Ingreso",1,-1)*Flujo_USD!E4:E203)+SUMPRODUCT((MONTH(Flujo_USD!A4:A203)=10)*(YEAR(Flujo_USD!A4:A203)=YEAR(TODAY()))*IF(Flujo_USD!D4:D203="Ingreso",1,-1)*Flujo_USD!E4:E203)+SUMPRODUCT((MONTH(Flujo_USD!A4:A203)=11)*(YEAR(Flujo_USD!A4:A203)=YEAR(TODAY()))*IF(Flujo_USD!D4:D203="Ingreso",1,-1)*Flujo_USD!E4:E203),0)
B25: Dic | C25: =IFERROR(SUMPRODUCT((MONTH(Flujo_BOB!A4:A203)=12)*(YEAR(Flujo_BOB!A4:A203)=YEAR(TODAY()))*(Flujo_BOB!D4:D203="Ingreso")*Flujo_BOB!E4:E203)+SUMPRODUCT((MONTH(Flujo_USD!A4:A203)=12)*(YEAR(Flujo_USD!A4:A203)=YEAR(TODAY()))*(Flujo_USD!D4:D203="Ingreso")*Flujo_USD!E4:E203)*D4,0) | D25: =IFERROR(SUMPRODUCT((MONTH(Flujo_BOB!A4:A203)=12)*(YEAR(Flujo_BOB!A4:A203)=YEAR(TODAY()))*(Flujo_BOB!D4:D203="Egreso")*Flujo_BOB!E4:E203)+SUMPRODUCT((MONTH(Flujo_USD!A4:A203)=12)*(YEAR(Flujo_USD!A4:A203)=YEAR(TODAY()))*(Flujo_USD!D4:D203="Egreso")*Flujo_USD!E4:E203)*D4,0) | F25: Dic | G25: =IFERROR(SUMPRODUCT((MONTH(Flujo_BOB!A4:A203)=1)*(YEAR(Flujo_BOB!A4:A203)=YEAR(TODAY()))*IF(Flujo_BOB!D4:D203="Ingreso",1,-1)*Flujo_BOB!E4:E203)+SUMPRODUCT((MONTH(Flujo_BOB!A4:A203)=2)*(YEAR(Flujo_BOB!A4:A203)=YEAR(TODAY()))*IF(Flujo_BOB!D4:D203="Ingreso",1,-1)*Flujo_BOB!E4:E203)+SUMPRODUCT((MONTH(Flujo_BOB!A4:A203)=3)*(YEAR(Flujo_BOB!A4:A203)=YEAR(TODAY()))*IF(Flujo_BOB!D4:D203="Ingreso",1,-1)*Flujo_BOB!E4:E203)+SUMPRODUCT((MONTH(Flujo_BOB!A4:A203)=4)*(YEAR(Flujo_BOB!A4:A203)=YEAR(TODAY()))*IF(Flujo_BOB!D4:D203="Ingreso",1,-1)*Flujo_BOB!E4:E203)+SUMPRODUCT((MONTH(Flujo_BOB!A4:A203)=5)*(YEAR(Flujo_BOB!A4:A203)=YEAR(TODAY()))*IF(Flujo_BOB!D4:D203="Ingreso",1,-1)*Flujo_BOB!E4:E203)+SUMPRODUCT((MONTH(Flujo_BOB!A4:A203)=6)*(YEAR(Flujo_BOB!A4:A203)=YEAR(TODAY()))*IF(Flujo_BOB!D4:D203="Ingreso",1,-1)*Flujo_BOB!E4:E203)+SUMPRODUCT((MONTH(Flujo_BOB!A4:A203)=7)*(YEAR(Flujo_BOB!A4:A203)=YEAR(TODAY()))*IF(Flujo_BOB!D4:D203="Ingreso",1,-1)*Flujo_BOB!E4:E203)+SUMPRODUCT((MONTH(Flujo_BOB!A4:A203)=8)*(YEAR(Flujo_BOB!A4:A203)=YEAR(TODAY()))*IF(Flujo_BOB!D4:D203="Ingreso",1,-1)*Flujo_BOB!E4:E203)+SUMPRODUCT((MONTH(Flujo_BOB!A4:A203)=9)*(YEAR(Flujo_BOB!A4:A203)=YEAR(TODAY()))*IF(Flujo_BOB!D4:D203="Ingreso",1,-1)*Flujo_BOB!E4:E203)+SUMPRODUCT((MONTH(Flujo_BOB!A4:A203)=10)*(YEAR(Flujo_BOB!A4:A203)=YEAR(TODAY()))*IF(Flujo_BOB!D4:D203="Ingreso",1,-1)*Flujo_BOB!E4:E203)+SUMPRODUCT((MONTH(Flujo_BOB!A4:A203)=11)*(YEAR(Flujo_BOB!A4:A203)=YEAR(TODAY()))*IF(Flujo_BOB!D4:D203="Ingreso",1,-1)*Flujo_BOB!E4:E203)+SUMPRODUCT((MONTH(Flujo_BOB!A4:A203)=12)*(YEAR(Flujo_BOB!A4:A203)=YEAR(TODAY()))*IF(Flujo_BOB!D4:D203="Ingreso",1,-1)*Flujo_BOB!E4:E203),0) | H25: =IFERROR(SUMPRODUCT((MONTH(Flujo_USD!A4:A203)=1)*(YEAR(Flujo_USD!A4:A203)=YEAR(TODAY()))*IF(Flujo_USD!D4:D203="Ingreso",1,-1)*Flujo_USD!E4:E203)+SUMPRODUCT((MONTH(Flujo_USD!A4:A203)=2)*(YEAR(Flujo_USD!A4:A203)=YEAR(TODAY()))*IF(Flujo_USD!D4:D203="Ingreso",1,-1)*Flujo_USD!E4:E203)+SUMPRODUCT((MONTH(Flujo_USD!A4:A203)=3)*(YEAR(Flujo_USD!A4:A203)=YEAR(TODAY()))*IF(Flujo_USD!D4:D203="Ingreso",1,-1)*Flujo_USD!E4:E203)+SUMPRODUCT((MONTH(Flujo_USD!A4:A203)=4)*(YEAR(Flujo_USD!A4:A203)=YEAR(TODAY()))*IF(Flujo_USD!D4:D203="Ingreso",1,-1)*Flujo_USD!E4:E203)+SUMPRODUCT((MONTH(Flujo_USD!A4:A203)=5)*(YEAR(Flujo_USD!A4:A203)=YEAR(TODAY()))*IF(Flujo_USD!D4:D203="Ingreso",1,-1)*Flujo_USD!E4:E203)+SUMPRODUCT((MONTH(Flujo_USD!A4:A203)=6)*(YEAR(Flujo_USD!A4:A203)=YEAR(TODAY()))*IF(Flujo_USD!D4:D203="Ingreso",1,-1)*Flujo_USD!E4:E203)+SUMPRODUCT((MONTH(Flujo_USD!A4:A203)=7)*(YEAR(Flujo_USD!A4:A203)=YEAR(TODAY()))*IF(Flujo_USD!D4:D203="Ingreso",1,-1)*Flujo_USD!E4:E203)+SUMPRODUCT((MONTH(Flujo_USD!A4:A203)=8)*(YEAR(Flujo_USD!A4:A203)=YEAR(TODAY()))*IF(Flujo_USD!D4:D203="Ingreso",1,-1)*Flujo_USD!E4:E203)+SUMPRODUCT((MONTH(Flujo_USD!A4:A203)=9)*(YEAR(Flujo_USD!A4:A203)=YEAR(TODAY()))*IF(Flujo_USD!D4:D203="Ingreso",1,-1)*Flujo_USD!E4:E203)+SUMPRODUCT((MONTH(Flujo_USD!A4:A203)=10)*(YEAR(Flujo_USD!A4:A203)=YEAR(TODAY()))*IF(Flujo_USD!D4:D203="Ingreso",1,-1)*Flujo_USD!E4:E203)+SUMPRODUCT((MONTH(Flujo_USD!A4:A203)=11)*(YEAR(Flujo_USD!A4:A203)=YEAR(TODAY()))*IF(Flujo_USD!D4:D203="Ingreso",1,-1)*Flujo_USD!E4:E203)+SUMPRODUCT((MONTH(Flujo_USD!A4:A203)=12)*(YEAR(Flujo_USD!A4:A203)=YEAR(TODAY()))*IF(Flujo_USD!D4:D203="Ingreso",1,-1)*Flujo_USD!E4:E203),0)

Sheet Flujo_BOB
A1: FLUJO DE CAJA EN BOLIVIANOS
A2: Registra todos los ingresos y egresos en BOLIVIANOS.
A3: FECHA | B3: CONCEPTO | C3: CATEGORIA | D3: TIPO | E3: MONTO (Bs.) | F3: SALDO ACUMULADO | G3: OBSERVACION
A4: 45659 | B4: Ventas enero semana 1 | C4: Ventas | D4: Ingreso | E4: 15000 | F4: =IF(D4="Ingreso",E4,IF(D4="Egreso",-E4,0))
A5: 45662 | B5: Alquiler local | C5: Alquiler | D5: Egreso | E5: 3500 | F5: =IF(A5="",F4,F4+IF(D5="Ingreso",E5,IF(D5="Egreso",-E5,0)))
A6: 45662 | B6: Sueldos enero | C6: Sueldos | D6: Egreso | E6: 8000 | F6: =IF(A6="",F5,F5+IF(D6="Ingreso",E6,IF(D6="Egreso",-E6,0))) | G6: 3 empleados
A7: 45667 | B7: Ventas enero semana 2 | C7: Ventas | D7: Ingreso | E7: 12000 | F7: =IF(A7="",F6,F6+IF(D7="Ingreso",E7,IF(D7="Egreso",-E7,0)))
A8: 45672 | B8: Servicios basicos | C8: Servicios | D8: Egreso | E8: 700 | F8: =IF(A8="",F7,F7+IF(D8="Ingreso",E8,IF(D8="Egreso",-E8,0)))
A9: 45677 | B9: Ventas enero semana 3 | C9: Ventas | D9: Ingreso | E9: 18000 | F9: =IF(A9="",F8,F8+IF(D9="Ingreso",E9,IF(D9="Egreso",-E9,0)))
A10: 45682 | B10: Compra mercaderia | C10: Compras | D10: Egreso | E10: 10000 | F10: =IF(A10="",F9,F9+IF(D10="Ingreso",E10,IF(D10="Egreso",-E10,0)))
A11: 45689 | B11: Ventas febrero semana 1 | C11: Ventas | D11: Ingreso | E11: 16000 | F11: =IF(A11="",F10,F10+IF(D11="Ingreso",E11,IF(D11="Egreso",-E11,0)))
A12: 45693 | B12: Alquiler local | C12: Alquiler | D12: Egreso | E12: 3500 | F12: =IF(A12="",F11,F11+IF(D12="Ingreso",E12,IF(D12="Egreso",-E12,0)))
F13: =IF(A13="",F12,F12+IF(D13="Ingreso",E13,IF(D13="Egreso",-E13,0)))
F14: =IF(A14="",F13,F13+IF(D14="Ingreso",E14,IF(D14="Egreso",-E14,0)))
F15: =IF(A15="",F14,F14+IF(D15="Ingreso",E15,IF(D15="Egreso",-E15,0)))
F16: =IF(A16="",F15,F15+IF(D16="Ingreso",E16,IF(D16="Egreso",-E16,0)))
F17: =IF(A17="",F16,F16+IF(D17="Ingreso",E17,IF(D17="Egreso",-E17,0)))
F18: =IF(A18="",F17,F17+IF(D18="Ingreso",E18,IF(D18="Egreso",-E18,0)))
F19: =IF(A19="",F18,F18+IF(D19="Ingreso",E19,IF(D19="Egreso",-E19,0)))
F20: =IF(A20="",F19,F19+IF(D20="Ingreso",E20,IF(D20="Egreso",-E20,0)))
F21: =IF(A21="",F20,F20+IF(D21="Ingreso",E21,IF(D21="Egreso",-E21,0)))
F22: =IF(A22="",F21,F21+IF(D22="Ingreso",E22,IF(D22="Egreso",-E22,0)))
F23: =IF(A23="",F22,F22+IF(D23="Ingreso",E23,IF(D23="Egreso",-E23,0)))
F24: =IF(A24="",F23,F23+IF(D24="Ingreso",E24,IF(D24="Egreso",-E24,0)))
... F203: =IF(A203="",F202,F202+IF(D203="Ingreso",E203,IF(D203="Egreso",-E203,0)))

Sheet Flujo_USD
A1: FLUJO DE CAJA EN DOLARES
A2: Registra todos los ingresos y egresos en DOLARES.
A3: FECHA | B3: CONCEPTO | C3: CATEGORIA | D3: TIPO | E3: MONTO (USD) | F3: SALDO ACUMULADO | G3: OBSERVACION
A4: 45660 | B4: Pago cliente exportacion | C4: Ventas | D4: Ingreso | E4: 2000 | F4: =IF(D4="Ingreso",E4,IF(D4="Egreso",-E4,0))
A5: 45667 | B5: Compra insumos importados | C5: Compras | D5: Egreso | E5: 800 | F5: =IF(A5="",F4,F4+IF(D5="Ingreso",E5,IF(D5="Egreso",-E5,0)))
A6: 45677 | B6: Comision plataforma | C6: Servicios | D6: Egreso | E6: 150 | F6: =IF(A6="",F5,F5+IF(D6="Ingreso",E6,IF(D6="Egreso",-E6,0))) | G6: Stripe
A7: 45691 | B7: Pago cliente exportacion | C7: Ventas | D7: Ingreso | E7: 2500 | F7: =IF(A7="",F6,F6+IF(D7="Ingreso",E7,IF(D7="Egreso",-E7,0)))
F8: =IF(A8="",F7,F7+IF(D8="Ingreso",E8,IF(D8="Egreso",-E8,0)))
F9: =IF(A9="",F8,F8+IF(D9="Ingreso",E9,IF(D9="Egreso",-E9,0)))
F10: =IF(A10="",F9,F9+IF(D10="Ingreso",E10,IF(D10="Egreso",-E10,0)))
F11: =IF(A11="",F10,F10+IF(D11="Ingreso",E11,IF(D11="Egreso",-E11,0)))
F12: =IF(A12="",F11,F11+IF(D12="Ingreso",E12,IF(D12="Egreso",-E12,0)))
F13: =IF(A13="",F12,F12+IF(D13="Ingreso",E13,IF(D13="Egreso",-E13,0)))
F14: =IF(A14="",F13,F13+IF(D14="Ingreso",E14,IF(D14="Egreso",-E14,0)))
F15: =IF(A15="",F14,F14+IF(D15="Ingreso",E15,IF(D15="Egreso",-E15,0)))
F16: =IF(A16="",F15,F15+IF(D16="Ingreso",E16,IF(D16="Egreso",-E16,0)))
F17: =IF(A17="",F16,F16+IF(D17="Ingreso",E17,IF(D17="Egreso",-E17,0)))
F18: =IF(A18="",F17,F17+IF(D18="Ingreso",E18,IF(D18="Egreso",-E18,0)))
F19: =IF(A19="",F18,F18+IF(D19="Ingreso",E19,IF(D19="Egreso",-E19,0)))
... F203: =IF(A203="",F202,F202+IF(D203="Ingreso",E203,IF(D203="Egreso",-E203,0)))

Sheet TipoCambio
A1: HISTORIAL TIPO DE CAMBIO
A2: Registra el tipo de cambio mensual Bs/USD para referencia.
A3: MES | B3: COMPRA | C3: VENTA | D3: PROMEDIO | E3: VARIACION
A4: Ene | B4: 6.86 | C4: 6.96 | D4: =IFERROR((B4+C4)/2,0) | E4: =0
A5: Feb | B5: 6.86 | C5: 6.96 | D5: =IFERROR((B5+C5)/2,0) | E5: =IFERROR((D5-D4)/D4,0)
A6: Mar | B6: 6.86 | C6: 6.96 | D6: =IFERROR((B6+C6)/2,0) | E6: =IFERROR((D6-D5)/D5,0)
A7: Abr | B7: 6.86 | C7: 6.96 | D7: =IFERROR((B7+C7)/2,0) | E7: =IFERROR((D7-D6)/D6,0)
A8: May | B8: 6.86 | C8: 6.96 | D8: =IFERROR((B8+C8)/2,0) | E8: =IFERROR((D8-D7)/D7,0)
A9: Jun | B9: 6.86 | C9: 6.96 | D9: =IFERROR((B9+C9)/2,0) | E9: =IFERROR((D9-D8)/D8,0)
A10: Jul | B10: 6.86 | C10: 6.96 | D10: =IFERROR((B10+C10)/2,0) | E10: =IFERROR((D10-D9)/D9,0)
A11: Ago | B11: 6.86 | C11: 6.96 | D11: =IFERROR((B11+C11)/2,0) | E11: =IFERROR((D11-D10)/D10,0)
A12: Sep | B12: 6.86 | C12: 6.96 | D12: =IFERROR((B12+C12)/2,0) | E12: =IFERROR((D12-D11)/D11,0)
A13: Oct | B13: 6.86 | C13: 6.96 | D13: =IFERROR((B13+C13)/2,0) | E13: =IFERROR((D13-D12)/D12,0)
A14: Nov | B14: 6.86 | C14: 6.96 | D14: =IFERROR((B14+C14)/2,0) | E14: =IFERROR((D14-D13)/D13,0)
A15: Dic | B15: 6.86 | C15: 6.96 | D15: =IFERROR((B15+C15)/2,0) | E15: =IFERROR((D15-D14)/D14,0)

Sheet Proyeccion
B1: PROYECCION DE FLUJO DE CAJA
B2: Ingresa tus estimaciones de ingresos y egresos para los proximos meses.
B4: MES | C4: INGRESOS PROY. (Bs.) | D4: EGRESOS PROY. (Bs.) | E4: SALDO PROY.
B5: Ene | E5: =C5-D5
B6: Feb | E6: =E5+C6-D6
B7: Mar | E7: =E6+C7-D7
B8: Abr | E8: =E7+C8-D8
B9: May | E9: =E8+C9-D9
B10: Jun | E10: =E9+C10-D10
B11: Jul | E11: =E10+C11-D11
B12: Ago | E12: =E11+C12-D12
B13: Sep | E13: =E12+C13-D13
B14: Oct | E14: =E13+C14-D14
B15: Nov | E15: =E14+C15-D15
B16: Dic | E16: =E15+C16-D16

Sheet Config
A1: v1.0.0
A3: CONFIGURACION
A5: Producto | B5: Flujo de Caja Dual Bs/USD
A6: Version | B6: v1.0.0
A7: Marca | B7: No Somos Ignorantes
A8: Precio | B8: Bs. 99
A9: Proteccion | B9: nsi2024
A11: INSTRUCCIONES
A12: 1. | B12: Ingresa el tipo de cambio actual en el Dashboard (celda D4).
A13: 2. | B13: En 'Flujo_BOB', registra ingresos/egresos en Bolivianos.
A14: 3. | B14: En 'Flujo_USD', registra ingresos/egresos en Dolares.
A15: 4. | B15: El Dashboard combina ambas monedas automaticamente.
A16: 5. | B16: En 'TipoCambio', registra el TC mensual de referencia.
A17: 6. | B17: En 'Proyeccion', estima flujos futuros.
A18: 7. | B18: Para desbloquear: Revisar -> Desproteger hoja -> nsi2024
