Workbook

Sheet Dashboard
B2: GESTOR DE COSTO DE VENTAS
B3: No Somos Ignorantes | v1.0 | Analisis de margen bruto
B5: VENTAS TOTALES (Bs.) | F5: COSTO DE VENTAS (Bs.)
B6: =IFERROR(SUM(Ventas!G4:G203),0) | F6: =IFERROR(SUM(Ventas!H4:H203),0)
B8: UTILIDAD BRUTA (Bs.) | F8: ROTACION DE INVENTARIO
B9: =B6-F6 | F9: =IFERROR(F6/((Inventario!C4+Inventario!D4)/2),0)
B10: Margen bruto: | C10: =IFERROR(B9/B6,0) | F10: Dias de inventario: | G10: =IFERROR(365/F9,0)
B12: FORMULA: Inv. Inicial + Compras - Inv. Final = Costo de Ventas
B13: Inventario Inicial: | D13: =Inventario!C4
B14: (+) Compras del Periodo: | D14: =SUM(Compras!E4:E203)
B15: (-) Inventario Final: | D15: =Inventario!D4
B16: (=) Costo de Ventas: | D16: =D13+D14-D15
B18: MARGEN BRUTO MENSUAL | F18: % MARGEN BRUTO MENSUAL
B19: Mes | C19: Ventas | D19: COGS | F19: Mes | G19: Margen %
B20: Ene | C20: =IFERROR(SUMPRODUCT((MONTH(Ventas!A4:A203)=1)*Ventas!G4:G203),0) | D20: =IFERROR(SUMPRODUCT((MONTH(Ventas!A4:A203)=1)*Ventas!H4:H203),0) | F20: Ene | G20: =IFERROR((C20-D20)/C20,0)
B21: Feb | C21: =IFERROR(SUMPRODUCT((MONTH(Ventas!A4:A203)=2)*Ventas!G4:G203),0) | D21: =IFERROR(SUMPRODUCT((MONTH(Ventas!A4:A203)=2)*Ventas!H4:H203),0) | F21: Feb | G21: =IFERROR((C21-D21)/C21,0)
B22: Mar | C22: =IFERROR(SUMPRODUCT((MONTH(Ventas!A4:A203)=3)*Ventas!G4:G203),0) | D22: =IFERROR(SUMPRODUCT((MONTH(Ventas!A4:A203)=3)*Ventas!H4:H203),0) | F22: Mar | G22: =IFERROR((C22-D22)/C22,0)
B23: Abr | C23: =IFERROR(SUMPRODUCT((MONTH(Ventas!A4:A203)=4)*Ventas!G4:G203),0) | D23: =IFERROR(SUMPRODUCT((MONTH(Ventas!A4:A203)=4)*Ventas!H4:H203),0) | F23: Abr | G23: =IFERROR((C23-D23)/C23,0)
B24: May | C24: =IFERROR(SUMPRODUCT((MONTH(Ventas!A4:A203)=5)*Ventas!G4:G203),0) | D24: =IFERROR(SUMPRODUCT((MONTH(Ventas!A4:A203)=5)*Ventas!H4:H203),0) | F24: May | G24: =IFERROR((C24-D24)/C24,0)
B25: Jun | C25: =IFERROR(SUMPRODUCT((MONTH(Ventas!A4:A203)=6)*Ventas!G4:G203),0) | D25: =IFERROR(SUMPRODUCT((MONTH(Ventas!A4:A203)=6)*Ventas!H4:H203),0) | F25: Jun | G25: =IFERROR((C25-D25)/C25,0)
B26: Jul | C26: =IFERROR(SUMPRODUCT((MONTH(Ventas!A4:A203)=7)*Ventas!G4:G203),0) | D26: =IFERROR(SUMPRODUCT((MONTH(Ventas!A4:A203)=7)*Ventas!H4:H203),0) | F26: Jul | G26: =IFERROR((C26-D26)/C26,0)
B27: Ago | C27: =IFERROR(SUMPRODUCT((MONTH(Ventas!A4:A203)=8)*Ventas!G4:G203),0) | D27: =IFERROR(SUMPRODUCT((MONTH(Ventas!A4:A203)=8)*Ventas!H4:H203),0) | F27: Ago | G27: =IFERROR((C27-D27)/C27,0)
B28: Sep | C28: =IFERROR(SUMPRODUCT((MONTH(Ventas!A4:A203)=9)*Ventas!G4:G203),0) | D28: =IFERROR(SUMPRODUCT((MONTH(Ventas!A4:A203)=9)*Ventas!H4:H203),0) | F28: Sep | G28: =IFERROR((C28-D28)/C28,0)
B29: Oct | C29: =IFERROR(SUMPRODUCT((MONTH(Ventas!A4:A203)=10)*Ventas!G4:G203),0) | D29: =IFERROR(SUMPRODUCT((MONTH(Ventas!A4:A203)=10)*Ventas!H4:H203),0) | F29: Oct | G29: =IFERROR((C29-D29)/C29,0)
B30: Nov | C30: =IFERROR(SUMPRODUCT((MONTH(Ventas!A4:A203)=11)*Ventas!G4:G203),0) | D30: =IFERROR(SUMPRODUCT((MONTH(Ventas!A4:A203)=11)*Ventas!H4:H203),0) | F30: Nov | G30: =IFERROR((C30-D30)/C30,0)
B31: Dic | C31: =IFERROR(SUMPRODUCT((MONTH(Ventas!A4:A203)=12)*Ventas!G4:G203),0) | D31: =IFERROR(SUMPRODUCT((MONTH(Ventas!A4:A203)=12)*Ventas!H4:H203),0) | F31: Dic | G31: =IFERROR((C31-D31)/C31,0)

Sheet Inventario
A1: INVENTARIO INICIAL Y FINAL
A2: Ingresa el valor del inventario al inicio y final del periodo para calcular el costo de ventas.
A3: # | B3: CATEGORIA / PRODUCTO | C3: INV. INICIAL (Bs.) | D3: INV. FINAL (Bs.) | E3: VARIACION
B4: TOTAL INVENTARIO | C4: =SUM(C5:C34) | D4: =SUM(D5:D34) | E4: =D4-C4
A5: =IF(B5="","",ROW()-4) | B5: Materia Prima A | C5: 25000 | D5: 22000 | E5: =IFERROR(D5-C5,0)
A6: =IF(B6="","",ROW()-4) | B6: Materia Prima B | C6: 15000 | D6: 18000 | E6: =IFERROR(D6-C6,0)
A7: =IF(B7="","",ROW()-4) | B7: Productos en Proceso | C7: 8000 | D7: 6000 | E7: =IFERROR(D7-C7,0)
A8: =IF(B8="","",ROW()-4) | B8: Productos Terminados | C8: 30000 | D8: 28000 | E8: =IFERROR(D8-C8,0)
A9: =IF(B9="","",ROW()-4) | B9: Suministros | C9: 5000 | D9: 4500 | E9: =IFERROR(D9-C9,0)
A10: =IF(B10="","",ROW()-4) | E10: =IFERROR(D10-C10,0)
A11: =IF(B11="","",ROW()-4) | E11: =IFERROR(D11-C11,0)
A12: =IF(B12="","",ROW()-4) | E12: =IFERROR(D12-C12,0)
A13: =IF(B13="","",ROW()-4) | E13: =IFERROR(D13-C13,0)
A14: =IF(B14="","",ROW()-4) | E14: =IFERROR(D14-C14,0)
A15: =IF(B15="","",ROW()-4) | E15: =IFERROR(D15-C15,0)
A16: =IF(B16="","",ROW()-4) | E16: =IFERROR(D16-C16,0)
A17: =IF(B17="","",ROW()-4) | E17: =IFERROR(D17-C17,0)
A18: =IF(B18="","",ROW()-4) | E18: =IFERROR(D18-C18,0)
A19: =IF(B19="","",ROW()-4) | E19: =IFERROR(D19-C19,0)
A20: =IF(B20="","",ROW()-4) | E20: =IFERROR(D20-C20,0)
A21: =IF(B21="","",ROW()-4) | E21: =IFERROR(D21-C21,0)
... A34: =IF(B34="","",ROW()-4) | E34: =IFERROR(D34-C34,0)

Sheet Compras
A1: REGISTRO DE COMPRAS
A2: Registra todas las compras de inventario/mercaderia del periodo.
A3: FECHA | B3: PROVEEDOR | C3: PRODUCTO/DETALLE | D3: CANTIDAD | E3: TOTAL COMPRA (Bs.) | F3: OBSERVACION
A4: 45662 | B4: Proveedor ABC | C4: Materia Prima A | D4: 100 | E4: 12500
A5: 45667 | B5: Distribuidora XYZ | C5: Materia Prima B | D5: 50 | E5: 7500
A6: 45672 | B6: Suministros SRL | C6: Suministros varios | D6: 1 | E6: 2000
A7: 45689 | B7: Proveedor ABC | C7: Materia Prima A | D7: 80 | E7: 10000
A8: 45693 | B8: Distribuidora XYZ | C8: Materia Prima B | D8: 60 | E8: 9000

Sheet Ventas
A1: VENTAS Y COSTO DE VENTAS
A2: Registra cada venta con su costo unitario para calcular el margen bruto por producto.
A3: FECHA | B3: PRODUCTO | C3: CANTIDAD | D3: PRECIO UNIT. | E3: COSTO UNIT. | F3: MARGEN % | G3: TOTAL VENTA | H3: TOTAL COSTO | I3: UTILIDAD
A4: 45665 | B4: Producto Terminado A | C4: 20 | D4: 150 | E4: 80 | F4: =IFERROR((D4-E4)/D4,0) | G4: =IFERROR(C4*D4,0) | H4: =IFERROR(C4*E4,0) | I4: =G4-H4
A5: 45669 | B5: Producto Terminado B | C5: 15 | D5: 220 | E5: 120 | F5: =IFERROR((D5-E5)/D5,0) | G5: =IFERROR(C5*D5,0) | H5: =IFERROR(C5*E5,0) | I5: =G5-H5
A6: 45672 | B6: Producto Terminado A | C6: 25 | D6: 150 | E6: 80 | F6: =IFERROR((D6-E6)/D6,0) | G6: =IFERROR(C6*D6,0) | H6: =IFERROR(C6*E6,0) | I6: =G6-H6
A7: 45677 | B7: Producto Terminado C | C7: 10 | D7: 350 | E7: 200 | F7: =IFERROR((D7-E7)/D7,0) | G7: =IFERROR(C7*D7,0) | H7: =IFERROR(C7*E7,0) | I7: =G7-H7
A8: 45682 | B8: Producto Terminado B | C8: 18 | D8: 220 | E8: 120 | F8: =IFERROR((D8-E8)/D8,0) | G8: =IFERROR(C8*D8,0) | H8: =IFERROR(C8*E8,0) | I8: =G8-H8
A9: 45691 | B9: Producto Terminado A | C9: 30 | D9: 150 | E9: 80 | F9: =IFERROR((D9-E9)/D9,0) | G9: =IFERROR(C9*D9,0) | H9: =IFERROR(C9*E9,0) | I9: =G9-H9
A10: 45696 | B10: Producto Terminado C | C10: 12 | D10: 350 | E10: 200 | F10: =IFERROR((D10-E10)/D10,0) | G10: =IFERROR(C10*D10,0) | H10: =IFERROR(C10*E10,0) | I10: =G10-H10
F11: =IFERROR((D11-E11)/D11,0) | G11: =IFERROR(C11*D11,0) | H11: =IFERROR(C11*E11,0) | I11: =G11-H11
F12: =IFERROR((D12-E12)/D12,0) | G12: =IFERROR(C12*D12,0) | H12: =IFERROR(C12*E12,0) | I12: =G12-H12
F13: =IFERROR((D13-E13)/D13,0) | G13: =IFERROR(C13*D13,0) | H13: =IFERROR(C13*E13,0) | I13: =G13-H13
F14: =IFERROR((D14-E14)/D14,0) | G14: =IFERROR(C14*D14,0) | H14: =IFERROR(C14*E14,0) | I14: =G14-H14
F15: =IFERROR((D15-E15)/D15,0) | G15: =IFERROR(C15*D15,0) | H15: =IFERROR(C15*E15,0) | I15: =G15-H15
F16: =IFERROR((D16-E16)/D16,0) | G16: =IFERROR(C16*D16,0) | H16: =IFERROR(C16*E16,0) | I16: =G16-H16
F17: =IFERROR((D17-E17)/D17,0) | G17: =IFERROR(C17*D17,0) | H17: =IFERROR(C17*E17,0) | I17: =G17-H17
F18: =IFERROR((D18-E18)/D18,0) | G18: =IFERROR(C18*D18,0) | H18: =IFERROR(C18*E18,0) | I18: =G18-H18
F19: =IFERROR((D19-E19)/D19,0) | G19: =IFERROR(C19*D19,0) | H19: =IFERROR(C19*E19,0) | I19: =G19-H19
F20: =IFERROR((D20-E20)/D20,0) | G20: =IFERROR(C20*D20,0) | H20: =IFERROR(C20*E20,0) | I20: =G20-H20
F21: =IFERROR((D21-E21)/D21,0) | G21: =IFERROR(C21*D21,0) | H21: =IFERROR(C21*E21,0) | I21: =G21-H21
F22: =IFERROR((D22-E22)/D22,0) | G22: =IFERROR(C22*D22,0) | H22: =IFERROR(C22*E22,0) | I22: =G22-H22
... F203: =IFERROR((D203-E203)/D203,0) | G203: =IFERROR(C203*D203,0) | H203: =IFERROR(C203*E203,0) | I203: =G203-H203

Sheet Config
A1: v1.0.0
A3: CONFIGURACION
A5: Producto | B5: Gestor de Costo de Ventas
A6: Version | B6: v1.0.0
A7: Marca | B7: No Somos Ignorantes
A8: Precio | B8: Bs. 59
A9: Proteccion | B9: nsi2024
A11: INSTRUCCIONES
A12: 1. | B12: En 'Inventario', ingresa el valor del inventario inicial y final.
A13: 2. | B13: En 'Compras', registra todas las compras del periodo.
A14: 3. | B14: En 'Ventas', registra cada venta con su precio y costo unitario.
A15: 4. | B15: El Dashboard calcula automaticamente el COGS, margen bruto y rotacion.
A16: 5. | B16: Formula COGS: Inv. Inicial + Compras - Inv. Final = Costo de Ventas
A17: 6. | B17: Para desbloquear: Revisar -> Desproteger hoja -> nsi2024
