Workbook

Sheet Presupuesto
B2: PRESUPUESTO 50/30/20
B3: No Somos Ignorantes | v1.0 | Tu primer paso hacia la libertad financiera
B5: TU INGRESO MENSUAL (Bs.) | D5: 5000
B7: CATEGORÍA | C7: MONTO (Bs.) | D7: % DEL INGRESO | E7: LÍMITE (Bs.) | F7: ESTADO
B8: 50% NECESIDADES — Lo que necesitas para vivir
B9: Vivienda (alquiler/cuota) | C9: 1200 | D9: =IF($D$5>0,C9/$D$5,0)
B10: Servicios básicos (luz, agua, gas) | C10: 200 | D10: =IF($D$5>0,C10/$D$5,0)
B11: Alimentación y mercado | C11: 800 | D11: =IF($D$5>0,C11/$D$5,0)
B12: Transporte | C12: 300 | D12: =IF($D$5>0,C12/$D$5,0)
B13: Seguros (salud, vida) | C13: 0 | D13: =IF($D$5>0,C13/$D$5,0)
B14: Educación obligatoria | C14: 0 | D14: =IF($D$5>0,C14/$D$5,0)
B15: Medicinas / Salud | C15: 0 | D15: =IF($D$5>0,C15/$D$5,0)
B16: Teléfono / Internet básico | C16: 0 | D16: =IF($D$5>0,C16/$D$5,0)
B17: TOTAL NECESIDADES | C17: =SUM(C9:C16) | D17: =IF($D$5>0,C17/$D$5,0) | E17: =$D$5*0.5 | F17: =IF(C17<=E17,"DENTRO DEL LIMITE","EXCEDIDO")
B18: Disponible restante | E18: =E17-C17
B20: 30% DESEOS — Lo que te hace feliz
B21: Entretenimiento / Salidas | C21: 300 | D21: =IF($D$5>0,C21/$D$5,0)
B22: Restaurantes / Comida fuera | C22: 200 | D22: =IF($D$5>0,C22/$D$5,0)
B23: Compras personales (ropa, etc.) | C23: 150 | D23: =IF($D$5>0,C23/$D$5,0)
B24: Streaming / Suscripciones | C24: 50 | D24: =IF($D$5>0,C24/$D$5,0)
B25: Hobbies / Deportes | C25: 0 | D25: =IF($D$5>0,C25/$D$5,0)
B26: Regalos | C26: 0 | D26: =IF($D$5>0,C26/$D$5,0)
B27: Viajes / Vacaciones | C27: 0 | D27: =IF($D$5>0,C27/$D$5,0)
B28: Otros deseos | C28: 0 | D28: =IF($D$5>0,C28/$D$5,0)
B29: TOTAL DESEOS | C29: =SUM(C21:C28) | D29: =IF($D$5>0,C29/$D$5,0) | E29: =$D$5*0.3 | F29: =IF(C29<=E29,"DENTRO DEL LIMITE","EXCEDIDO")
B30: Disponible restante | E30: =E29-C29
B32: 20% AHORRO E INVERSIONES — Tu futuro
B33: Fondo de emergencia | C33: 500 | D33: =IF($D$5>0,C33/$D$5,0)
B34: Inversiones / Ahorro largo plazo | C34: 300 | D34: =IF($D$5>0,C34/$D$5,0)
B35: Metas de ahorro (viaje, auto, etc.) | C35: 200 | D35: =IF($D$5>0,C35/$D$5,0)
B36: Pago extra de deudas | C36: 0 | D36: =IF($D$5>0,C36/$D$5,0)
B37: Educación / Cursos | C37: 0 | D37: =IF($D$5>0,C37/$D$5,0)
B38: Retiro / Jubilación | C38: 0 | D38: =IF($D$5>0,C38/$D$5,0)
B39: TOTAL AHORRO | C39: =SUM(C33:C38) | D39: =IF($D$5>0,C39/$D$5,0) | E39: =$D$5*0.2 | F39: =IF(C39>=E39,"META ALCANZADA","AUN FALTA")
B40: Te falta ahorrar | E40: =MAX(0,E39-C39)
B42: TOTAL GASTOS + AHORRO | C42: =C17+C29+C39 | D42: =IF($D$5>0,C42/$D$5,0) | E42: =$D$5 | F42: =IF(C42<=E42,"PRESUPUESTO OK","GASTAS DE MAS")
B43: SOBRANTE / (DEFICIT) | C43: =$D$5-C42

Sheet Dashboard
B2: DASHBOARD - RESUMEN VISUAL
B3: Tus finanzas de un vistazo
B5: INGRESO MENSUAL | C5: TOTAL ASIGNADO | D5: SOBRANTE | E5: % UTILIZADO | F5: ESTADO
B6: =Presupuesto!D5 | C6: =Presupuesto!C42 | D6: =Presupuesto!C43 | E6: =Presupuesto!D42 | F6: =Presupuesto!F42
B8: Categoría | C8: Monto | D8: Límite ideal | E8: Diferencia
B9: Necesidades (50%) | C9: =Presupuesto!C17 | D9: =Presupuesto!D5*0.5 | E9: =D9-C9
B10: Deseos (30%) | C10: =Presupuesto!C29 | D10: =Presupuesto!D5*0.3 | E10: =D10-C10
B11: Ahorro (20%) | C11: =Presupuesto!C39 | D11: =Presupuesto!D5*0.2 | E11: =D11-C11

Sheet Instrucciones
B2: COMO USAR TU PRESUPUESTO 50/30/20
B5: PASO 1: INGRESA TU INGRESO MENSUAL
B6: Ve a la hoja 'Presupuesto' y escribe tu ingreso neto (lo que recibes
B7: despues de impuestos) en la celda amarilla grande.
B9: PASO 2: LLENA TUS NECESIDADES (50%)
B10: Escribe cuanto gastas en cada categoria de necesidades.
B11: Estas son cosas que NECESITAS para vivir: vivienda, comida, transporte.
B12: La regla dice que no deberia ser mas del 50% de tu ingreso.
B14: PASO 3: LLENA TUS DESEOS (30%)
B15: Escribe cuanto gastas en cosas que te gustan pero no son esenciales.
B16: Restaurantes, entretenimiento, compras, suscripciones.
B17: Maximo 30% de tu ingreso.
... B45: Siguenos en YouTube: @NoSomosIgnorantes

Sheet Config
A1: Version | B1: v1.0.0
A2: Producto | B2: Presupuesto 50/30/20
A3: Marca | B3: No Somos Ignorantes
A4: Sitio web | B4: nosomosignorantes.com
A5: YouTube | B5: @NoSomosIgnorantes
A6: Precio | B6: GRATIS (Lead Magnet)
A7: Proteccion | B7: Celdas de formula protegidas
A8: Fecha | B8: Febrero 2026
