Workbook

Sheet Dashboard
B2: SISTEMA DE VENTAS — PANEL EJECUTIVO
B3: No Somos Ignorantes | v1.0 | Resumen en tiempo real
B5: VENTAS DEL MES (Bs.) | F5: UNIDADES VENDIDAS
B6: =IFERROR(SUMPRODUCT((MONTH(Ventas!A4:A203)=MONTH(TODAY()))*(YEAR(Ventas!A4:A203)=YEAR(TODAY()))*Ventas!H4:H203),0) | F6: =IFERROR(SUMPRODUCT((MONTH(Ventas!A4:A203)=MONTH(TODAY()))*(YEAR(Ventas!A4:A203)=YEAR(TODAY()))*Ventas!E4:E203),0)
B7: Meta mensual: | C7: 50000 | F7: Transacciones: | G7: =IFERROR(SUMPRODUCT((MONTH(Ventas!A4:A203)=MONTH(TODAY()))*(YEAR(Ventas!A4:A203)=YEAR(TODAY()))*(Ventas!H4:H203>0)*1),0)
B8: Cumplimiento: | C8: =IFERROR(B6/C7,0) | F8: Ticket promedio: | G8: =IFERROR(B6/G7,"—")
B11: GANANCIA BRUTA (Bs.) | F11: ALERTAS DE INVENTARIO
B12: =IFERROR(SUMPRODUCT((MONTH(Ventas!A4:A203)=MONTH(TODAY()))*(YEAR(Ventas!A4:A203)=YEAR(TODAY()))*Ventas!H4:H203)-SUMPRODUCT((MONTH(Ventas!A4:A203)=MONTH(TODAY()))*(YEAR(Ventas!A4:A203)=YEAR(TODAY()))*Ventas!E4:E203*IFERROR(VLOOKUP(Ventas!C4:C203,Productos!A4:H103,4,FALSE),0)),0) | F12: =COUNTIF(Productos!I4:I103,"BAJO")+COUNTIF(Productos!I4:I103,"AGOTADO")
B13: Margen (%): | C13: =IFERROR(B12/B6,0) | F13: Agotados: | G13: =COUNTIF(Productos!I4:I103,"AGOTADO")
F14: Stock bajo: | G14: =COUNTIF(Productos!I4:I103,"BAJO")
B17: TOTAL PRODUCTOS | F17: VALOR INVENTARIO (Bs.)
B18: =COUNTA(Productos!B4:B103) | F18: =IFERROR(SUMPRODUCT(Productos!E4:E103*Productos!G4:G103),0)
B21: TOP 5 PRODUCTOS POR VENTAS
B22: Producto | C22: Ventas (Bs.) | F22: Método de Pago | G22: Total (Bs.)
B23: =IFERROR(INDEX(Productos!B4:B103,MATCH(LARGE(Productos!J4:J103,1),Productos!J4:J103,0)),"—") | C23: =IFERROR(LARGE(Productos!J4:J103,1),0) | F23: Efectivo | G23: =IFERROR(SUMPRODUCT((Ventas!I4:I203="Efectivo")*Ventas!H4:H203),0)
B24: =IFERROR(INDEX(Productos!B4:B103,MATCH(LARGE(Productos!J4:J103,2),Productos!J4:J103,0)),"—") | C24: =IFERROR(LARGE(Productos!J4:J103,2),0) | F24: Transferencia | G24: =IFERROR(SUMPRODUCT((Ventas!I4:I203="Transferencia")*Ventas!H4:H203),0)
B25: =IFERROR(INDEX(Productos!B4:B103,MATCH(LARGE(Productos!J4:J103,3),Productos!J4:J103,0)),"—") | C25: =IFERROR(LARGE(Productos!J4:J103,3),0) | F25: QR | G25: =IFERROR(SUMPRODUCT((Ventas!I4:I203="QR")*Ventas!H4:H203),0)
B26: =IFERROR(INDEX(Productos!B4:B103,MATCH(LARGE(Productos!J4:J103,4),Productos!J4:J103,0)),"—") | C26: =IFERROR(LARGE(Productos!J4:J103,4),0) | F26: Tarjeta | G26: =IFERROR(SUMPRODUCT((Ventas!I4:I203="Tarjeta")*Ventas!H4:H203),0)
B27: =IFERROR(INDEX(Productos!B4:B103,MATCH(LARGE(Productos!J4:J103,5),Productos!J4:J103,0)),"—") | C27: =IFERROR(LARGE(Productos!J4:J103,5),0)

Sheet Productos
A1: CATÁLOGO DE PRODUCTOS
A2: Registra tus productos con código único. Las celdas amarillas son editables.
A3: CÓDIGO | B3: PRODUCTO | C3: CATEGORÍA | D3: COSTO (Bs.) | E3: PRECIO VENTA (Bs.) | F3: MARGEN (%) | G3: STOCK ACTUAL | H3: STOCK MÍNIMO | I3: ESTADO | J3: VENTAS ACUM. (Bs.)
A4: =IF(B4="","","PROD-"&TEXT(ROW()-3,"0000")) | B4: Café Molido 500g | C4: Alimentos | D4: 35 | E4: 55 | F4: =IFERROR((E4-D4)/D4,0) | G4: 50 | H4: 10 | I4: =IF(B4="","",IF(G4=0,"AGOTADO",IF(G4<=H4,"BAJO","NORMAL"))) | J4: =IFERROR(SUMPRODUCT((Ventas!C4:C203=A4)*Ventas!H4:H203),0)
A5: =IF(B5="","","PROD-"&TEXT(ROW()-3,"0000")) | B5: Jugo Natural 1L | C5: Bebidas | D5: 8 | E5: 15 | F5: =IFERROR((E5-D5)/D5,0) | G5: 120 | H5: 20 | I5: =IF(B5="","",IF(G5=0,"AGOTADO",IF(G5<=H5,"BAJO","NORMAL"))) | J5: =IFERROR(SUMPRODUCT((Ventas!C4:C203=A5)*Ventas!H4:H203),0)
A6: =IF(B6="","","PROD-"&TEXT(ROW()-3,"0000")) | B6: Detergente Premium | C6: Limpieza | D6: 22 | E6: 38 | F6: =IFERROR((E6-D6)/D6,0) | G6: 80 | H6: 15 | I6: =IF(B6="","",IF(G6=0,"AGOTADO",IF(G6<=H6,"BAJO","NORMAL"))) | J6: =IFERROR(SUMPRODUCT((Ventas!C4:C203=A6)*Ventas!H4:H203),0)
A7: =IF(B7="","","PROD-"&TEXT(ROW()-3,"0000")) | B7: Cable USB-C | C7: Electrónica | D7: 15 | E7: 35 | F7: =IFERROR((E7-D7)/D7,0) | G7: 45 | H7: 10 | I7: =IF(B7="","",IF(G7=0,"AGOTADO",IF(G7<=H7,"BAJO","NORMAL"))) | J7: =IFERROR(SUMPRODUCT((Ventas!C4:C203=A7)*Ventas!H4:H203),0)
A8: =IF(B8="","","PROD-"&TEXT(ROW()-3,"0000")) | B8: Camiseta Algodón | C8: Ropa | D8: 30 | E8: 65 | F8: =IFERROR((E8-D8)/D8,0) | G8: 60 | H8: 12 | I8: =IF(B8="","",IF(G8=0,"AGOTADO",IF(G8<=H8,"BAJO","NORMAL"))) | J8: =IFERROR(SUMPRODUCT((Ventas!C4:C203=A8)*Ventas!H4:H203),0)
A9: =IF(B9="","","PROD-"&TEXT(ROW()-3,"0000")) | F9: =IFERROR((E9-D9)/D9,0) | I9: =IF(B9="","",IF(G9=0,"AGOTADO",IF(G9<=H9,"BAJO","NORMAL"))) | J9: =IFERROR(SUMPRODUCT((Ventas!C4:C203=A9)*Ventas!H4:H203),0)
A10: =IF(B10="","","PROD-"&TEXT(ROW()-3,"0000")) | F10: =IFERROR((E10-D10)/D10,0) | I10: =IF(B10="","",IF(G10=0,"AGOTADO",IF(G10<=H10,"BAJO","NORMAL"))) | J10: =IFERROR(SUMPRODUCT((Ventas!C4:C203=A10)*Ventas!H4:H203),0)
A11: =IF(B11="","","PROD-"&TEXT(ROW()-3,"0000")) | F11: =IFERROR((E11-D11)/D11,0) | I11: =IF(B11="","",IF(G11=0,"AGOTADO",IF(G11<=H11,"BAJO","NORMAL"))) | J11: =IFERROR(SUMPRODUCT((Ventas!C4:C203=A11)*Ventas!H4:H203),0)
A12: =IF(B12="","","PROD-"&TEXT(ROW()-3,"0000")) | F12: =IFERROR((E12-D12)/D12,0) | I12: =IF(B12="","",IF(G12=0,"AGOTADO",IF(G12<=H12,"BAJO","NORMAL"))) | J12: =IFERROR(SUMPRODUCT((Ventas!C4:C203=A12)*Ventas!H4:H203),0)
A13: =IF(B13="","","PROD-"&TEXT(ROW()-3,"0000")) | F13: =IFERROR((E13-D13)/D13,0) | I13: =IF(B13="","",IF(G13=0,"AGOTADO",IF(G13<=H13,"BAJO","NORMAL"))) | J13: =IFERROR(SUMPRODUCT((Ventas!C4:C203=A13)*Ventas!H4:H203),0)
A14: =IF(B14="","","PROD-"&TEXT(ROW()-3,"0000")) | F14: =IFERROR((E14-D14)/D14,0) | I14: =IF(B14="","",IF(G14=0,"AGOTADO",IF(G14<=H14,"BAJO","NORMAL"))) | J14: =IFERROR(SUMPRODUCT((Ventas!C4:C203=A14)*Ventas!H4:H203),0)
A15: =IF(B15="","","PROD-"&TEXT(ROW()-3,"0000")) | F15: =IFERROR((E15-D15)/D15,0) | I15: =IF(B15="","",IF(G15=0,"AGOTADO",IF(G15<=H15,"BAJO","NORMAL"))) | J15: =IFERROR(SUMPRODUCT((Ventas!C4:C203=A15)*Ventas!H4:H203),0)
A16: =IF(B16="","","PROD-"&TEXT(ROW()-3,"0000")) | F16: =IFERROR((E16-D16)/D16,0) | I16: =IF(B16="","",IF(G16=0,"AGOTADO",IF(G16<=H16,"BAJO","NORMAL"))) | J16: =IFERROR(SUMPRODUCT((Ventas!C4:C203=A16)*Ventas!H4:H203),0)
A17: =IF(B17="","","PROD-"&TEXT(ROW()-3,"0000")) | F17: =IFERROR((E17-D17)/D17,0) | I17: =IF(B17="","",IF(G17=0,"AGOTADO",IF(G17<=H17,"BAJO","NORMAL"))) | J17: =IFERROR(SUMPRODUCT((Ventas!C4:C203=A17)*Ventas!H4:H203),0)
A18: =IF(B18="","","PROD-"&TEXT(ROW()-3,"0000")) | F18: =IFERROR((E18-D18)/D18,0) | I18: =IF(B18="","",IF(G18=0,"AGOTADO",IF(G18<=H18,"BAJO","NORMAL"))) | J18: =IFERROR(SUMPRODUCT((Ventas!C4:C203=A18)*Ventas!H4:H203),0)
A19: =IF(B19="","","PROD-"&TEXT(ROW()-3,"0000")) | F19: =IFERROR((E19-D19)/D19,0) | I19: =IF(B19="","",IF(G19=0,"AGOTADO",IF(G19<=H19,"BAJO","NORMAL"))) | J19: =IFERROR(SUMPRODUCT((Ventas!C4:C203=A19)*Ventas!H4:H203),0)
A20: =IF(B20="","","PROD-"&TEXT(ROW()-3,"0000")) | F20: =IFERROR((E20-D20)/D20,0) | I20: =IF(B20="","",IF(G20=0,"AGOTADO",IF(G20<=H20,"BAJO","NORMAL"))) | J20: =IFERROR(SUMPRODUCT((Ventas!C4:C203=A20)*Ventas!H4:H203),0)
A21: =IF(B21="","","PROD-"&TEXT(ROW()-3,"0000")) | F21: =IFERROR((E21-D21)/D21,0) | I21: =IF(B21="","",IF(G21=0,"AGOTADO",IF(G21<=H21,"BAJO","NORMAL"))) | J21: =IFERROR(SUMPRODUCT((Ventas!C4:C203=A21)*Ventas!H4:H203),0)
A22: =IF(B22="","","PROD-"&TEXT(ROW()-3,"0000")) | F22: =IFERROR((E22-D22)/D22,0) | I22: =IF(B22="","",IF(G22=0,"AGOTADO",IF(G22<=H22,"BAJO","NORMAL"))) | J22: =IFERROR(SUMPRODUCT((Ventas!C4:C203=A22)*Ventas!H4:H203),0)
A23: =IF(B23="","","PROD-"&TEXT(ROW()-3,"0000")) | F23: =IFERROR((E23-D23)/D23,0) | I23: =IF(B23="","",IF(G23=0,"AGOTADO",IF(G23<=H23,"BAJO","NORMAL"))) | J23: =IFERROR(SUMPRODUCT((Ventas!C4:C203=A23)*Ventas!H4:H203),0)
A24: =IF(B24="","","PROD-"&TEXT(ROW()-3,"0000")) | F24: =IFERROR((E24-D24)/D24,0) | I24: =IF(B24="","",IF(G24=0,"AGOTADO",IF(G24<=H24,"BAJO","NORMAL"))) | J24: =IFERROR(SUMPRODUCT((Ventas!C4:C203=A24)*Ventas!H4:H203),0)
A25: =IF(B25="","","PROD-"&TEXT(ROW()-3,"0000")) | F25: =IFERROR((E25-D25)/D25,0) | I25: =IF(B25="","",IF(G25=0,"AGOTADO",IF(G25<=H25,"BAJO","NORMAL"))) | J25: =IFERROR(SUMPRODUCT((Ventas!C4:C203=A25)*Ventas!H4:H203),0)
A26: =IF(B26="","","PROD-"&TEXT(ROW()-3,"0000")) | F26: =IFERROR((E26-D26)/D26,0) | I26: =IF(B26="","",IF(G26=0,"AGOTADO",IF(G26<=H26,"BAJO","NORMAL"))) | J26: =IFERROR(SUMPRODUCT((Ventas!C4:C203=A26)*Ventas!H4:H203),0)
A27: =IF(B27="","","PROD-"&TEXT(ROW()-3,"0000")) | F27: =IFERROR((E27-D27)/D27,0) | I27: =IF(B27="","",IF(G27=0,"AGOTADO",IF(G27<=H27,"BAJO","NORMAL"))) | J27: =IFERROR(SUMPRODUCT((Ventas!C4:C203=A27)*Ventas!H4:H203),0)
A28: =IF(B28="","","PROD-"&TEXT(ROW()-3,"0000")) | F28: =IFERROR((E28-D28)/D28,0) | I28: =IF(B28="","",IF(G28=0,"AGOTADO",IF(G28<=H28,"BAJO","NORMAL"))) | J28: =IFERROR(SUMPRODUCT((Ventas!C4:C203=A28)*Ventas!H4:H203),0)
A29: =IF(B29="","","PROD-"&TEXT(ROW()-3,"0000")) | F29: =IFERROR((E29-D29)/D29,0) | I29: =IF(B29="","",IF(G29=0,"AGOTADO",IF(G29<=H29,"BAJO","NORMAL"))) | J29: =IFERROR(SUMPRODUCT((Ventas!C4:C203=A29)*Ventas!H4:H203),0)
A30: =IF(B30="","","PROD-"&TEXT(ROW()-3,"0000")) | F30: =IFERROR((E30-D30)/D30,0) | I30: =IF(B30="","",IF(G30=0,"AGOTADO",IF(G30<=H30,"BAJO","NORMAL"))) | J30: =IFERROR(SUMPRODUCT((Ventas!C4:C203=A30)*Ventas!H4:H203),0)
A31: =IF(B31="","","PROD-"&TEXT(ROW()-3,"0000")) | F31: =IFERROR((E31-D31)/D31,0) | I31: =IF(B31="","",IF(G31=0,"AGOTADO",IF(G31<=H31,"BAJO","NORMAL"))) | J31: =IFERROR(SUMPRODUCT((Ventas!C4:C203=A31)*Ventas!H4:H203),0)
A32: =IF(B32="","","PROD-"&TEXT(ROW()-3,"0000")) | F32: =IFERROR((E32-D32)/D32,0) | I32: =IF(B32="","",IF(G32=0,"AGOTADO",IF(G32<=H32,"BAJO","NORMAL"))) | J32: =IFERROR(SUMPRODUCT((Ventas!C4:C203=A32)*Ventas!H4:H203),0)
A33: =IF(B33="","","PROD-"&TEXT(ROW()-3,"0000")) | F33: =IFERROR((E33-D33)/D33,0) | I33: =IF(B33="","",IF(G33=0,"AGOTADO",IF(G33<=H33,"BAJO","NORMAL"))) | J33: =IFERROR(SUMPRODUCT((Ventas!C4:C203=A33)*Ventas!H4:H203),0)
A34: =IF(B34="","","PROD-"&TEXT(ROW()-3,"0000")) | F34: =IFERROR((E34-D34)/D34,0) | I34: =IF(B34="","",IF(G34=0,"AGOTADO",IF(G34<=H34,"BAJO","NORMAL"))) | J34: =IFERROR(SUMPRODUCT((Ventas!C4:C203=A34)*Ventas!H4:H203),0)
A35: =IF(B35="","","PROD-"&TEXT(ROW()-3,"0000")) | F35: =IFERROR((E35-D35)/D35,0) | I35: =IF(B35="","",IF(G35=0,"AGOTADO",IF(G35<=H35,"BAJO","NORMAL"))) | J35: =IFERROR(SUMPRODUCT((Ventas!C4:C203=A35)*Ventas!H4:H203),0)
A36: =IF(B36="","","PROD-"&TEXT(ROW()-3,"0000")) | F36: =IFERROR((E36-D36)/D36,0) | I36: =IF(B36="","",IF(G36=0,"AGOTADO",IF(G36<=H36,"BAJO","NORMAL"))) | J36: =IFERROR(SUMPRODUCT((Ventas!C4:C203=A36)*Ventas!H4:H203),0)
A37: =IF(B37="","","PROD-"&TEXT(ROW()-3,"0000")) | F37: =IFERROR((E37-D37)/D37,0) | I37: =IF(B37="","",IF(G37=0,"AGOTADO",IF(G37<=H37,"BAJO","NORMAL"))) | J37: =IFERROR(SUMPRODUCT((Ventas!C4:C203=A37)*Ventas!H4:H203),0)
A38: =IF(B38="","","PROD-"&TEXT(ROW()-3,"0000")) | F38: =IFERROR((E38-D38)/D38,0) | I38: =IF(B38="","",IF(G38=0,"AGOTADO",IF(G38<=H38,"BAJO","NORMAL"))) | J38: =IFERROR(SUMPRODUCT((Ventas!C4:C203=A38)*Ventas!H4:H203),0)
A39: =IF(B39="","","PROD-"&TEXT(ROW()-3,"0000")) | F39: =IFERROR((E39-D39)/D39,0) | I39: =IF(B39="","",IF(G39=0,"AGOTADO",IF(G39<=H39,"BAJO","NORMAL"))) | J39: =IFERROR(SUMPRODUCT((Ventas!C4:C203=A39)*Ventas!H4:H203),0)
A40: =IF(B40="","","PROD-"&TEXT(ROW()-3,"0000")) | F40: =IFERROR((E40-D40)/D40,0) | I40: =IF(B40="","",IF(G40=0,"AGOTADO",IF(G40<=H40,"BAJO","NORMAL"))) | J40: =IFERROR(SUMPRODUCT((Ventas!C4:C203=A40)*Ventas!H4:H203),0)
A41: =IF(B41="","","PROD-"&TEXT(ROW()-3,"0000")) | F41: =IFERROR((E41-D41)/D41,0) | I41: =IF(B41="","",IF(G41=0,"AGOTADO",IF(G41<=H41,"BAJO","NORMAL"))) | J41: =IFERROR(SUMPRODUCT((Ventas!C4:C203=A41)*Ventas!H4:H203),0)
A42: =IF(B42="","","PROD-"&TEXT(ROW()-3,"0000")) | F42: =IFERROR((E42-D42)/D42,0) | I42: =IF(B42="","",IF(G42=0,"AGOTADO",IF(G42<=H42,"BAJO","NORMAL"))) | J42: =IFERROR(SUMPRODUCT((Ventas!C4:C203=A42)*Ventas!H4:H203),0)
A43: =IF(B43="","","PROD-"&TEXT(ROW()-3,"0000")) | F43: =IFERROR((E43-D43)/D43,0) | I43: =IF(B43="","",IF(G43=0,"AGOTADO",IF(G43<=H43,"BAJO","NORMAL"))) | J43: =IFERROR(SUMPRODUCT((Ventas!C4:C203=A43)*Ventas!H4:H203),0)
A44: =IF(B44="","","PROD-"&TEXT(ROW()-3,"0000")) | F44: =IFERROR((E44-D44)/D44,0) | I44: =IF(B44="","",IF(G44=0,"AGOTADO",IF(G44<=H44,"BAJO","NORMAL"))) | J44: =IFERROR(SUMPRODUCT((Ventas!C4:C203=A44)*Ventas!H4:H203),0)
A45: =IF(B45="","","PROD-"&TEXT(ROW()-3,"0000")) | F45: =IFERROR((E45-D45)/D45,0) | I45: =IF(B45="","",IF(G45=0,"AGOTADO",IF(G45<=H45,"BAJO","NORMAL"))) | J45: =IFERROR(SUMPRODUCT((Ventas!C4:C203=A45)*Ventas!H4:H203),0)
A46: =IF(B46="","","PROD-"&TEXT(ROW()-3,"0000")) | F46: =IFERROR((E46-D46)/D46,0) | I46: =IF(B46="","",IF(G46=0,"AGOTADO",IF(G46<=H46,"BAJO","NORMAL"))) | J46: =IFERROR(SUMPRODUCT((Ventas!C4:C203=A46)*Ventas!H4:H203),0)
A47: =IF(B47="","","PROD-"&TEXT(ROW()-3,"0000")) | F47: =IFERROR((E47-D47)/D47,0) | I47: =IF(B47="","",IF(G47=0,"AGOTADO",IF(G47<=H47,"BAJO","NORMAL"))) | J47: =IFERROR(SUMPRODUCT((Ventas!C4:C203=A47)*Ventas!H4:H203),0)
A48: =IF(B48="","","PROD-"&TEXT(ROW()-3,"0000")) | F48: =IFERROR((E48-D48)/D48,0) | I48: =IF(B48="","",IF(G48=0,"AGOTADO",IF(G48<=H48,"BAJO","NORMAL"))) | J48: =IFERROR(SUMPRODUCT((Ventas!C4:C203=A48)*Ventas!H4:H203),0)
A49: =IF(B49="","","PROD-"&TEXT(ROW()-3,"0000")) | F49: =IFERROR((E49-D49)/D49,0) | I49: =IF(B49="","",IF(G49=0,"AGOTADO",IF(G49<=H49,"BAJO","NORMAL"))) | J49: =IFERROR(SUMPRODUCT((Ventas!C4:C203=A49)*Ventas!H4:H203),0)
A50: =IF(B50="","","PROD-"&TEXT(ROW()-3,"0000")) | F50: =IFERROR((E50-D50)/D50,0) | I50: =IF(B50="","",IF(G50=0,"AGOTADO",IF(G50<=H50,"BAJO","NORMAL"))) | J50: =IFERROR(SUMPRODUCT((Ventas!C4:C203=A50)*Ventas!H4:H203),0)
A51: =IF(B51="","","PROD-"&TEXT(ROW()-3,"0000")) | F51: =IFERROR((E51-D51)/D51,0) | I51: =IF(B51="","",IF(G51=0,"AGOTADO",IF(G51<=H51,"BAJO","NORMAL"))) | J51: =IFERROR(SUMPRODUCT((Ventas!C4:C203=A51)*Ventas!H4:H203),0)
A52: =IF(B52="","","PROD-"&TEXT(ROW()-3,"0000")) | F52: =IFERROR((E52-D52)/D52,0) | I52: =IF(B52="","",IF(G52=0,"AGOTADO",IF(G52<=H52,"BAJO","NORMAL"))) | J52: =IFERROR(SUMPRODUCT((Ventas!C4:C203=A52)*Ventas!H4:H203),0)
A53: =IF(B53="","","PROD-"&TEXT(ROW()-3,"0000")) | F53: =IFERROR((E53-D53)/D53,0) | I53: =IF(B53="","",IF(G53=0,"AGOTADO",IF(G53<=H53,"BAJO","NORMAL"))) | J53: =IFERROR(SUMPRODUCT((Ventas!C4:C203=A53)*Ventas!H4:H203),0)
A54: =IF(B54="","","PROD-"&TEXT(ROW()-3,"0000")) | F54: =IFERROR((E54-D54)/D54,0) | I54: =IF(B54="","",IF(G54=0,"AGOTADO",IF(G54<=H54,"BAJO","NORMAL"))) | J54: =IFERROR(SUMPRODUCT((Ventas!C4:C203=A54)*Ventas!H4:H203),0)
A55: =IF(B55="","","PROD-"&TEXT(ROW()-3,"0000")) | F55: =IFERROR((E55-D55)/D55,0) | I55: =IF(B55="","",IF(G55=0,"AGOTADO",IF(G55<=H55,"BAJO","NORMAL"))) | J55: =IFERROR(SUMPRODUCT((Ventas!C4:C203=A55)*Ventas!H4:H203),0)
A56: =IF(B56="","","PROD-"&TEXT(ROW()-3,"0000")) | F56: =IFERROR((E56-D56)/D56,0) | I56: =IF(B56="","",IF(G56=0,"AGOTADO",IF(G56<=H56,"BAJO","NORMAL"))) | J56: =IFERROR(SUMPRODUCT((Ventas!C4:C203=A56)*Ventas!H4:H203),0)
A57: =IF(B57="","","PROD-"&TEXT(ROW()-3,"0000")) | F57: =IFERROR((E57-D57)/D57,0) | I57: =IF(B57="","",IF(G57=0,"AGOTADO",IF(G57<=H57,"BAJO","NORMAL"))) | J57: =IFERROR(SUMPRODUCT((Ventas!C4:C203=A57)*Ventas!H4:H203),0)
A58: =IF(B58="","","PROD-"&TEXT(ROW()-3,"0000")) | F58: =IFERROR((E58-D58)/D58,0) | I58: =IF(B58="","",IF(G58=0,"AGOTADO",IF(G58<=H58,"BAJO","NORMAL"))) | J58: =IFERROR(SUMPRODUCT((Ventas!C4:C203=A58)*Ventas!H4:H203),0)
A59: =IF(B59="","","PROD-"&TEXT(ROW()-3,"0000")) | F59: =IFERROR((E59-D59)/D59,0) | I59: =IF(B59="","",IF(G59=0,"AGOTADO",IF(G59<=H59,"BAJO","NORMAL"))) | J59: =IFERROR(SUMPRODUCT((Ventas!C4:C203=A59)*Ventas!H4:H203),0)
A60: =IF(B60="","","PROD-"&TEXT(ROW()-3,"0000")) | F60: =IFERROR((E60-D60)/D60,0) | I60: =IF(B60="","",IF(G60=0,"AGOTADO",IF(G60<=H60,"BAJO","NORMAL"))) | J60: =IFERROR(SUMPRODUCT((Ventas!C4:C203=A60)*Ventas!H4:H203),0)
A61: =IF(B61="","","PROD-"&TEXT(ROW()-3,"0000")) | F61: =IFERROR((E61-D61)/D61,0) | I61: =IF(B61="","",IF(G61=0,"AGOTADO",IF(G61<=H61,"BAJO","NORMAL"))) | J61: =IFERROR(SUMPRODUCT((Ventas!C4:C203=A61)*Ventas!H4:H203),0)
A62: =IF(B62="","","PROD-"&TEXT(ROW()-3,"0000")) | F62: =IFERROR((E62-D62)/D62,0) | I62: =IF(B62="","",IF(G62=0,"AGOTADO",IF(G62<=H62,"BAJO","NORMAL"))) | J62: =IFERROR(SUMPRODUCT((Ventas!C4:C203=A62)*Ventas!H4:H203),0)
A63: =IF(B63="","","PROD-"&TEXT(ROW()-3,"0000")) | F63: =IFERROR((E63-D63)/D63,0) | I63: =IF(B63="","",IF(G63=0,"AGOTADO",IF(G63<=H63,"BAJO","NORMAL"))) | J63: =IFERROR(SUMPRODUCT((Ventas!C4:C203=A63)*Ventas!H4:H203),0)
A64: =IF(B64="","","PROD-"&TEXT(ROW()-3,"0000")) | F64: =IFERROR((E64-D64)/D64,0) | I64: =IF(B64="","",IF(G64=0,"AGOTADO",IF(G64<=H64,"BAJO","NORMAL"))) | J64: =IFERROR(SUMPRODUCT((Ventas!C4:C203=A64)*Ventas!H4:H203),0)
A65: =IF(B65="","","PROD-"&TEXT(ROW()-3,"0000")) | F65: =IFERROR((E65-D65)/D65,0) | I65: =IF(B65="","",IF(G65=0,"AGOTADO",IF(G65<=H65,"BAJO","NORMAL"))) | J65: =IFERROR(SUMPRODUCT((Ventas!C4:C203=A65)*Ventas!H4:H203),0)
A66: =IF(B66="","","PROD-"&TEXT(ROW()-3,"0000")) | F66: =IFERROR((E66-D66)/D66,0) | I66: =IF(B66="","",IF(G66=0,"AGOTADO",IF(G66<=H66,"BAJO","NORMAL"))) | J66: =IFERROR(SUMPRODUCT((Ventas!C4:C203=A66)*Ventas!H4:H203),0)
A67: =IF(B67="","","PROD-"&TEXT(ROW()-3,"0000")) | F67: =IFERROR((E67-D67)/D67,0) | I67: =IF(B67="","",IF(G67=0,"AGOTADO",IF(G67<=H67,"BAJO","NORMAL"))) | J67: =IFERROR(SUMPRODUCT((Ventas!C4:C203=A67)*Ventas!H4:H203),0)
A68: =IF(B68="","","PROD-"&TEXT(ROW()-3,"0000")) | F68: =IFERROR((E68-D68)/D68,0) | I68: =IF(B68="","",IF(G68=0,"AGOTADO",IF(G68<=H68,"BAJO","NORMAL"))) | J68: =IFERROR(SUMPRODUCT((Ventas!C4:C203=A68)*Ventas!H4:H203),0)
A69: =IF(B69="","","PROD-"&TEXT(ROW()-3,"0000")) | F69: =IFERROR((E69-D69)/D69,0) | I69: =IF(B69="","",IF(G69=0,"AGOTADO",IF(G69<=H69,"BAJO","NORMAL"))) | J69: =IFERROR(SUMPRODUCT((Ventas!C4:C203=A69)*Ventas!H4:H203),0)
A70: =IF(B70="","","PROD-"&TEXT(ROW()-3,"0000")) | F70: =IFERROR((E70-D70)/D70,0) | I70: =IF(B70="","",IF(G70=0,"AGOTADO",IF(G70<=H70,"BAJO","NORMAL"))) | J70: =IFERROR(SUMPRODUCT((Ventas!C4:C203=A70)*Ventas!H4:H203),0)
A71: =IF(B71="","","PROD-"&TEXT(ROW()-3,"0000")) | F71: =IFERROR((E71-D71)/D71,0) | I71: =IF(B71="","",IF(G71=0,"AGOTADO",IF(G71<=H71,"BAJO","NORMAL"))) | J71: =IFERROR(SUMPRODUCT((Ventas!C4:C203=A71)*Ventas!H4:H203),0)
A72: =IF(B72="","","PROD-"&TEXT(ROW()-3,"0000")) | F72: =IFERROR((E72-D72)/D72,0) | I72: =IF(B72="","",IF(G72=0,"AGOTADO",IF(G72<=H72,"BAJO","NORMAL"))) | J72: =IFERROR(SUMPRODUCT((Ventas!C4:C203=A72)*Ventas!H4:H203),0)
A73: =IF(B73="","","PROD-"&TEXT(ROW()-3,"0000")) | F73: =IFERROR((E73-D73)/D73,0) | I73: =IF(B73="","",IF(G73=0,"AGOTADO",IF(G73<=H73,"BAJO","NORMAL"))) | J73: =IFERROR(SUMPRODUCT((Ventas!C4:C203=A73)*Ventas!H4:H203),0)
A74: =IF(B74="","","PROD-"&TEXT(ROW()-3,"0000")) | F74: =IFERROR((E74-D74)/D74,0) | I74: =IF(B74="","",IF(G74=0,"AGOTADO",IF(G74<=H74,"BAJO","NORMAL"))) | J74: =IFERROR(SUMPRODUCT((Ventas!C4:C203=A74)*Ventas!H4:H203),0)
A75: =IF(B75="","","PROD-"&TEXT(ROW()-3,"0000")) | F75: =IFERROR((E75-D75)/D75,0) | I75: =IF(B75="","",IF(G75=0,"AGOTADO",IF(G75<=H75,"BAJO","NORMAL"))) | J75: =IFERROR(SUMPRODUCT((Ventas!C4:C203=A75)*Ventas!H4:H203),0)
A76: =IF(B76="","","PROD-"&TEXT(ROW()-3,"0000")) | F76: =IFERROR((E76-D76)/D76,0) | I76: =IF(B76="","",IF(G76=0,"AGOTADO",IF(G76<=H76,"BAJO","NORMAL"))) | J76: =IFERROR(SUMPRODUCT((Ventas!C4:C203=A76)*Ventas!H4:H203),0)
A77: =IF(B77="","","PROD-"&TEXT(ROW()-3,"0000")) | F77: =IFERROR((E77-D77)/D77,0) | I77: =IF(B77="","",IF(G77=0,"AGOTADO",IF(G77<=H77,"BAJO","NORMAL"))) | J77: =IFERROR(SUMPRODUCT((Ventas!C4:C203=A77)*Ventas!H4:H203),0)
A78: =IF(B78="","","PROD-"&TEXT(ROW()-3,"0000")) | F78: =IFERROR((E78-D78)/D78,0) | I78: =IF(B78="","",IF(G78=0,"AGOTADO",IF(G78<=H78,"BAJO","NORMAL"))) | J78: =IFERROR(SUMPRODUCT((Ventas!C4:C203=A78)*Ventas!H4:H203),0)
A79: =IF(B79="","","PROD-"&TEXT(ROW()-3,"0000")) | F79: =IFERROR((E79-D79)/D79,0) | I79: =IF(B79="","",IF(G79=0,"AGOTADO",IF(G79<=H79,"BAJO","NORMAL"))) | J79: =IFERROR(SUMPRODUCT((Ventas!C4:C203=A79)*Ventas!H4:H203),0)
A80: =IF(B80="","","PROD-"&TEXT(ROW()-3,"0000")) | F80: =IFERROR((E80-D80)/D80,0) | I80: =IF(B80="","",IF(G80=0,"AGOTADO",IF(G80<=H80,"BAJO","NORMAL"))) | J80: =IFERROR(SUMPRODUCT((Ventas!C4:C203=A80)*Ventas!H4:H203),0)
A81: =IF(B81="","","PROD-"&TEXT(ROW()-3,"0000")) | F81: =IFERROR((E81-D81)/D81,0) | I81: =IF(B81="","",IF(G81=0,"AGOTADO",IF(G81<=H81,"BAJO","NORMAL"))) | J81: =IFERROR(SUMPRODUCT((Ventas!C4:C203=A81)*Ventas!H4:H203),0)
A82: =IF(B82="","","PROD-"&TEXT(ROW()-3,"0000")) | F82: =IFERROR((E82-D82)/D82,0) | I82: =IF(B82="","",IF(G82=0,"AGOTADO",IF(G82<=H82,"BAJO","NORMAL"))) | J82: =IFERROR(SUMPRODUCT((Ventas!C4:C203=A82)*Ventas!H4:H203),0)
A83: =IF(B83="","","PROD-"&TEXT(ROW()-3,"0000")) | F83: =IFERROR((E83-D83)/D83,0) | I83: =IF(B83="","",IF(G83=0,"AGOTADO",IF(G83<=H83,"BAJO","NORMAL"))) | J83: =IFERROR(SUMPRODUCT((Ventas!C4:C203=A83)*Ventas!H4:H203),0)
A84: =IF(B84="","","PROD-"&TEXT(ROW()-3,"0000")) | F84: =IFERROR((E84-D84)/D84,0) | I84: =IF(B84="","",IF(G84=0,"AGOTADO",IF(G84<=H84,"BAJO","NORMAL"))) | J84: =IFERROR(SUMPRODUCT((Ventas!C4:C203=A84)*Ventas!H4:H203),0)
A85: =IF(B85="","","PROD-"&TEXT(ROW()-3,"0000")) | F85: =IFERROR((E85-D85)/D85,0) | I85: =IF(B85="","",IF(G85=0,"AGOTADO",IF(G85<=H85,"BAJO","NORMAL"))) | J85: =IFERROR(SUMPRODUCT((Ventas!C4:C203=A85)*Ventas!H4:H203),0)
A86: =IF(B86="","","PROD-"&TEXT(ROW()-3,"0000")) | F86: =IFERROR((E86-D86)/D86,0) | I86: =IF(B86="","",IF(G86=0,"AGOTADO",IF(G86<=H86,"BAJO","NORMAL"))) | J86: =IFERROR(SUMPRODUCT((Ventas!C4:C203=A86)*Ventas!H4:H203),0)
A87: =IF(B87="","","PROD-"&TEXT(ROW()-3,"0000")) | F87: =IFERROR((E87-D87)/D87,0) | I87: =IF(B87="","",IF(G87=0,"AGOTADO",IF(G87<=H87,"BAJO","NORMAL"))) | J87: =IFERROR(SUMPRODUCT((Ventas!C4:C203=A87)*Ventas!H4:H203),0)
A88: =IF(B88="","","PROD-"&TEXT(ROW()-3,"0000")) | F88: =IFERROR((E88-D88)/D88,0) | I88: =IF(B88="","",IF(G88=0,"AGOTADO",IF(G88<=H88,"BAJO","NORMAL"))) | J88: =IFERROR(SUMPRODUCT((Ventas!C4:C203=A88)*Ventas!H4:H203),0)
A89: =IF(B89="","","PROD-"&TEXT(ROW()-3,"0000")) | F89: =IFERROR((E89-D89)/D89,0) | I89: =IF(B89="","",IF(G89=0,"AGOTADO",IF(G89<=H89,"BAJO","NORMAL"))) | J89: =IFERROR(SUMPRODUCT((Ventas!C4:C203=A89)*Ventas!H4:H203),0)
A90: =IF(B90="","","PROD-"&TEXT(ROW()-3,"0000")) | F90: =IFERROR((E90-D90)/D90,0) | I90: =IF(B90="","",IF(G90=0,"AGOTADO",IF(G90<=H90,"BAJO","NORMAL"))) | J90: =IFERROR(SUMPRODUCT((Ventas!C4:C203=A90)*Ventas!H4:H203),0)
A91: =IF(B91="","","PROD-"&TEXT(ROW()-3,"0000")) | F91: =IFERROR((E91-D91)/D91,0) | I91: =IF(B91="","",IF(G91=0,"AGOTADO",IF(G91<=H91,"BAJO","NORMAL"))) | J91: =IFERROR(SUMPRODUCT((Ventas!C4:C203=A91)*Ventas!H4:H203),0)
A92: =IF(B92="","","PROD-"&TEXT(ROW()-3,"0000")) | F92: =IFERROR((E92-D92)/D92,0) | I92: =IF(B92="","",IF(G92=0,"AGOTADO",IF(G92<=H92,"BAJO","NORMAL"))) | J92: =IFERROR(SUMPRODUCT((Ventas!C4:C203=A92)*Ventas!H4:H203),0)
A93: =IF(B93="","","PROD-"&TEXT(ROW()-3,"0000")) | F93: =IFERROR((E93-D93)/D93,0) | I93: =IF(B93="","",IF(G93=0,"AGOTADO",IF(G93<=H93,"BAJO","NORMAL"))) | J93: =IFERROR(SUMPRODUCT((Ventas!C4:C203=A93)*Ventas!H4:H203),0)
A94: =IF(B94="","","PROD-"&TEXT(ROW()-3,"0000")) | F94: =IFERROR((E94-D94)/D94,0) | I94: =IF(B94="","",IF(G94=0,"AGOTADO",IF(G94<=H94,"BAJO","NORMAL"))) | J94: =IFERROR(SUMPRODUCT((Ventas!C4:C203=A94)*Ventas!H4:H203),0)
A95: =IF(B95="","","PROD-"&TEXT(ROW()-3,"0000")) | F95: =IFERROR((E95-D95)/D95,0) | I95: =IF(B95="","",IF(G95=0,"AGOTADO",IF(G95<=H95,"BAJO","NORMAL"))) | J95: =IFERROR(SUMPRODUCT((Ventas!C4:C203=A95)*Ventas!H4:H203),0)
A96: =IF(B96="","","PROD-"&TEXT(ROW()-3,"0000")) | F96: =IFERROR((E96-D96)/D96,0) | I96: =IF(B96="","",IF(G96=0,"AGOTADO",IF(G96<=H96,"BAJO","NORMAL"))) | J96: =IFERROR(SUMPRODUCT((Ventas!C4:C203=A96)*Ventas!H4:H203),0)
A97: =IF(B97="","","PROD-"&TEXT(ROW()-3,"0000")) | F97: =IFERROR((E97-D97)/D97,0) | I97: =IF(B97="","",IF(G97=0,"AGOTADO",IF(G97<=H97,"BAJO","NORMAL"))) | J97: =IFERROR(SUMPRODUCT((Ventas!C4:C203=A97)*Ventas!H4:H203),0)
A98: =IF(B98="","","PROD-"&TEXT(ROW()-3,"0000")) | F98: =IFERROR((E98-D98)/D98,0) | I98: =IF(B98="","",IF(G98=0,"AGOTADO",IF(G98<=H98,"BAJO","NORMAL"))) | J98: =IFERROR(SUMPRODUCT((Ventas!C4:C203=A98)*Ventas!H4:H203),0)
A99: =IF(B99="","","PROD-"&TEXT(ROW()-3,"0000")) | F99: =IFERROR((E99-D99)/D99,0) | I99: =IF(B99="","",IF(G99=0,"AGOTADO",IF(G99<=H99,"BAJO","NORMAL"))) | J99: =IFERROR(SUMPRODUCT((Ventas!C4:C203=A99)*Ventas!H4:H203),0)
A100: =IF(B100="","","PROD-"&TEXT(ROW()-3,"0000")) | F100: =IFERROR((E100-D100)/D100,0) | I100: =IF(B100="","",IF(G100=0,"AGOTADO",IF(G100<=H100,"BAJO","NORMAL"))) | J100: =IFERROR(SUMPRODUCT((Ventas!C4:C203=A100)*Ventas!H4:H203),0)
...

Sheet Ventas
A1: REGISTRO DE VENTAS
A2: Ingresa el código del producto en la columna C. El nombre y precio se llenan automáticamente (VLOOKUP).
A3: FECHA | B3: # VENTA | C3: CÓDIGO PROD. | D3: PRODUCTO (auto) | E3: CANT. | F3: PRECIO UNIT. (auto) | G3: DESC. (%) | H3: TOTAL (Bs.) | I3: MÉTODO PAGO | J3: VENDEDOR
A4: 45672 | B4: =IF(A4="","",ROW()-3) | C4: PROD-0001 | D4: =IFERROR(VLOOKUP(C4,Productos!A4:B103,2,FALSE),"") | E4: 3 | F4: =IFERROR(VLOOKUP(C4,Productos!A4:E103,5,FALSE),0) | G4: 0 | H4: =IFERROR(E4*F4*(1-G4),0) | I4: Efectivo | J4: Ana
A5: 45672 | B5: =IF(A5="","",ROW()-3) | C5: PROD-0002 | D5: =IFERROR(VLOOKUP(C5,Productos!A4:B103,2,FALSE),"") | E5: 10 | F5: =IFERROR(VLOOKUP(C5,Productos!A4:E103,5,FALSE),0) | G5: 0.05 | H5: =IFERROR(E5*F5*(1-G5),0) | I5: QR | J5: Carlos
A6: 45673 | B6: =IF(A6="","",ROW()-3) | C6: PROD-0003 | D6: =IFERROR(VLOOKUP(C6,Productos!A4:B103,2,FALSE),"") | E6: 2 | F6: =IFERROR(VLOOKUP(C6,Productos!A4:E103,5,FALSE),0) | G6: 0 | H6: =IFERROR(E6*F6*(1-G6),0) | I6: Transferencia | J6: Ana
A7: 45673 | B7: =IF(A7="","",ROW()-3) | C7: PROD-0005 | D7: =IFERROR(VLOOKUP(C7,Productos!A4:B103,2,FALSE),"") | E7: 4 | F7: =IFERROR(VLOOKUP(C7,Productos!A4:E103,5,FALSE),0) | G7: 0.1 | H7: =IFERROR(E7*F7*(1-G7),0) | I7: Tarjeta | J7: María
A8: 45674 | B8: =IF(A8="","",ROW()-3) | C8: PROD-0001 | D8: =IFERROR(VLOOKUP(C8,Productos!A4:B103,2,FALSE),"") | E8: 5 | F8: =IFERROR(VLOOKUP(C8,Productos!A4:E103,5,FALSE),0) | G8: 0 | H8: =IFERROR(E8*F8*(1-G8),0) | I8: Efectivo | J8: Carlos
A9: 45674 | B9: =IF(A9="","",ROW()-3) | C9: PROD-0004 | D9: =IFERROR(VLOOKUP(C9,Productos!A4:B103,2,FALSE),"") | E9: 2 | F9: =IFERROR(VLOOKUP(C9,Productos!A4:E103,5,FALSE),0) | G9: 0 | H9: =IFERROR(E9*F9*(1-G9),0) | I9: QR | J9: Ana
A10: 45675 | B10: =IF(A10="","",ROW()-3) | C10: PROD-0002 | D10: =IFERROR(VLOOKUP(C10,Productos!A4:B103,2,FALSE),"") | E10: 8 | F10: =IFERROR(VLOOKUP(C10,Productos!A4:E103,5,FALSE),0) | G10: 0 | H10: =IFERROR(E10*F10*(1-G10),0) | I10: Transferencia | J10: María
A11: 45675 | B11: =IF(A11="","",ROW()-3) | C11: PROD-0005 | D11: =IFERROR(VLOOKUP(C11,Productos!A4:B103,2,FALSE),"") | E11: 3 | F11: =IFERROR(VLOOKUP(C11,Productos!A4:E103,5,FALSE),0) | G11: 0.05 | H11: =IFERROR(E11*F11*(1-G11),0) | I11: Efectivo | J11: Carlos
B12: =IF(A12="","",ROW()-3) | D12: =IFERROR(VLOOKUP(C12,Productos!A4:B103,2,FALSE),"") | F12: =IFERROR(VLOOKUP(C12,Productos!A4:E103,5,FALSE),0) | H12: =IFERROR(E12*F12*(1-G12),0)
B13: =IF(A13="","",ROW()-3) | D13: =IFERROR(VLOOKUP(C13,Productos!A4:B103,2,FALSE),"") | F13: =IFERROR(VLOOKUP(C13,Productos!A4:E103,5,FALSE),0) | H13: =IFERROR(E13*F13*(1-G13),0)
B14: =IF(A14="","",ROW()-3) | D14: =IFERROR(VLOOKUP(C14,Productos!A4:B103,2,FALSE),"") | F14: =IFERROR(VLOOKUP(C14,Productos!A4:E103,5,FALSE),0) | H14: =IFERROR(E14*F14*(1-G14),0)
B15: =IF(A15="","",ROW()-3) | D15: =IFERROR(VLOOKUP(C15,Productos!A4:B103,2,FALSE),"") | F15: =IFERROR(VLOOKUP(C15,Productos!A4:E103,5,FALSE),0) | H15: =IFERROR(E15*F15*(1-G15),0)
B16: =IF(A16="","",ROW()-3) | D16: =IFERROR(VLOOKUP(C16,Productos!A4:B103,2,FALSE),"") | F16: =IFERROR(VLOOKUP(C16,Productos!A4:E103,5,FALSE),0) | H16: =IFERROR(E16*F16*(1-G16),0)
B17: =IF(A17="","",ROW()-3) | D17: =IFERROR(VLOOKUP(C17,Productos!A4:B103,2,FALSE),"") | F17: =IFERROR(VLOOKUP(C17,Productos!A4:E103,5,FALSE),0) | H17: =IFERROR(E17*F17*(1-G17),0)
B18: =IF(A18="","",ROW()-3) | D18: =IFERROR(VLOOKUP(C18,Productos!A4:B103,2,FALSE),"") | F18: =IFERROR(VLOOKUP(C18,Productos!A4:E103,5,FALSE),0) | H18: =IFERROR(E18*F18*(1-G18),0)
B19: =IF(A19="","",ROW()-3) | D19: =IFERROR(VLOOKUP(C19,Productos!A4:B103,2,FALSE),"") | F19: =IFERROR(VLOOKUP(C19,Productos!A4:E103,5,FALSE),0) | H19: =IFERROR(E19*F19*(1-G19),0)
B20: =IF(A20="","",ROW()-3) | D20: =IFERROR(VLOOKUP(C20,Productos!A4:B103,2,FALSE),"") | F20: =IFERROR(VLOOKUP(C20,Productos!A4:E103,5,FALSE),0) | H20: =IFERROR(E20*F20*(1-G20),0)
B21: =IF(A21="","",ROW()-3) | D21: =IFERROR(VLOOKUP(C21,Productos!A4:B103,2,FALSE),"") | F21: =IFERROR(VLOOKUP(C21,Productos!A4:E103,5,FALSE),0) | H21: =IFERROR(E21*F21*(1-G21),0)
B22: =IF(A22="","",ROW()-3) | D22: =IFERROR(VLOOKUP(C22,Productos!A4:B103,2,FALSE),"") | F22: =IFERROR(VLOOKUP(C22,Productos!A4:E103,5,FALSE),0) | H22: =IFERROR(E22*F22*(1-G22),0)
B23: =IF(A23="","",ROW()-3) | D23: =IFERROR(VLOOKUP(C23,Productos!A4:B103,2,FALSE),"") | F23: =IFERROR(VLOOKUP(C23,Productos!A4:E103,5,FALSE),0) | H23: =IFERROR(E23*F23*(1-G23),0)
B24: =IF(A24="","",ROW()-3) | D24: =IFERROR(VLOOKUP(C24,Productos!A4:B103,2,FALSE),"") | F24: =IFERROR(VLOOKUP(C24,Productos!A4:E103,5,FALSE),0) | H24: =IFERROR(E24*F24*(1-G24),0)
B25: =IF(A25="","",ROW()-3) | D25: =IFERROR(VLOOKUP(C25,Productos!A4:B103,2,FALSE),"") | F25: =IFERROR(VLOOKUP(C25,Productos!A4:E103,5,FALSE),0) | H25: =IFERROR(E25*F25*(1-G25),0)
B26: =IF(A26="","",ROW()-3) | D26: =IFERROR(VLOOKUP(C26,Productos!A4:B103,2,FALSE),"") | F26: =IFERROR(VLOOKUP(C26,Productos!A4:E103,5,FALSE),0) | H26: =IFERROR(E26*F26*(1-G26),0)
B27: =IF(A27="","",ROW()-3) | D27: =IFERROR(VLOOKUP(C27,Productos!A4:B103,2,FALSE),"") | F27: =IFERROR(VLOOKUP(C27,Productos!A4:E103,5,FALSE),0) | H27: =IFERROR(E27*F27*(1-G27),0)
B28: =IF(A28="","",ROW()-3) | D28: =IFERROR(VLOOKUP(C28,Productos!A4:B103,2,FALSE),"") | F28: =IFERROR(VLOOKUP(C28,Productos!A4:E103,5,FALSE),0) | H28: =IFERROR(E28*F28*(1-G28),0)
B29: =IF(A29="","",ROW()-3) | D29: =IFERROR(VLOOKUP(C29,Productos!A4:B103,2,FALSE),"") | F29: =IFERROR(VLOOKUP(C29,Productos!A4:E103,5,FALSE),0) | H29: =IFERROR(E29*F29*(1-G29),0)
B30: =IF(A30="","",ROW()-3) | D30: =IFERROR(VLOOKUP(C30,Productos!A4:B103,2,FALSE),"") | F30: =IFERROR(VLOOKUP(C30,Productos!A4:E103,5,FALSE),0) | H30: =IFERROR(E30*F30*(1-G30),0)
B31: =IF(A31="","",ROW()-3) | D31: =IFERROR(VLOOKUP(C31,Productos!A4:B103,2,FALSE),"") | F31: =IFERROR(VLOOKUP(C31,Productos!A4:E103,5,FALSE),0) | H31: =IFERROR(E31*F31*(1-G31),0)
B32: =IF(A32="","",ROW()-3) | D32: =IFERROR(VLOOKUP(C32,Productos!A4:B103,2,FALSE),"") | F32: =IFERROR(VLOOKUP(C32,Productos!A4:E103,5,FALSE),0) | H32: =IFERROR(E32*F32*(1-G32),0)
B33: =IF(A33="","",ROW()-3) | D33: =IFERROR(VLOOKUP(C33,Productos!A4:B103,2,FALSE),"") | F33: =IFERROR(VLOOKUP(C33,Productos!A4:E103,5,FALSE),0) | H33: =IFERROR(E33*F33*(1-G33),0)
B34: =IF(A34="","",ROW()-3) | D34: =IFERROR(VLOOKUP(C34,Productos!A4:B103,2,FALSE),"") | F34: =IFERROR(VLOOKUP(C34,Productos!A4:E103,5,FALSE),0) | H34: =IFERROR(E34*F34*(1-G34),0)
B35: =IF(A35="","",ROW()-3) | D35: =IFERROR(VLOOKUP(C35,Productos!A4:B103,2,FALSE),"") | F35: =IFERROR(VLOOKUP(C35,Productos!A4:E103,5,FALSE),0) | H35: =IFERROR(E35*F35*(1-G35),0)
B36: =IF(A36="","",ROW()-3) | D36: =IFERROR(VLOOKUP(C36,Productos!A4:B103,2,FALSE),"") | F36: =IFERROR(VLOOKUP(C36,Productos!A4:E103,5,FALSE),0) | H36: =IFERROR(E36*F36*(1-G36),0)
B37: =IF(A37="","",ROW()-3) | D37: =IFERROR(VLOOKUP(C37,Productos!A4:B103,2,FALSE),"") | F37: =IFERROR(VLOOKUP(C37,Productos!A4:E103,5,FALSE),0) | H37: =IFERROR(E37*F37*(1-G37),0)
B38: =IF(A38="","",ROW()-3) | D38: =IFERROR(VLOOKUP(C38,Productos!A4:B103,2,FALSE),"") | F38: =IFERROR(VLOOKUP(C38,Productos!A4:E103,5,FALSE),0) | H38: =IFERROR(E38*F38*(1-G38),0)
B39: =IF(A39="","",ROW()-3) | D39: =IFERROR(VLOOKUP(C39,Productos!A4:B103,2,FALSE),"") | F39: =IFERROR(VLOOKUP(C39,Productos!A4:E103,5,FALSE),0) | H39: =IFERROR(E39*F39*(1-G39),0)
B40: =IF(A40="","",ROW()-3) | D40: =IFERROR(VLOOKUP(C40,Productos!A4:B103,2,FALSE),"") | F40: =IFERROR(VLOOKUP(C40,Productos!A4:E103,5,FALSE),0) | H40: =IFERROR(E40*F40*(1-G40),0)
B41: =IF(A41="","",ROW()-3) | D41: =IFERROR(VLOOKUP(C41,Productos!A4:B103,2,FALSE),"") | F41: =IFERROR(VLOOKUP(C41,Productos!A4:E103,5,FALSE),0) | H41: =IFERROR(E41*F41*(1-G41),0)
B42: =IF(A42="","",ROW()-3) | D42: =IFERROR(VLOOKUP(C42,Productos!A4:B103,2,FALSE),"") | F42: =IFERROR(VLOOKUP(C42,Productos!A4:E103,5,FALSE),0) | H42: =IFERROR(E42*F42*(1-G42),0)
B43: =IF(A43="","",ROW()-3) | D43: =IFERROR(VLOOKUP(C43,Productos!A4:B103,2,FALSE),"") | F43: =IFERROR(VLOOKUP(C43,Productos!A4:E103,5,FALSE),0) | H43: =IFERROR(E43*F43*(1-G43),0)
B44: =IF(A44="","",ROW()-3) | D44: =IFERROR(VLOOKUP(C44,Productos!A4:B103,2,FALSE),"") | F44: =IFERROR(VLOOKUP(C44,Productos!A4:E103,5,FALSE),0) | H44: =IFERROR(E44*F44*(1-G44),0)
B45: =IF(A45="","",ROW()-3) | D45: =IFERROR(VLOOKUP(C45,Productos!A4:B103,2,FALSE),"") | F45: =IFERROR(VLOOKUP(C45,Productos!A4:E103,5,FALSE),0) | H45: =IFERROR(E45*F45*(1-G45),0)
B46: =IF(A46="","",ROW()-3) | D46: =IFERROR(VLOOKUP(C46,Productos!A4:B103,2,FALSE),"") | F46: =IFERROR(VLOOKUP(C46,Productos!A4:E103,5,FALSE),0) | H46: =IFERROR(E46*F46*(1-G46),0)
B47: =IF(A47="","",ROW()-3) | D47: =IFERROR(VLOOKUP(C47,Productos!A4:B103,2,FALSE),"") | F47: =IFERROR(VLOOKUP(C47,Productos!A4:E103,5,FALSE),0) | H47: =IFERROR(E47*F47*(1-G47),0)
B48: =IF(A48="","",ROW()-3) | D48: =IFERROR(VLOOKUP(C48,Productos!A4:B103,2,FALSE),"") | F48: =IFERROR(VLOOKUP(C48,Productos!A4:E103,5,FALSE),0) | H48: =IFERROR(E48*F48*(1-G48),0)
B49: =IF(A49="","",ROW()-3) | D49: =IFERROR(VLOOKUP(C49,Productos!A4:B103,2,FALSE),"") | F49: =IFERROR(VLOOKUP(C49,Productos!A4:E103,5,FALSE),0) | H49: =IFERROR(E49*F49*(1-G49),0)
B50: =IF(A50="","",ROW()-3) | D50: =IFERROR(VLOOKUP(C50,Productos!A4:B103,2,FALSE),"") | F50: =IFERROR(VLOOKUP(C50,Productos!A4:E103,5,FALSE),0) | H50: =IFERROR(E50*F50*(1-G50),0)
B51: =IF(A51="","",ROW()-3) | D51: =IFERROR(VLOOKUP(C51,Productos!A4:B103,2,FALSE),"") | F51: =IFERROR(VLOOKUP(C51,Productos!A4:E103,5,FALSE),0) | H51: =IFERROR(E51*F51*(1-G51),0)
B52: =IF(A52="","",ROW()-3) | D52: =IFERROR(VLOOKUP(C52,Productos!A4:B103,2,FALSE),"") | F52: =IFERROR(VLOOKUP(C52,Productos!A4:E103,5,FALSE),0) | H52: =IFERROR(E52*F52*(1-G52),0)
B53: =IF(A53="","",ROW()-3) | D53: =IFERROR(VLOOKUP(C53,Productos!A4:B103,2,FALSE),"") | F53: =IFERROR(VLOOKUP(C53,Productos!A4:E103,5,FALSE),0) | H53: =IFERROR(E53*F53*(1-G53),0)
B54: =IF(A54="","",ROW()-3) | D54: =IFERROR(VLOOKUP(C54,Productos!A4:B103,2,FALSE),"") | F54: =IFERROR(VLOOKUP(C54,Productos!A4:E103,5,FALSE),0) | H54: =IFERROR(E54*F54*(1-G54),0)
B55: =IF(A55="","",ROW()-3) | D55: =IFERROR(VLOOKUP(C55,Productos!A4:B103,2,FALSE),"") | F55: =IFERROR(VLOOKUP(C55,Productos!A4:E103,5,FALSE),0) | H55: =IFERROR(E55*F55*(1-G55),0)
B56: =IF(A56="","",ROW()-3) | D56: =IFERROR(VLOOKUP(C56,Productos!A4:B103,2,FALSE),"") | F56: =IFERROR(VLOOKUP(C56,Productos!A4:E103,5,FALSE),0) | H56: =IFERROR(E56*F56*(1-G56),0)
B57: =IF(A57="","",ROW()-3) | D57: =IFERROR(VLOOKUP(C57,Productos!A4:B103,2,FALSE),"") | F57: =IFERROR(VLOOKUP(C57,Productos!A4:E103,5,FALSE),0) | H57: =IFERROR(E57*F57*(1-G57),0)
B58: =IF(A58="","",ROW()-3) | D58: =IFERROR(VLOOKUP(C58,Productos!A4:B103,2,FALSE),"") | F58: =IFERROR(VLOOKUP(C58,Productos!A4:E103,5,FALSE),0) | H58: =IFERROR(E58*F58*(1-G58),0)
B59: =IF(A59="","",ROW()-3) | D59: =IFERROR(VLOOKUP(C59,Productos!A4:B103,2,FALSE),"") | F59: =IFERROR(VLOOKUP(C59,Productos!A4:E103,5,FALSE),0) | H59: =IFERROR(E59*F59*(1-G59),0)
B60: =IF(A60="","",ROW()-3) | D60: =IFERROR(VLOOKUP(C60,Productos!A4:B103,2,FALSE),"") | F60: =IFERROR(VLOOKUP(C60,Productos!A4:E103,5,FALSE),0) | H60: =IFERROR(E60*F60*(1-G60),0)
B61: =IF(A61="","",ROW()-3) | D61: =IFERROR(VLOOKUP(C61,Productos!A4:B103,2,FALSE),"") | F61: =IFERROR(VLOOKUP(C61,Productos!A4:E103,5,FALSE),0) | H61: =IFERROR(E61*F61*(1-G61),0)
B62: =IF(A62="","",ROW()-3) | D62: =IFERROR(VLOOKUP(C62,Productos!A4:B103,2,FALSE),"") | F62: =IFERROR(VLOOKUP(C62,Productos!A4:E103,5,FALSE),0) | H62: =IFERROR(E62*F62*(1-G62),0)
B63: =IF(A63="","",ROW()-3) | D63: =IFERROR(VLOOKUP(C63,Productos!A4:B103,2,FALSE),"") | F63: =IFERROR(VLOOKUP(C63,Productos!A4:E103,5,FALSE),0) | H63: =IFERROR(E63*F63*(1-G63),0)
B64: =IF(A64="","",ROW()-3) | D64: =IFERROR(VLOOKUP(C64,Productos!A4:B103,2,FALSE),"") | F64: =IFERROR(VLOOKUP(C64,Productos!A4:E103,5,FALSE),0) | H64: =IFERROR(E64*F64*(1-G64),0)
B65: =IF(A65="","",ROW()-3) | D65: =IFERROR(VLOOKUP(C65,Productos!A4:B103,2,FALSE),"") | F65: =IFERROR(VLOOKUP(C65,Productos!A4:E103,5,FALSE),0) | H65: =IFERROR(E65*F65*(1-G65),0)
B66: =IF(A66="","",ROW()-3) | D66: =IFERROR(VLOOKUP(C66,Productos!A4:B103,2,FALSE),"") | F66: =IFERROR(VLOOKUP(C66,Productos!A4:E103,5,FALSE),0) | H66: =IFERROR(E66*F66*(1-G66),0)
B67: =IF(A67="","",ROW()-3) | D67: =IFERROR(VLOOKUP(C67,Productos!A4:B103,2,FALSE),"") | F67: =IFERROR(VLOOKUP(C67,Productos!A4:E103,5,FALSE),0) | H67: =IFERROR(E67*F67*(1-G67),0)
B68: =IF(A68="","",ROW()-3) | D68: =IFERROR(VLOOKUP(C68,Productos!A4:B103,2,FALSE),"") | F68: =IFERROR(VLOOKUP(C68,Productos!A4:E103,5,FALSE),0) | H68: =IFERROR(E68*F68*(1-G68),0)
B69: =IF(A69="","",ROW()-3) | D69: =IFERROR(VLOOKUP(C69,Productos!A4:B103,2,FALSE),"") | F69: =IFERROR(VLOOKUP(C69,Productos!A4:E103,5,FALSE),0) | H69: =IFERROR(E69*F69*(1-G69),0)
B70: =IF(A70="","",ROW()-3) | D70: =IFERROR(VLOOKUP(C70,Productos!A4:B103,2,FALSE),"") | F70: =IFERROR(VLOOKUP(C70,Productos!A4:E103,5,FALSE),0) | H70: =IFERROR(E70*F70*(1-G70),0)
B71: =IF(A71="","",ROW()-3) | D71: =IFERROR(VLOOKUP(C71,Productos!A4:B103,2,FALSE),"") | F71: =IFERROR(VLOOKUP(C71,Productos!A4:E103,5,FALSE),0) | H71: =IFERROR(E71*F71*(1-G71),0)
B72: =IF(A72="","",ROW()-3) | D72: =IFERROR(VLOOKUP(C72,Productos!A4:B103,2,FALSE),"") | F72: =IFERROR(VLOOKUP(C72,Productos!A4:E103,5,FALSE),0) | H72: =IFERROR(E72*F72*(1-G72),0)
B73: =IF(A73="","",ROW()-3) | D73: =IFERROR(VLOOKUP(C73,Productos!A4:B103,2,FALSE),"") | F73: =IFERROR(VLOOKUP(C73,Productos!A4:E103,5,FALSE),0) | H73: =IFERROR(E73*F73*(1-G73),0)
B74: =IF(A74="","",ROW()-3) | D74: =IFERROR(VLOOKUP(C74,Productos!A4:B103,2,FALSE),"") | F74: =IFERROR(VLOOKUP(C74,Productos!A4:E103,5,FALSE),0) | H74: =IFERROR(E74*F74*(1-G74),0)
B75: =IF(A75="","",ROW()-3) | D75: =IFERROR(VLOOKUP(C75,Productos!A4:B103,2,FALSE),"") | F75: =IFERROR(VLOOKUP(C75,Productos!A4:E103,5,FALSE),0) | H75: =IFERROR(E75*F75*(1-G75),0)
B76: =IF(A76="","",ROW()-3) | D76: =IFERROR(VLOOKUP(C76,Productos!A4:B103,2,FALSE),"") | F76: =IFERROR(VLOOKUP(C76,Productos!A4:E103,5,FALSE),0) | H76: =IFERROR(E76*F76*(1-G76),0)
B77: =IF(A77="","",ROW()-3) | D77: =IFERROR(VLOOKUP(C77,Productos!A4:B103,2,FALSE),"") | F77: =IFERROR(VLOOKUP(C77,Productos!A4:E103,5,FALSE),0) | H77: =IFERROR(E77*F77*(1-G77),0)
B78: =IF(A78="","",ROW()-3) | D78: =IFERROR(VLOOKUP(C78,Productos!A4:B103,2,FALSE),"") | F78: =IFERROR(VLOOKUP(C78,Productos!A4:E103,5,FALSE),0) | H78: =IFERROR(E78*F78*(1-G78),0)
B79: =IF(A79="","",ROW()-3) | D79: =IFERROR(VLOOKUP(C79,Productos!A4:B103,2,FALSE),"") | F79: =IFERROR(VLOOKUP(C79,Productos!A4:E103,5,FALSE),0) | H79: =IFERROR(E79*F79*(1-G79),0)
B80: =IF(A80="","",ROW()-3) | D80: =IFERROR(VLOOKUP(C80,Productos!A4:B103,2,FALSE),"") | F80: =IFERROR(VLOOKUP(C80,Productos!A4:E103,5,FALSE),0) | H80: =IFERROR(E80*F80*(1-G80),0)
B81: =IF(A81="","",ROW()-3) | D81: =IFERROR(VLOOKUP(C81,Productos!A4:B103,2,FALSE),"") | F81: =IFERROR(VLOOKUP(C81,Productos!A4:E103,5,FALSE),0) | H81: =IFERROR(E81*F81*(1-G81),0)
B82: =IF(A82="","",ROW()-3) | D82: =IFERROR(VLOOKUP(C82,Productos!A4:B103,2,FALSE),"") | F82: =IFERROR(VLOOKUP(C82,Productos!A4:E103,5,FALSE),0) | H82: =IFERROR(E82*F82*(1-G82),0)
B83: =IF(A83="","",ROW()-3) | D83: =IFERROR(VLOOKUP(C83,Productos!A4:B103,2,FALSE),"") | F83: =IFERROR(VLOOKUP(C83,Productos!A4:E103,5,FALSE),0) | H83: =IFERROR(E83*F83*(1-G83),0)
B84: =IF(A84="","",ROW()-3) | D84: =IFERROR(VLOOKUP(C84,Productos!A4:B103,2,FALSE),"") | F84: =IFERROR(VLOOKUP(C84,Productos!A4:E103,5,FALSE),0) | H84: =IFERROR(E84*F84*(1-G84),0)
B85: =IF(A85="","",ROW()-3) | D85: =IFERROR(VLOOKUP(C85,Productos!A4:B103,2,FALSE),"") | F85: =IFERROR(VLOOKUP(C85,Productos!A4:E103,5,FALSE),0) | H85: =IFERROR(E85*F85*(1-G85),0)
B86: =IF(A86="","",ROW()-3) | D86: =IFERROR(VLOOKUP(C86,Productos!A4:B103,2,FALSE),"") | F86: =IFERROR(VLOOKUP(C86,Productos!A4:E103,5,FALSE),0) | H86: =IFERROR(E86*F86*(1-G86),0)
B87: =IF(A87="","",ROW()-3) | D87: =IFERROR(VLOOKUP(C87,Productos!A4:B103,2,FALSE),"") | F87: =IFERROR(VLOOKUP(C87,Productos!A4:E103,5,FALSE),0) | H87: =IFERROR(E87*F87*(1-G87),0)
B88: =IF(A88="","",ROW()-3) | D88: =IFERROR(VLOOKUP(C88,Productos!A4:B103,2,FALSE),"") | F88: =IFERROR(VLOOKUP(C88,Productos!A4:E103,5,FALSE),0) | H88: =IFERROR(E88*F88*(1-G88),0)
B89: =IF(A89="","",ROW()-3) | D89: =IFERROR(VLOOKUP(C89,Productos!A4:B103,2,FALSE),"") | F89: =IFERROR(VLOOKUP(C89,Productos!A4:E103,5,FALSE),0) | H89: =IFERROR(E89*F89*(1-G89),0)
B90: =IF(A90="","",ROW()-3) | D90: =IFERROR(VLOOKUP(C90,Productos!A4:B103,2,FALSE),"") | F90: =IFERROR(VLOOKUP(C90,Productos!A4:E103,5,FALSE),0) | H90: =IFERROR(E90*F90*(1-G90),0)
B91: =IF(A91="","",ROW()-3) | D91: =IFERROR(VLOOKUP(C91,Productos!A4:B103,2,FALSE),"") | F91: =IFERROR(VLOOKUP(C91,Productos!A4:E103,5,FALSE),0) | H91: =IFERROR(E91*F91*(1-G91),0)
B92: =IF(A92="","",ROW()-3) | D92: =IFERROR(VLOOKUP(C92,Productos!A4:B103,2,FALSE),"") | F92: =IFERROR(VLOOKUP(C92,Productos!A4:E103,5,FALSE),0) | H92: =IFERROR(E92*F92*(1-G92),0)
B93: =IF(A93="","",ROW()-3) | D93: =IFERROR(VLOOKUP(C93,Productos!A4:B103,2,FALSE),"") | F93: =IFERROR(VLOOKUP(C93,Productos!A4:E103,5,FALSE),0) | H93: =IFERROR(E93*F93*(1-G93),0)
B94: =IF(A94="","",ROW()-3) | D94: =IFERROR(VLOOKUP(C94,Productos!A4:B103,2,FALSE),"") | F94: =IFERROR(VLOOKUP(C94,Productos!A4:E103,5,FALSE),0) | H94: =IFERROR(E94*F94*(1-G94),0)
B95: =IF(A95="","",ROW()-3) | D95: =IFERROR(VLOOKUP(C95,Productos!A4:B103,2,FALSE),"") | F95: =IFERROR(VLOOKUP(C95,Productos!A4:E103,5,FALSE),0) | H95: =IFERROR(E95*F95*(1-G95),0)
B96: =IF(A96="","",ROW()-3) | D96: =IFERROR(VLOOKUP(C96,Productos!A4:B103,2,FALSE),"") | F96: =IFERROR(VLOOKUP(C96,Productos!A4:E103,5,FALSE),0) | H96: =IFERROR(E96*F96*(1-G96),0)
B97: =IF(A97="","",ROW()-3) | D97: =IFERROR(VLOOKUP(C97,Productos!A4:B103,2,FALSE),"") | F97: =IFERROR(VLOOKUP(C97,Productos!A4:E103,5,FALSE),0) | H97: =IFERROR(E97*F97*(1-G97),0)
B98: =IF(A98="","",ROW()-3) | D98: =IFERROR(VLOOKUP(C98,Productos!A4:B103,2,FALSE),"") | F98: =IFERROR(VLOOKUP(C98,Productos!A4:E103,5,FALSE),0) | H98: =IFERROR(E98*F98*(1-G98),0)
B99: =IF(A99="","",ROW()-3) | D99: =IFERROR(VLOOKUP(C99,Productos!A4:B103,2,FALSE),"") | F99: =IFERROR(VLOOKUP(C99,Productos!A4:E103,5,FALSE),0) | H99: =IFERROR(E99*F99*(1-G99),0)
B100: =IF(A100="","",ROW()-3) | D100: =IFERROR(VLOOKUP(C100,Productos!A4:B103,2,FALSE),"") | F100: =IFERROR(VLOOKUP(C100,Productos!A4:E103,5,FALSE),0) | H100: =IFERROR(E100*F100*(1-G100),0)
...

Sheet Inventario
A1: MOVIMIENTOS DE INVENTARIO
A2: Registra entradas y salidas de inventario. Tipo: ENTRADA = compras/reposición, SALIDA = ajustes/pérdidas.
A3: FECHA | B3: CÓDIGO PROD. | C3: PRODUCTO (auto) | D3: TIPO | E3: CANTIDAD | F3: COSTO UNIT. | G3: TOTAL MOVIMIENTO | H3: OBSERVACIÓN
C4: =IFERROR(VLOOKUP(B4,Productos!A4:B103,2,FALSE),"") | G4: =IFERROR(E4*F4,0)
C5: =IFERROR(VLOOKUP(B5,Productos!A4:B103,2,FALSE),"") | G5: =IFERROR(E5*F5,0)
C6: =IFERROR(VLOOKUP(B6,Productos!A4:B103,2,FALSE),"") | G6: =IFERROR(E6*F6,0)
C7: =IFERROR(VLOOKUP(B7,Productos!A4:B103,2,FALSE),"") | G7: =IFERROR(E7*F7,0)
C8: =IFERROR(VLOOKUP(B8,Productos!A4:B103,2,FALSE),"") | G8: =IFERROR(E8*F8,0)
C9: =IFERROR(VLOOKUP(B9,Productos!A4:B103,2,FALSE),"") | G9: =IFERROR(E9*F9,0)
C10: =IFERROR(VLOOKUP(B10,Productos!A4:B103,2,FALSE),"") | G10: =IFERROR(E10*F10,0)
C11: =IFERROR(VLOOKUP(B11,Productos!A4:B103,2,FALSE),"") | G11: =IFERROR(E11*F11,0)
C12: =IFERROR(VLOOKUP(B12,Productos!A4:B103,2,FALSE),"") | G12: =IFERROR(E12*F12,0)
C13: =IFERROR(VLOOKUP(B13,Productos!A4:B103,2,FALSE),"") | G13: =IFERROR(E13*F13,0)
C14: =IFERROR(VLOOKUP(B14,Productos!A4:B103,2,FALSE),"") | G14: =IFERROR(E14*F14,0)
C15: =IFERROR(VLOOKUP(B15,Productos!A4:B103,2,FALSE),"") | G15: =IFERROR(E15*F15,0)
C16: =IFERROR(VLOOKUP(B16,Productos!A4:B103,2,FALSE),"") | G16: =IFERROR(E16*F16,0)
C17: =IFERROR(VLOOKUP(B17,Productos!A4:B103,2,FALSE),"") | G17: =IFERROR(E17*F17,0)
C18: =IFERROR(VLOOKUP(B18,Productos!A4:B103,2,FALSE),"") | G18: =IFERROR(E18*F18,0)
C19: =IFERROR(VLOOKUP(B19,Productos!A4:B103,2,FALSE),"") | G19: =IFERROR(E19*F19,0)
C20: =IFERROR(VLOOKUP(B20,Productos!A4:B103,2,FALSE),"") | G20: =IFERROR(E20*F20,0)
C21: =IFERROR(VLOOKUP(B21,Productos!A4:B103,2,FALSE),"") | G21: =IFERROR(E21*F21,0)
C22: =IFERROR(VLOOKUP(B22,Productos!A4:B103,2,FALSE),"") | G22: =IFERROR(E22*F22,0)
C23: =IFERROR(VLOOKUP(B23,Productos!A4:B103,2,FALSE),"") | G23: =IFERROR(E23*F23,0)
C24: =IFERROR(VLOOKUP(B24,Productos!A4:B103,2,FALSE),"") | G24: =IFERROR(E24*F24,0)
C25: =IFERROR(VLOOKUP(B25,Productos!A4:B103,2,FALSE),"") | G25: =IFERROR(E25*F25,0)
C26: =IFERROR(VLOOKUP(B26,Productos!A4:B103,2,FALSE),"") | G26: =IFERROR(E26*F26,0)
C27: =IFERROR(VLOOKUP(B27,Productos!A4:B103,2,FALSE),"") | G27: =IFERROR(E27*F27,0)
C28: =IFERROR(VLOOKUP(B28,Productos!A4:B103,2,FALSE),"") | G28: =IFERROR(E28*F28,0)
C29: =IFERROR(VLOOKUP(B29,Productos!A4:B103,2,FALSE),"") | G29: =IFERROR(E29*F29,0)
C30: =IFERROR(VLOOKUP(B30,Productos!A4:B103,2,FALSE),"") | G30: =IFERROR(E30*F30,0)
C31: =IFERROR(VLOOKUP(B31,Productos!A4:B103,2,FALSE),"") | G31: =IFERROR(E31*F31,0)
C32: =IFERROR(VLOOKUP(B32,Productos!A4:B103,2,FALSE),"") | G32: =IFERROR(E32*F32,0)
C33: =IFERROR(VLOOKUP(B33,Productos!A4:B103,2,FALSE),"") | G33: =IFERROR(E33*F33,0)
C34: =IFERROR(VLOOKUP(B34,Productos!A4:B103,2,FALSE),"") | G34: =IFERROR(E34*F34,0)
C35: =IFERROR(VLOOKUP(B35,Productos!A4:B103,2,FALSE),"") | G35: =IFERROR(E35*F35,0)
C36: =IFERROR(VLOOKUP(B36,Productos!A4:B103,2,FALSE),"") | G36: =IFERROR(E36*F36,0)
C37: =IFERROR(VLOOKUP(B37,Productos!A4:B103,2,FALSE),"") | G37: =IFERROR(E37*F37,0)
C38: =IFERROR(VLOOKUP(B38,Productos!A4:B103,2,FALSE),"") | G38: =IFERROR(E38*F38,0)
C39: =IFERROR(VLOOKUP(B39,Productos!A4:B103,2,FALSE),"") | G39: =IFERROR(E39*F39,0)
C40: =IFERROR(VLOOKUP(B40,Productos!A4:B103,2,FALSE),"") | G40: =IFERROR(E40*F40,0)
C41: =IFERROR(VLOOKUP(B41,Productos!A4:B103,2,FALSE),"") | G41: =IFERROR(E41*F41,0)
C42: =IFERROR(VLOOKUP(B42,Productos!A4:B103,2,FALSE),"") | G42: =IFERROR(E42*F42,0)
C43: =IFERROR(VLOOKUP(B43,Productos!A4:B103,2,FALSE),"") | G43: =IFERROR(E43*F43,0)
C44: =IFERROR(VLOOKUP(B44,Productos!A4:B103,2,FALSE),"") | G44: =IFERROR(E44*F44,0)
C45: =IFERROR(VLOOKUP(B45,Productos!A4:B103,2,FALSE),"") | G45: =IFERROR(E45*F45,0)
C46: =IFERROR(VLOOKUP(B46,Productos!A4:B103,2,FALSE),"") | G46: =IFERROR(E46*F46,0)
C47: =IFERROR(VLOOKUP(B47,Productos!A4:B103,2,FALSE),"") | G47: =IFERROR(E47*F47,0)
C48: =IFERROR(VLOOKUP(B48,Productos!A4:B103,2,FALSE),"") | G48: =IFERROR(E48*F48,0)
C49: =IFERROR(VLOOKUP(B49,Productos!A4:B103,2,FALSE),"") | G49: =IFERROR(E49*F49,0)
C50: =IFERROR(VLOOKUP(B50,Productos!A4:B103,2,FALSE),"") | G50: =IFERROR(E50*F50,0)
C51: =IFERROR(VLOOKUP(B51,Productos!A4:B103,2,FALSE),"") | G51: =IFERROR(E51*F51,0)
C52: =IFERROR(VLOOKUP(B52,Productos!A4:B103,2,FALSE),"") | G52: =IFERROR(E52*F52,0)
C53: =IFERROR(VLOOKUP(B53,Productos!A4:B103,2,FALSE),"") | G53: =IFERROR(E53*F53,0)
C54: =IFERROR(VLOOKUP(B54,Productos!A4:B103,2,FALSE),"") | G54: =IFERROR(E54*F54,0)
C55: =IFERROR(VLOOKUP(B55,Productos!A4:B103,2,FALSE),"") | G55: =IFERROR(E55*F55,0)
C56: =IFERROR(VLOOKUP(B56,Productos!A4:B103,2,FALSE),"") | G56: =IFERROR(E56*F56,0)
C57: =IFERROR(VLOOKUP(B57,Productos!A4:B103,2,FALSE),"") | G57: =IFERROR(E57*F57,0)
C58: =IFERROR(VLOOKUP(B58,Productos!A4:B103,2,FALSE),"") | G58: =IFERROR(E58*F58,0)
C59: =IFERROR(VLOOKUP(B59,Productos!A4:B103,2,FALSE),"") | G59: =IFERROR(E59*F59,0)
C60: =IFERROR(VLOOKUP(B60,Productos!A4:B103,2,FALSE),"") | G60: =IFERROR(E60*F60,0)
C61: =IFERROR(VLOOKUP(B61,Productos!A4:B103,2,FALSE),"") | G61: =IFERROR(E61*F61,0)
C62: =IFERROR(VLOOKUP(B62,Productos!A4:B103,2,FALSE),"") | G62: =IFERROR(E62*F62,0)
C63: =IFERROR(VLOOKUP(B63,Productos!A4:B103,2,FALSE),"") | G63: =IFERROR(E63*F63,0)
C64: =IFERROR(VLOOKUP(B64,Productos!A4:B103,2,FALSE),"") | G64: =IFERROR(E64*F64,0)
C65: =IFERROR(VLOOKUP(B65,Productos!A4:B103,2,FALSE),"") | G65: =IFERROR(E65*F65,0)
C66: =IFERROR(VLOOKUP(B66,Productos!A4:B103,2,FALSE),"") | G66: =IFERROR(E66*F66,0)
C67: =IFERROR(VLOOKUP(B67,Productos!A4:B103,2,FALSE),"") | G67: =IFERROR(E67*F67,0)
C68: =IFERROR(VLOOKUP(B68,Productos!A4:B103,2,FALSE),"") | G68: =IFERROR(E68*F68,0)
C69: =IFERROR(VLOOKUP(B69,Productos!A4:B103,2,FALSE),"") | G69: =IFERROR(E69*F69,0)
C70: =IFERROR(VLOOKUP(B70,Productos!A4:B103,2,FALSE),"") | G70: =IFERROR(E70*F70,0)
C71: =IFERROR(VLOOKUP(B71,Productos!A4:B103,2,FALSE),"") | G71: =IFERROR(E71*F71,0)
C72: =IFERROR(VLOOKUP(B72,Productos!A4:B103,2,FALSE),"") | G72: =IFERROR(E72*F72,0)
C73: =IFERROR(VLOOKUP(B73,Productos!A4:B103,2,FALSE),"") | G73: =IFERROR(E73*F73,0)
C74: =IFERROR(VLOOKUP(B74,Productos!A4:B103,2,FALSE),"") | G74: =IFERROR(E74*F74,0)
C75: =IFERROR(VLOOKUP(B75,Productos!A4:B103,2,FALSE),"") | G75: =IFERROR(E75*F75,0)
C76: =IFERROR(VLOOKUP(B76,Productos!A4:B103,2,FALSE),"") | G76: =IFERROR(E76*F76,0)
C77: =IFERROR(VLOOKUP(B77,Productos!A4:B103,2,FALSE),"") | G77: =IFERROR(E77*F77,0)
C78: =IFERROR(VLOOKUP(B78,Productos!A4:B103,2,FALSE),"") | G78: =IFERROR(E78*F78,0)
C79: =IFERROR(VLOOKUP(B79,Productos!A4:B103,2,FALSE),"") | G79: =IFERROR(E79*F79,0)
C80: =IFERROR(VLOOKUP(B80,Productos!A4:B103,2,FALSE),"") | G80: =IFERROR(E80*F80,0)
C81: =IFERROR(VLOOKUP(B81,Productos!A4:B103,2,FALSE),"") | G81: =IFERROR(E81*F81,0)
C82: =IFERROR(VLOOKUP(B82,Productos!A4:B103,2,FALSE),"") | G82: =IFERROR(E82*F82,0)
C83: =IFERROR(VLOOKUP(B83,Productos!A4:B103,2,FALSE),"") | G83: =IFERROR(E83*F83,0)
C84: =IFERROR(VLOOKUP(B84,Productos!A4:B103,2,FALSE),"") | G84: =IFERROR(E84*F84,0)
C85: =IFERROR(VLOOKUP(B85,Productos!A4:B103,2,FALSE),"") | G85: =IFERROR(E85*F85,0)
C86: =IFERROR(VLOOKUP(B86,Productos!A4:B103,2,FALSE),"") | G86: =IFERROR(E86*F86,0)
C87: =IFERROR(VLOOKUP(B87,Productos!A4:B103,2,FALSE),"") | G87: =IFERROR(E87*F87,0)
C88: =IFERROR(VLOOKUP(B88,Productos!A4:B103,2,FALSE),"") | G88: =IFERROR(E88*F88,0)
C89: =IFERROR(VLOOKUP(B89,Productos!A4:B103,2,FALSE),"") | G89: =IFERROR(E89*F89,0)
C90: =IFERROR(VLOOKUP(B90,Productos!A4:B103,2,FALSE),"") | G90: =IFERROR(E90*F90,0)
C91: =IFERROR(VLOOKUP(B91,Productos!A4:B103,2,FALSE),"") | G91: =IFERROR(E91*F91,0)
C92: =IFERROR(VLOOKUP(B92,Productos!A4:B103,2,FALSE),"") | G92: =IFERROR(E92*F92,0)
C93: =IFERROR(VLOOKUP(B93,Productos!A4:B103,2,FALSE),"") | G93: =IFERROR(E93*F93,0)
C94: =IFERROR(VLOOKUP(B94,Productos!A4:B103,2,FALSE),"") | G94: =IFERROR(E94*F94,0)
C95: =IFERROR(VLOOKUP(B95,Productos!A4:B103,2,FALSE),"") | G95: =IFERROR(E95*F95,0)
C96: =IFERROR(VLOOKUP(B96,Productos!A4:B103,2,FALSE),"") | G96: =IFERROR(E96*F96,0)
C97: =IFERROR(VLOOKUP(B97,Productos!A4:B103,2,FALSE),"") | G97: =IFERROR(E97*F97,0)
C98: =IFERROR(VLOOKUP(B98,Productos!A4:B103,2,FALSE),"") | G98: =IFERROR(E98*F98,0)
C99: =IFERROR(VLOOKUP(B99,Productos!A4:B103,2,FALSE),"") | G99: =IFERROR(E99*F99,0)
C100: =IFERROR(VLOOKUP(B100,Productos!A4:B103,2,FALSE),"") | G100: =IFERROR(E100*F100,0)
...

Sheet Reportes
B2: REPORTES DE VENTAS
B4: VENTAS POR CATEGORÍA | G4: VENTAS POR VENDEDOR
B5: Categoría | C5: Ventas (Bs.) | D5: % del Total | G5: Vendedor | H5: Ventas (Bs.) | I5: # Transacciones
B6: Alimentos | C6: =IFERROR(SUMPRODUCT((VLOOKUP(Ventas!C4:C203,Productos!A4:C103,3,FALSE)="Alimentos")*Ventas!H4:H203),0) | D6: =IFERROR(C6/SUM(C6:C11),0) | G6: Ana | H6: =IFERROR(SUMPRODUCT((Ventas!J4:J203="Ana")*Ventas!H4:H203),0) | I6: =COUNTIF(Ventas!J4:J203,"Ana")
B7: Bebidas | C7: =IFERROR(SUMPRODUCT((VLOOKUP(Ventas!C4:C203,Productos!A4:C103,3,FALSE)="Bebidas")*Ventas!H4:H203),0) | D7: =IFERROR(C7/SUM(C6:C11),0) | G7: Carlos | H7: =IFERROR(SUMPRODUCT((Ventas!J4:J203="Carlos")*Ventas!H4:H203),0) | I7: =COUNTIF(Ventas!J4:J203,"Carlos")
B8: Limpieza | C8: =IFERROR(SUMPRODUCT((VLOOKUP(Ventas!C4:C203,Productos!A4:C103,3,FALSE)="Limpieza")*Ventas!H4:H203),0) | D8: =IFERROR(C8/SUM(C6:C11),0) | G8: María | H8: =IFERROR(SUMPRODUCT((Ventas!J4:J203="María")*Ventas!H4:H203),0) | I8: =COUNTIF(Ventas!J4:J203,"María")
B9: Electrónica | C9: =IFERROR(SUMPRODUCT((VLOOKUP(Ventas!C4:C203,Productos!A4:C103,3,FALSE)="Electrónica")*Ventas!H4:H203),0) | D9: =IFERROR(C9/SUM(C6:C11),0) | G9: Pedro | H9: =IFERROR(SUMPRODUCT((Ventas!J4:J203="Pedro")*Ventas!H4:H203),0) | I9: =COUNTIF(Ventas!J4:J203,"Pedro")
B10: Ropa | C10: =IFERROR(SUMPRODUCT((VLOOKUP(Ventas!C4:C203,Productos!A4:C103,3,FALSE)="Ropa")*Ventas!H4:H203),0) | D10: =IFERROR(C10/SUM(C6:C11),0) | G10: Lucía | H10: =IFERROR(SUMPRODUCT((Ventas!J4:J203="Lucía")*Ventas!H4:H203),0) | I10: =COUNTIF(Ventas!J4:J203,"Lucía")
B11: Otros | C11: =IFERROR(SUMPRODUCT((VLOOKUP(Ventas!C4:C203,Productos!A4:C103,3,FALSE)="Otros")*Ventas!H4:H203),0) | D11: =IFERROR(C11/SUM(C6:C11),0)
B12: TOTAL | C12: =SUM(C6:C11)

Sheet Config
A1: v1.0.0
A3: CONFIGURACIÓN
A5: Producto | B5: Sistema de Ventas con Código Único
A6: Versión | B6: v1.0.0
A7: Marca | B7: No Somos Ignorantes
A8: Precio | B8: Bs. 89
A9: Protección | B9: nsi2024
A11: INSTRUCCIONES
A12: 1. | B12: Las celdas AMARILLAS son editables — ingresa tus datos ahí.
A13: 2. | B13: Las celdas VERDES se calculan automáticamente — no las modifiques.
A14: 3. | B14: En la hoja 'Productos', registra tus productos con nombre, costo y precio.
A15: 4. | B15: El CÓDIGO se genera automáticamente (PROD-0001, PROD-0002, etc.).
A16: 5. | B16: En la hoja 'Ventas', ingresa el código del producto y la cantidad.
A17: 6. | B17: El nombre y precio se llenan solos con VLOOKUP.
A18: 7. | B18: El Dashboard muestra KPIs, gráficos y alertas en tiempo real.
A19: 8. | B19: Para desbloquear una hoja: Revisar → Desproteger hoja → nsi2024
